Workbook
Name datos: #REF!
Name datos: #REF!
Name datos: #REF!
Name errores: #REF!
Name errores: #REF!
Name errores: #REF!

Sheet BD Centrales 2025
A1: ID Central infotécnica | B1: Nemotécnico Central Infotécnica | C1: Nombre Central Infotécnica | D1: Coordinado | E1: RUT Coordinado | F1: Propietario | G1: N° Centrales del coordinado | H1: POI | I1: POI CMg | J1: BARRA_TRANSF | K1: Cantidad de unidades | L1: Año | M1: Tipo de central | N1: Tipo tecnología | O1: Medio de generación | P1: Región | Q1: Provincia | R1: Comuna | S1: Estado | T1: Fecha EO | U1: Potencia máxima bruta Central [MW] | V1: Potencia máxima neta Central [MW] | W1: Inyección energía [GWh] | X1: Retiros energía Bloque A [MWh] | Y1: Retiros energía Bloque B [MWh] | Z1: Retiros energía Bloque C [MWh] | AA1: Retiros energía Total 2025 [MWh] | AB1: CMg precio captura | AC1: CMg promedio horario | AD1: CMg promedio solar | AE1: CMg promedio noche | AF1: Porcentaje iny. costo cero | AG1: Pagos laterales | AH1: Ingresos Energía Coordinado (Balance) | AI1: Ingresos Potencia Coordinado | AJ1: Ingresos SSCC Coordinado | AK1: PPA mínimo | AL1: Ingresos Estimados PPA | AM1: Ingresos energía (balance + PPA) | AN1: Ingresos Totales [USD/MWh]
A2: 0 | B2: CE05G0265 | C2: PFV MALGARIDA | D2: ACCIONA ENERGÍA CHILE HOLDINGS S.A. | E2: =_xlfn.XLOOKUP(D2,'[2]Coordinados SEN'!$A:$A,'[2]Coordinados SEN'!$B:$B,"-",0) -> 76.437.712-5 | F2: ACCIONA ENERGÍA CHILE HOLDINGS S.A. | G2: =COUNTIFS($D$2:$D$1194,D2) -> 6 | H2: ID2284-S/E MALGARIDA | I2: S/E MALGARIDA 220KV | J2: =_xlfn.XLOOKUP(I2,'[2]Barras CMg'!$E$2:$E$1527,'[2]Barras CMg'!$A$2:$A$1527,"------",0,1) -> MALGARIDA_____220 | K2: 1 | L2: 2025 | M2: Fotovoltaica | N2: Parque fotovoltaico | O2: Instalaciones de generación | P2: Atacama | Q2: Chañaral | R2: Diego de Almagro | S2: Operativa | T2: 19-06-2021 | U2: 204.32 | V2: 200.68 | W2: =_xlfn.XLOOKUP(C2,#REF!,#REF!,"S/I",0) -> #REF! | X2: =_xlfn.XLOOKUP($D2,[2]Retiros_dinamica!$F:$F,[2]Retiros_dinamica!B:B,"S/I",0) -> 448325.71 | Y2: =_xlfn.XLOOKUP($D2,[2]Retiros_dinamica!$F:$F,[2]Retiros_dinamica!C:C,"S/I",0) -> 508026.01 | Z2: =_xlfn.XLOOKUP($D2,[2]Retiros_dinamica!$F:$F,[2]Retiros_dinamica!D:D,"S/I",0) -> 259394.42 | AA2: =_xlfn.XLOOKUP($D2,[2]Retiros_dinamica!$F:$F,[2]Retiros_dinamica!E:E,"S/I",0) -> 1215746.1 | AB2: =_xlfn.XLOOKUP(C2,[2]CMg!$I$4:$I$106,[2]CMg!$M$4:$M$106,"----",0,1) -> 7.4844658 | AC2: =_xlfn.XLOOKUP(C2,'[3]Promedio Cmg'!$A$4:$A$106,'[3]Promedio Cmg'!$B$4:$B$106,"---",0,1) -> 48.996233 | AD2: =_xlfn.XLOOKUP(C2,'[3]Promedio solar Cmg'!$A$4:$A$106,'[3]Promedio solar Cmg'!$B$4:$B$106,"----",0,1) -> 9.320074 | AE2: =_xlfn.XLOOKUP(C2,[2]CMg!$O$4:$O$106,[2]CMg!$P$4:$P$106,"----",0,1) -> 77.330802 | AF2: =_xlfn.XLOOKUP(C2,[2]CMg!$S$4:$S$106,[2]CMg!$U$4:$U$106,"----",0,1) -> 0.46124872 | AH2: =_xlfn.XLOOKUP($E2,'[2]Balance económico'!$C:$C,'[2]Balance económico'!$D:$D,"-",0) -> -6.7605287e+10 | AI2: =_xlfn.XLOOKUP($E2,'[2]Balance económico'!$C:$C,'[2]Balance económico'!$E:$E,"-",0) -> -1.1939622e+10 | AJ2: =_xlfn.XLOOKUP($E2,'[2]Balance económico'!$C:$C,'[2]Balance económico'!$F:$F,"-",0) -> 4.7816583e+09 | AK2: =IF(AA2>0,"PPA","-") -> PPA | AL2: {=IFERROR((X2*[2]!Tabla2[Bloque A] + 'BD Centrales 2025'!Y934*[2]!Tabla2[Bloque B] + 'BD Centrales 2025'!Z934*[2]!Tabla2[Bloque C])*#REF!,"-")} -> - | AM2: =IFERROR(AH2+AL2,"-") -> - | AN2: =IFERROR((AH2+AI2+AJ2)/(SUMIFS($W$2:$W$1194,$E$2:$E$1194,E2)*1000*#REF!),0) -> 0
A3: 2 | B3: CE06G0035 | C3: TER MAULE | D3: ELEKTRA GENERACIÓN S.A. | E3: =_xlfn.XLOOKUP(D3,'[2]Coordinados SEN'!$A:$A,'[2]Coordinados SEN'!$B:$B,"-",0) -> 76.594.660-3 | F3: ELEKTRA GENERACIÓN S.A. | G3: =COUNTIFS($D$2:$D$1194,D3) -> 5 | H3: S/E CONSTITUCION 23KV | I3: S/E CONSTITUCION 23KV | J3: =_xlfn.XLOOKUP(I3,'[2]Barras CMg'!$E$2:$E$1527,'[2]Barras CMg'!$A$2:$A$1527,"------",0,1) -> CONSTIT1______023 | K3: 6 | L3: 2025 | M3: Termoeléctrica | N3: Motor de combustión interna | O3: Pequeños medio de generación o PMG | P3: Maule | Q3: Talca | R3: Constitución | S3: Operativa | T3: 07-06-2007 | U3: 6.099 | V3: 5.959 | W3: =_xlfn.XLOOKUP(C3,#REF!,#REF!,"S/I",0) -> #REF! | X3: =_xlfn.XLOOKUP($D3,[2]Retiros_dinamica!$F:$F,[2]Retiros_dinamica!B:B,"S/I",0) -> S/I | Y3: =_xlfn.XLOOKUP($D3,[2]Retiros_dinamica!$F:$F,[2]Retiros_dinamica!C:C,"S/I",0) -> S/I | Z3: =_xlfn.XLOOKUP($D3,[2]Retiros_dinamica!$F:$F,[2]Retiros_dinamica!D:D,"S/I",0) -> S/I | AA3: =_xlfn.XLOOKUP($D3,[2]Retiros_dinamica!$F:$F,[2]Retiros_dinamica!E:E,"S/I",0) -> S/I | AB3: =_xlfn.XLOOKUP(C3,[2]CMg!$I$4:$I$106,[2]CMg!$M$4:$M$106,"----",0,1) -> ---- | AH3: =_xlfn.XLOOKUP($E3,'[2]Balance económico'!$C:$C,'[2]Balance económico'!$D:$D,"-",0) -> 1.0058747e+09 | AI3: =_xlfn.XLOOKUP($E3,'[2]Balance económico'!$C:$C,'[2]Balance económico'!$E:$E,"-",0) -> 2.3067282e+09 | AJ3: =_xlfn.XLOOKUP($E3,'[2]Balance económico'!$C:$C,'[2]Balance económico'!$F:$F,"-",0) -> ---- | AK3: =IF(AA3>0,"PPA","-") -> PPA | AL3: {=IFERROR((X3*[2]!Tabla2[Bloque A] + 'BD Centrales 2025'!Y1143*[2]!Tabla2[Bloque B] + 'BD Centrales 2025'!Z1143*[2]!Tabla2[Bloque C])*#REF!,"-")} -> - | AM3: =IFERROR(AH3+AL3,"-") -> - | AN3: =IFERROR((AH3+AI3+AJ3)/(SUMIFS($W$2:$W$1194,$E$2:$E$1194,E3)*1000*#REF!),0) -> 0
A4: 3 | B4: CE05G0035 | C4: TER CHILOE | D4: ELEKTRA GENERACIÓN S.A. | E4: =_xlfn.XLOOKUP(D4,'[2]Coordinados SEN'!$A:$A,'[2]Coordinados SEN'!$B:$B,"-",0) -> 76.594.660-3 | F4: ELEKTRA GENERACIÓN S.A. | G4: =COUNTIFS($D$2:$D$1194,D4) -> 5 | H4: S/E QUELLON 23KV | I4: S/E QUELLON 110KV | J4: =_xlfn.XLOOKUP(I4,'[2]Barras CMg'!$E$2:$E$1527,'[2]Barras CMg'!$A$2:$A$1527,"------",0,1) -> QUELLON_______110 | K4: 9 | L4: 2025 | M4: Termoeléctrica | N4: Motor de combustión interna | O4: Pequeños medio de generación o PMG | P4: Los Lagos | Q4: Chiloé | R4: Quellón | S4: Operativa | T4: 16-07-2008 | U4: 9.227 | V4: 9.056 | W4: =_xlfn.XLOOKUP(C4,#REF!,#REF!,"S/I",0) -> #REF! | X4: =_xlfn.XLOOKUP($D4,[2]Retiros_dinamica!$F:$F,[2]Retiros_dinamica!B:B,"S/I",0) -> S/I | Y4: =_xlfn.XLOOKUP($D4,[2]Retiros_dinamica!$F:$F,[2]Retiros_dinamica!C:C,"S/I",0) -> S/I | Z4: =_xlfn.XLOOKUP($D4,[2]Retiros_dinamica!$F:$F,[2]Retiros_dinamica!D:D,"S/I",0) -> S/I | AA4: =_xlfn.XLOOKUP($D4,[2]Retiros_dinamica!$F:$F,[2]Retiros_dinamica!E:E,"S/I",0) -> S/I | AB4: =_xlfn.XLOOKUP(C4,[2]CMg!$I$4:$I$106,[2]CMg!$M$4:$M$106,"----",0,1) -> ---- | AH4: =_xlfn.XLOOKUP($E4,'[2]Balance económico'!$C:$C,'[2]Balance económico'!$D:$D,"-",0) -> 1.0058747e+09 | AI4: =_xlfn.XLOOKUP($E4,'[2]Balance económico'!$C:$C,'[2]Balance económico'!$E:$E,"-",0) -> 2.3067282e+09 | AJ4: =_xlfn.XLOOKUP($E4,'[2]Balance económico'!$C:$C,'[2]Balance económico'!$F:$F,"-",0) -> ---- | AK4: =IF(AA4>0,"PPA","-") -> PPA | AL4: {=IFERROR((X4*[2]!Tabla2[Bloque A] + 'BD Centrales 2025'!Y1009*[2]!Tabla2[Bloque B] + 'BD Centrales 2025'!Z1009*[2]!Tabla2[Bloque C])*#REF!,"-")} -> - | AM4: =IFERROR(AH4+AL4,"-") -> - | AN4: =IFERROR((AH4+AI4+AJ4)/(SUMIFS($W$2:$W$1194,$E$2:$E$1194,E4)*1000*#REF!),0) -> 0
A5: 4 | B5: CE01G0035 | C5: TER CONSTITUCION | D5: ELEKTRA GENERACIÓN S.A. | E5: =_xlfn.XLOOKUP(D5,'[2]Coordinados SEN'!$A:$A,'[2]Coordinados SEN'!$B:$B,"-",0) -> 76.594.660-3 | F5: ELEKTRA GENERACIÓN S.A. | G5: =COUNTIFS($D$2:$D$1194,D5) -> 5 | H5: S/E CONSTITUCION 23KV | I5: S/E CONSTITUCION 23KV | J5: =_xlfn.XLOOKUP(I5,'[2]Barras CMg'!$E$2:$E$1527,'[2]Barras CMg'!$A$2:$A$1527,"------",0,1) -> CONSTIT1______023 | K5: 6 | L5: 2025 | M5: Termoeléctrica | N5: Motor de combustión interna | O5: Pequeños medio de generación o PMG | P5: Maule | Q5: Talca | R5: Constitución | S5: Operativa | T5: 06-06-2007 | U5: 9.593 | V5: 9.012 | W5: =_xlfn.XLOOKUP(C5,#REF!,#REF!,"S/I",0) -> #REF! | X5: =_xlfn.XLOOKUP($D5,[2]Retiros_dinamica!$F:$F,[2]Retiros_dinamica!B:B,"S/I",0) -> S/I | Y5: =_xlfn.XLOOKUP($D5,[2]Retiros_dinamica!$F:$F,[2]Retiros_dinamica!C:C,"S/I",0) -> S/I | Z5: =_xlfn.XLOOKUP($D5,[2]Retiros_dinamica!$F:$F,[2]Retiros_dinamica!D:D,"S/I",0) -> S/I | AA5: =_xlfn.XLOOKUP($D5,[2]Retiros_dinamica!$F:$F,[2]Retiros_dinamica!E:E,"S/I",0) -> S/I | AB5: =_xlfn.XLOOKUP(C5,[2]CMg!$I$4:$I$106,[2]CMg!$M$4:$M$106,"----",0,1) -> ---- | AH5: =_xlfn.XLOOKUP($E5,'[2]Balance económico'!$C:$C,'[2]Balance económico'!$D:$D,"-",0) -> 1.0058747e+09 | AI5: =_xlfn.XLOOKUP($E5,'[2]Balance económico'!$C:$C,'[2]Balance económico'!$E:$E,"-",0) -> 2.3067282e+09 | AJ5: =_xlfn.XLOOKUP($E5,'[2]Balance económico'!$C:$C,'[2]Balance económico'!$F:$F,"-",0) -> ---- | AK5: =IF(AA5>0,"PPA","-") -> PPA | AL5: {=IFERROR((X5*[2]!Tabla2[Bloque A] + 'BD Centrales 2025'!Y1075*[2]!Tabla2[Bloque B] + 'BD Centrales 2025'!Z1075*[2]!Tabla2[Bloque C])*#REF!,"-")} -> - | AM5: =IFERROR(AH5+AL5,"-") -> - | AN5: =IFERROR((AH5+AI5+AJ5)/(SUMIFS($W$2:$W$1194,$E$2:$E$1194,E5)*1000*#REF!),0) -> 0
A6: 5 | B6: CE01G0071 | C6: HP MARIPOSAS | D6: HIDROELÉCTRICA RÍO LIRCAY S.A. | E6: =_xlfn.XLOOKUP(D6,'[2]Coordinados SEN'!$A:$A,'[2]Coordinados SEN'!$B:$B,"-",0) -> 76.025.973-K | F6: HIDROELÉCTRICA RÍO LIRCAY S.A. | G6: =COUNTIFS($D$2:$D$1194,D6) -> 3 | H6: ID 1174 BA S/E MARIPOSAS 66KV BP1 | I6: S/E CENTRAL LIRCAY 66KV | J6: =_xlfn.XLOOKUP(I6,'[2]Barras CMg'!$E$2:$E$1527,'[2]Barras CMg'!$A$2:$A$1527,"------",0,1) -> LIRCAY________066 | K6: 1 | L6: 2025 | M6: Hidroeléctrica | N6: Minihidro de pasada | O6: Pequeños medio de generación o PMG | P6: Maule | Q6: Talca | R6: San Clemente | S6: Operativa – Autodespacho DS88 | T6: 26-03-2011 | U6: 6.3 | V6: 6.2855 | W6: =_xlfn.XLOOKUP(C6,#REF!,#REF!,"S/I",0) -> #REF! | X6: =_xlfn.XLOOKUP($D6,[2]Retiros_dinamica!$F:$F,[2]Retiros_dinamica!B:B,"S/I",0) -> S/I | Y6: =_xlfn.XLOOKUP($D6,[2]Retiros_dinamica!$F:$F,[2]Retiros_dinamica!C:C,"S/I",0) -> S/I | Z6: =_xlfn.XLOOKUP($D6,[2]Retiros_dinamica!$F:$F,[2]Retiros_dinamica!D:D,"S/I",0) -> S/I | AA6: =_xlfn.XLOOKUP($D6,[2]Retiros_dinamica!$F:$F,[2]Retiros_dinamica!E:E,"S/I",0) -> S/I | AB6: =_xlfn.XLOOKUP(C6,[2]CMg!$I$4:$I$106,[2]CMg!$M$4:$M$106,"----",0,1) -> ---- | AC6: =_xlfn.XLOOKUP(C6,[2]CMg!$A$4:$A$106,[2]CMg!$B$4:$B$106,"----",0,1) -> ---- | AD6: =_xlfn.XLOOKUP(C6,'[3]Promedio solar Cmg'!$A$4:$A$106,'[3]Promedio solar Cmg'!$B$4:$B$106,"----",0,1) -> ---- | AH6: =_xlfn.XLOOKUP($E6,'[2]Balance económico'!$C:$C,'[2]Balance económico'!$D:$D,"-",0) -> 2.4186895e+09 | AI6: =_xlfn.XLOOKUP($E6,'[2]Balance económico'!$C:$C,'[2]Balance económico'!$E:$E,"-",0) -> 1.0175922e+09 | AJ6: =_xlfn.XLOOKUP($E6,'[2]Balance económico'!$C:$C,'[2]Balance económico'!$F:$F,"-",0) -> ---- | AK6: =IF(AA6>0,"PPA","-") -> PPA | AL6: {=IFERROR((X6*[2]!Tabla2[Bloque A] + 'BD Centrales 2025'!Y78*[2]!Tabla2[Bloque B] + 'BD Centrales 2025'!Z78*[2]!Tabla2[Bloque C])*#REF!,"-")} -> - | AM6: =IFERROR(AH6+AL6,"-") -> - | AN6: =IFERROR((AH6+AI6+AJ6)/(SUMIFS($W$2:$W$1194,$E$2:$E$1194,E6)*1000*#REF!),0) -> 0
A7: 6 | B7: CE05G0012 | C7: HP EL RINCON | D7: ASOC. DE CANAL. SOCIEDAD DEL CANAL DE MAIPO | E7: =_xlfn.XLOOKUP(D7,'[2]Coordinados SEN'!$A:$A,'[2]Coordinados SEN'!$B:$B,"-",0) -> 70.009.410-3 | F7: ASOC. DE CANAL. SOCIEDAD DEL CANAL DE MAIPO | G7: =COUNTIFS($D$2:$D$1194,D7) -> 5 | H7: ID 1223 BA S/E CENTRAL FLORIDA 2 12KV BP1 | I7: S/E FLORIDA 110KV | J7: =_xlfn.XLOOKUP(I7,'[2]Barras CMg'!$E$2:$E$1527,'[2]Barras CMg'!$A$2:$A$1527,"------",0,1) -> FLORIDA_______110 | K7: 1 | L7: 2025 | M7: Hidroeléctrica | N7: Minihidro de pasada | O7: Pequeños medio de generación o PMG | P7: Metropolitana de Santiago | Q7: Santiago | R7: La Florida | S7: Operativa – Autodespacho DS88 | T7: 13-04-2007 | U7: 0.289 | V7: 0.284665 | W7: =_xlfn.XLOOKUP(C7,#REF!,#REF!,"S/I",0) -> #REF! | X7: =_xlfn.XLOOKUP($D7,[2]Retiros_dinamica!$F:$F,[2]Retiros_dinamica!B:B,"S/I",0) -> S/I | Y7: =_xlfn.XLOOKUP($D7,[2]Retiros_dinamica!$F:$F,[2]Retiros_dinamica!C:C,"S/I",0) -> S/I | Z7: =_xlfn.XLOOKUP($D7,[2]Retiros_dinamica!$F:$F,[2]Retiros_dinamica!D:D,"S/I",0) -> S/I | AA7: =_xlfn.XLOOKUP($D7,[2]Retiros_dinamica!$F:$F,[2]Retiros_dinamica!E:E,"S/I",0) -> S/I | AB7: =_xlfn.XLOOKUP(C7,[2]CMg!$I$4:$I$106,[2]CMg!$M$4:$M$106,"----",0,1) -> ---- | AC7: =_xlfn.XLOOKUP(C7,[2]CMg!$A$4:$A$106,[2]CMg!$B$4:$B$106,"----",0,1) -> ---- | AD7: =_xlfn.XLOOKUP(C7,'[3]Promedio solar Cmg'!$A$4:$A$106,'[3]Promedio solar Cmg'!$B$4:$B$106,"----",0,1) -> ---- | AH7: =_xlfn.XLOOKUP($E7,'[2]Balance económico'!$C:$C,'[2]Balance económico'!$D:$D,"-",0) -> 4.1842232e+09 | AI7: =_xlfn.XLOOKUP($E7,'[2]Balance económico'!$C:$C,'[2]Balance económico'!$E:$E,"-",0) -> 4.937221e+08 | AJ7: =_xlfn.XLOOKUP($E7,'[2]Balance económico'!$C:$C,'[2]Balance económico'!$F:$F,"-",0) -> ---- | AK7: =IF(AA7>0,"PPA","-") -> PPA | AL7: {=IFERROR((X7*[2]!Tabla2[Bloque A] + 'BD Centrales 2025'!Y50*[2]!Tabla2[Bloque B] + 'BD Centrales 2025'!Z50*[2]!Tabla2[Bloque C])*#REF!,"-")} -> - | AM7: =IFERROR(AH7+AL7,"-") -> - | AN7: =IFERROR((AH7+AI7+AJ7)/(SUMIFS($W$2:$W$1194,$E$2:$E$1194,E7)*1000*#REF!),0) -> 0
A8: 7 | B8: CE04G0012 | C8: PMGD HP EYZAGUIRRE | D8: ASOC. DE CANAL. SOCIEDAD DEL CANAL DE MAIPO | E8: =_xlfn.XLOOKUP(D8,'[2]Coordinados SEN'!$A:$A,'[2]Coordinados SEN'!$B:$B,"-",0) -> 70.009.410-3 | F8: ASOC. DE CANAL. SOCIEDAD DEL CANAL DE MAIPO | G8: =COUNTIFS($D$2:$D$1194,D8) -> 5 | H8: ID 1064 BA S/E PUENTE ALTO 12KV BP1 | I8: S/E PUENTE ALTO 12KV | J8: =_xlfn.XLOOKUP(I8,'[2]Barras CMg'!$E$2:$E$1527,'[2]Barras CMg'!$A$2:$A$1527,"------",0,1) -> ------ | K8: 1 | L8: 2025 | M8: Hidroeléctrica | N8: Minihidro de pasada | O8: Pequeños medio de generación distribuida o PMGD | P8: Metropolitana de Santiago | Q8: Cordillera | R8: Puente Alto | S8: Operativa | T8: 01-01-2003 | U8: 1.9 | V8: 1.8715 | W8: =_xlfn.XLOOKUP(C8,#REF!,#REF!,"S/I",0) -> #REF! | X8: =_xlfn.XLOOKUP($D8,[2]Retiros_dinamica!$F:$F,[2]Retiros_dinamica!B:B,"S/I",0) -> S/I | Y8: =_xlfn.XLOOKUP($D8,[2]Retiros_dinamica!$F:$F,[2]Retiros_dinamica!C:C,"S/I",0) -> S/I | Z8: =_xlfn.XLOOKUP($D8,[2]Retiros_dinamica!$F:$F,[2]Retiros_dinamica!D:D,"S/I",0) -> S/I | AA8: =_xlfn.XLOOKUP($D8,[2]Retiros_dinamica!$F:$F,[2]Retiros_dinamica!E:E,"S/I",0) -> S/I | AB8: =_xlfn.XLOOKUP(C8,[2]CMg!$I$4:$I$106,[2]CMg!$M$4:$M$106,"----",0,1) -> ---- | AH8: =_xlfn.XLOOKUP($E8,'[2]Balance económico'!$C:$C,'[2]Balance económico'!$D:$D,"-",0) -> 4.1842232e+09 | AI8: =_xlfn.XLOOKUP($E8,'[2]Balance económico'!$C:$C,'[2]Balance económico'!$E:$E,"-",0) -> 4.937221e+08 | AJ8: =_xlfn.XLOOKUP($E8,'[2]Balance económico'!$C:$C,'[2]Balance económico'!$F:$F,"-",0) -> ---- | AK8: =IF(AA8>0,"PPA","-") -> PPA | AL8: {=IFERROR((X8*[2]!Tabla2[Bloque A] + 'BD Centrales 2025'!Y929*[2]!Tabla2[Bloque B] + 'BD Centrales 2025'!Z929*[2]!Tabla2[Bloque C])*#REF!,"-")} -> - | AM8: =IFERROR(AH8+AL8,"-") -> - | AN8: =IFERROR((AH8+AI8+AJ8)/(SUMIFS($W$2:$W$1194,$E$2:$E$1194,E8)*1000*#REF!),0) -> 0
A9: 8 | B9: CE01G0031 | C9: TER CONCON | D9: TECNORED S.A. | E9: =_xlfn.XLOOKUP(D9,'[2]Coordinados SEN'!$A:$A,'[2]Coordinados SEN'!$B:$B,"-",0) -> 77.302.440-5 | F9: TECNORED S.A. | G9: =COUNTIFS($D$2:$D$1194,D9) -> 7 | H9: S/E CONCON 12kV | I9: S/E CONCON 12KV | J9: =_xlfn.XLOOKUP(I9,'[2]Barras CMg'!$E$2:$E$1527,'[2]Barras CMg'!$A$2:$A$1527,"------",0,1) -> CONCON________013 | K9: 3 | L9: 2025 | M9: Termoeléctrica | N9: Motor de combustión interna | O9: Pequeños medio de generación o PMG | P9: Valparaíso | Q9: Valparaíso | R9: Concón | S9: Operativa | T9: 23-04-2007 | U9: 2.489 | V9: 2.489 | W9: =_xlfn.XLOOKUP(C9,#REF!,#REF!,"S/I",0) -> #REF! | X9: =_xlfn.XLOOKUP($D9,[2]Retiros_dinamica!$F:$F,[2]Retiros_dinamica!B:B,"S/I",0) -> 25998.519 | Y9: =_xlfn.XLOOKUP($D9,[2]Retiros_dinamica!$F:$F,[2]Retiros_dinamica!C:C,"S/I",0) -> 36744.498 | Z9: =_xlfn.XLOOKUP($D9,[2]Retiros_dinamica!$F:$F,[2]Retiros_dinamica!D:D,"S/I",0) -> 13134.763 | AA9: =_xlfn.XLOOKUP($D9,[2]Retiros_dinamica!$F:$F,[2]Retiros_dinamica!E:E,"S/I",0) -> 75877.78 | AB9: =_xlfn.XLOOKUP(C9,[2]CMg!$I$4:$I$106,[2]CMg!$M$4:$M$106,"----",0,1) -> ---- | AH9: =_xlfn.XLOOKUP($E9,'[2]Balance económico'!$C:$C,'[2]Balance económico'!$D:$D,"-",0) -> -4.1482077e+09 | AI9: =_xlfn.XLOOKUP($E9,'[2]Balance económico'!$C:$C,'[2]Balance económico'!$E:$E,"-",0) -> 5.9046621e+08 | AJ9: =_xlfn.XLOOKUP($E9,'[2]Balance económico'!$C:$C,'[2]Balance económico'!$F:$F,"-",0) -> 2.2299489e+08 | AK9: =IF(AA9>0,"PPA","-") -> PPA | AL9: {=IFERROR((X9*[2]!Tabla2[Bloque A] + 'BD Centrales 2025'!Y1074*[2]!Tabla2[Bloque B] + 'BD Centrales 2025'!Z1074*[2]!Tabla2[Bloque C])*#REF!,"-")} -> - | AM9: =IFERROR(AH9+AL9,"-") -> - | AN9: =IFERROR((AH9+AI9+AJ9)/(SUMIFS($W$2:$W$1194,$E$2:$E$1194,E9)*1000*#REF!),0) -> 0
A10: 9 | B10: CE07G0031 | C10: TER EL TOTORAL | D10: TECNORED S.A. | E10: =_xlfn.XLOOKUP(D10,'[2]Coordinados SEN'!$A:$A,'[2]Coordinados SEN'!$B:$B,"-",0) -> 77.302.440-5 | F10: TECNORED S.A. | G10: =COUNTIFS($D$2:$D$1194,D10) -> 7 | H10: ID 1079 BA S/E EL TOTORAL 12KV BP1 | I10: S/E EL TOTORAL 12KV | J10: =_xlfn.XLOOKUP(I10,'[2]Barras CMg'!$E$2:$E$1527,'[2]Barras CMg'!$A$2:$A$1527,"------",0,1) -> TOTORAL_______012 | K10: 3 | L10: 2025 | M10: Termoeléctrica | N10: Motor de combustión interna | O10: PMG | P10: Valparaíso | Q10: San Antonio | R10: El Quisco | S10: Operativa | T10: 07-04-2008 | U10: 3.103 | V10: 3.103 | W10: =_xlfn.XLOOKUP(C10,#REF!,#REF!,"S/I",0) -> #REF! | X10: =_xlfn.XLOOKUP($D10,[2]Retiros_dinamica!$F:$F,[2]Retiros_dinamica!B:B,"S/I",0) -> 25998.519 | Y10: =_xlfn.XLOOKUP($D10,[2]Retiros_dinamica!$F:$F,[2]Retiros_dinamica!C:C,"S/I",0) -> 36744.498 | Z10: =_xlfn.XLOOKUP($D10,[2]Retiros_dinamica!$F:$F,[2]Retiros_dinamica!D:D,"S/I",0) -> 13134.763 | AA10: =_xlfn.XLOOKUP($D10,[2]Retiros_dinamica!$F:$F,[2]Retiros_dinamica!E:E,"S/I",0) -> 75877.78 | AB10: =_xlfn.XLOOKUP(C10,[2]CMg!$I$4:$I$106,[2]CMg!$M$4:$M$106,"----",0,1) -> ---- | AH10: =_xlfn.XLOOKUP($E10,'[2]Balance económico'!$C:$C,'[2]Balance económico'!$D:$D,"-",0) -> -4.1482077e+09 | AI10: =_xlfn.XLOOKUP($E10,'[2]Balance económico'!$C:$C,'[2]Balance económico'!$E:$E,"-",0) -> 5.9046621e+08 | AJ10: =_xlfn.XLOOKUP($E10,'[2]Balance económico'!$C:$C,'[2]Balance económico'!$F:$F,"-",0) -> 2.2299489e+08 | AK10: =IF(AA10>0,"PPA","-") -> PPA | AL10: {=IFERROR((X10*[2]!Tabla2[Bloque A] + 'BD Centrales 2025'!Y1097*[2]!Tabla2[Bloque B] + 'BD Centrales 2025'!Z1097*[2]!Tabla2[Bloque C])*#REF!,"-")} -> - | AM10: =IFERROR(AH10+AL10,"-") -> - | AN10: =IFERROR((AH10+AI10+AJ10)/(SUMIFS($W$2:$W$1194,$E$2:$E$1194,E10)*1000*#REF!),0) -> 0
A11: 10 | B11: CE02G0031 | C11: TER LAS VEGAS | D11: TECNORED S.A. | E11: =_xlfn.XLOOKUP(D11,'[2]Coordinados SEN'!$A:$A,'[2]Coordinados SEN'!$B:$B,"-",0) -> 77.302.440-5 | F11: TECNORED S.A. | G11: =COUNTIFS($D$2:$D$1194,D11) -> 7 | H11: S/E LAS VEGAS 110kv | I11: S/E LAS VEGAS (CHILQUINTA) 110KV | J11: =_xlfn.XLOOKUP(I11,'[2]Barras CMg'!$E$2:$E$1527,'[2]Barras CMg'!$A$2:$A$1527,"------",0,1) -> L.VEGAS2______110 | K11: 2 | L11: 2025 | M11: Termoeléctrica | N11: Motor de combustión interna | O11: Pequeños medio de generación o PMG | P11: Valparaíso | Q11: San Felipe de Aconcagua | R11: Llaillay | S11: Operativa | T11: 20-04-2007 | U11: 2.209 | V11: 2.209 | W11: =_xlfn.XLOOKUP(C11,#REF!,#REF!,"S/I",0) -> #REF! | X11: =_xlfn.XLOOKUP($D11,[2]Retiros_dinamica!$F:$F,[2]Retiros_dinamica!B:B,"S/I",0) -> 25998.519 | Y11: =_xlfn.XLOOKUP($D11,[2]Retiros_dinamica!$F:$F,[2]Retiros_dinamica!C:C,"S/I",0) -> 36744.498 | Z11: =_xlfn.XLOOKUP($D11,[2]Retiros_dinamica!$F:$F,[2]Retiros_dinamica!D:D,"S/I",0) -> 13134.763 | AA11: =_xlfn.XLOOKUP($D11,[2]Retiros_dinamica!$F:$F,[2]Retiros_dinamica!E:E,"S/I",0) -> 75877.78 | AB11: =_xlfn.XLOOKUP(C11,[2]CMg!$I$4:$I$106,[2]CMg!$M$4:$M$106,"----",0,1) -> ---- | AH11: =_xlfn.XLOOKUP($E11,'[2]Balance económico'!$C:$C,'[2]Balance económico'!$D:$D,"-",0) -> -4.1482077e+09 | AI11: =_xlfn.XLOOKUP($E11,'[2]Balance económico'!$C:$C,'[2]Balance económico'!$E:$E,"-",0) -> 5.9046621e+08 | AJ11: =_xlfn.XLOOKUP($E11,'[2]Balance económico'!$C:$C,'[2]Balance económico'!$F:$F,"-",0) -> 2.2299489e+08 | AK11: =IF(AA11>0,"PPA","-") -> PPA | AL11: {=IFERROR((X11*[2]!Tabla2[Bloque A] + 'BD Centrales 2025'!Y1126*[2]!Tabla2[Bloque B] + 'BD Centrales 2025'!Z1126*[2]!Tabla2[Bloque C])*#REF!,"-")} -> - | AM11: =IFERROR(AH11+AL11,"-") -> - | AN11: =IFERROR((AH11+AI11+AJ11)/(SUMIFS($W$2:$W$1194,$E$2:$E$1194,E11)*1000*#REF!),0) -> 0
A12: 11 | B12: CE09G0031 | C12: TER LINARES NORTE | D12: CGE COMERCIALIZADORA SPA | E12: =_xlfn.XLOOKUP(D12,'[2]Coordinados SEN'!$A:$A,'[2]Coordinados SEN'!$B:$B,"-",0) -> 77.316.204-2 | F12: TECNORED S.A. | G12: =COUNTIFS($D$2:$D$1194,D12) -> 1 | H12: S/E LINARES NORTE 13.2kV | I12: S/E LINARES NORTE 13.2KV | J12: =_xlfn.XLOOKUP(I12,'[2]Barras CMg'!$E$2:$E$1527,'[2]Barras CMg'!$A$2:$A$1527,"------",0,1) -> LIN.NORTE_____013 | K12: 1 | L12: 2025 | M12: Termoeléctrica | N12: Motor de combustión interna | O12: Pequeños medio de generación o PMG | P12: Maule | Q12: Linares | R12: Linares | S12: Operativa | T12: 20-03-2009 | U12: 0.467 | V12: 0.464 | W12: =_xlfn.XLOOKUP(C12,#REF!,#REF!,"S/I",0) -> #REF! | X12: =_xlfn.XLOOKUP($D12,[2]Retiros_dinamica!$F:$F,[2]Retiros_dinamica!B:B,"S/I",0) -> 23670.829 | Y12: =_xlfn.XLOOKUP($D12,[2]Retiros_dinamica!$F:$F,[2]Retiros_dinamica!C:C,"S/I",0) -> 34683.872 | Z12: =_xlfn.XLOOKUP($D12,[2]Retiros_dinamica!$F:$F,[2]Retiros_dinamica!D:D,"S/I",0) -> 13870.15 | AA12: =_xlfn.XLOOKUP($D12,[2]Retiros_dinamica!$F:$F,[2]Retiros_dinamica!E:E,"S/I",0) -> 72224.851 | AB12: =_xlfn.XLOOKUP(C12,[2]CMg!$I$4:$I$106,[2]CMg!$M$4:$M$106,"----",0,1) -> ---- | AH12: =_xlfn.XLOOKUP($E12,'[2]Balance económico'!$C:$C,'[2]Balance económico'!$D:$D,"-",0) -> -3.7105784e+09 | AI12: =_xlfn.XLOOKUP($E12,'[2]Balance económico'!$C:$C,'[2]Balance económico'!$E:$E,"-",0) -> -6.9608429e+08 | AJ12: =_xlfn.XLOOKUP($E12,'[2]Balance económico'!$C:$C,'[2]Balance económico'!$F:$F,"-",0) -> 2.0931587e+08 | AK12: =IF(AA12>0,"PPA","-") -> PPA | AL12: {=IFERROR((X12*[2]!Tabla2[Bloque A] + 'BD Centrales 2025'!Y1129*[2]!Tabla2[Bloque B] + 'BD Centrales 2025'!Z1129*[2]!Tabla2[Bloque C])*#REF!,"-")} -> - | AM12: =IFERROR(AH12+AL12,"-") -> - | AN12: =IFERROR((AH12+AI12+AJ12)/(SUMIFS($W$2:$W$1194,$E$2:$E$1194,E12)*1000*#REF!),0) -> 0
A13: 12 | B13: CE06G0031 | C13: TER PLACILLA | D13: ENERQUINTA S.A. | E13: =_xlfn.XLOOKUP(D13,'[2]Coordinados SEN'!$A:$A,'[2]Coordinados SEN'!$B:$B,"-",0) -> 77.402.185-K | F13: TECNORED S.A. | G13: =COUNTIFS($D$2:$D$1194,D13) -> 1 | H13: ID 3162 BA S/E PLACILLA (CHILQUINTA) 12KV BP1 | I13: S/E PLACILLA (CHILQUINTA) 12KV | J13: =_xlfn.XLOOKUP(I13,'[2]Barras CMg'!$E$2:$E$1527,'[2]Barras CMg'!$A$2:$A$1527,"------",0,1) -> PLACILLA_S____013 | K13: 2 | L13: 2025 | M13: Termoeléctrica | N13: Motor de combustión interna | O13: Pequeños medio de generación o PMG | P13: Valparaíso | Q13: Valparaíso | R13: Valparaíso | S13: Operativa | T13: 02-05-2008 | U13: 2.373 | V13: 2.373 | W13: =_xlfn.XLOOKUP(C13,#REF!,#REF!,"S/I",0) -> #REF! | X13: =_xlfn.XLOOKUP($D13,[2]Retiros_dinamica!$F:$F,[2]Retiros_dinamica!B:B,"S/I",0) -> 5461.8907 | Y13: =_xlfn.XLOOKUP($D13,[2]Retiros_dinamica!$F:$F,[2]Retiros_dinamica!C:C,"S/I",0) -> 9601.5787 | Z13: =_xlfn.XLOOKUP($D13,[2]Retiros_dinamica!$F:$F,[2]Retiros_dinamica!D:D,"S/I",0) -> 2922.7911 | AA13: =_xlfn.XLOOKUP($D13,[2]Retiros_dinamica!$F:$F,[2]Retiros_dinamica!E:E,"S/I",0) -> 17986.261 | AB13: =_xlfn.XLOOKUP(C13,[2]CMg!$I$4:$I$106,[2]CMg!$M$4:$M$106,"----",0,1) -> ---- | AH13: =_xlfn.XLOOKUP($E13,'[2]Balance económico'!$C:$C,'[2]Balance económico'!$D:$D,"-",0) -> 98284160 | AI13: =_xlfn.XLOOKUP($E13,'[2]Balance económico'!$C:$C,'[2]Balance económico'!$E:$E,"-",0) -> -1.5092092e+08 | AJ13: =_xlfn.XLOOKUP($E13,'[2]Balance económico'!$C:$C,'[2]Balance económico'!$F:$F,"-",0) -> 53787478 | AK13: =IF(AA13>0,"PPA","-") -> PPA | AL13: {=IFERROR((X13*[2]!Tabla2[Bloque A] + 'BD Centrales 2025'!Y1159*[2]!Tabla2[Bloque B] + 'BD Centrales 2025'!Z1159*[2]!Tabla2[Bloque C])*#REF!,"-")} -> - | AM13: =IFERROR(AH13+AL13,"-") -> - | AN13: =IFERROR((AH13+AI13+AJ13)/(SUMIFS($W$2:$W$1194,$E$2:$E$1194,E13)*1000*#REF!),0) -> 0
A14: 14 | B14: CE08G0031 | C14: TER SAN GREGORIO | D14: TECNORED S.A. | E14: =_xlfn.XLOOKUP(D14,'[2]Coordinados SEN'!$A:$A,'[2]Coordinados SEN'!$B:$B,"-",0) -> 77.302.440-5 | F14: TECNORED S.A. | G14: =COUNTIFS($D$2:$D$1194,D14) -> 7 | H14: S/E SAN GREGORIO 13.2kV | I14: S/E SAN GREGORIO 13.2KV | J14: =_xlfn.XLOOKUP(I14,'[2]Barras CMg'!$E$2:$E$1527,'[2]Barras CMg'!$A$2:$A$1527,"------",0,1) -> S.GREGORIO____013 | K14: 1 | L14: 2025 | M14: Termoeléctrica | N14: Motor de combustión interna | O14: Pequeños medio de generación o PMG | P14: Ñuble | Q14: Punilla | R14: Ñiquén | S14: Operativa | T14: 20-03-2009 | U14: 0.425 | V14: 0.422 | W14: =_xlfn.XLOOKUP(C14,#REF!,#REF!,"S/I",0) -> #REF! | X14: =_xlfn.XLOOKUP($D14,[2]Retiros_dinamica!$F:$F,[2]Retiros_dinamica!B:B,"S/I",0) -> 25998.519 | Y14: =_xlfn.XLOOKUP($D14,[2]Retiros_dinamica!$F:$F,[2]Retiros_dinamica!C:C,"S/I",0) -> 36744.498 | Z14: =_xlfn.XLOOKUP($D14,[2]Retiros_dinamica!$F:$F,[2]Retiros_dinamica!D:D,"S/I",0) -> 13134.763 | AA14: =_xlfn.XLOOKUP($D14,[2]Retiros_dinamica!$F:$F,[2]Retiros_dinamica!E:E,"S/I",0) -> 75877.78 | AB14: =_xlfn.XLOOKUP(C14,[2]CMg!$I$4:$I$106,[2]CMg!$M$4:$M$106,"----",0,1) -> ---- | AH14: =_xlfn.XLOOKUP($E14,'[2]Balance económico'!$C:$C,'[2]Balance económico'!$D:$D,"-",0) -> -4.1482077e+09 | AI14: =_xlfn.XLOOKUP($E14,'[2]Balance económico'!$C:$C,'[2]Balance económico'!$E:$E,"-",0) -> 5.9046621e+08 | AJ14: =_xlfn.XLOOKUP($E14,'[2]Balance económico'!$C:$C,'[2]Balance económico'!$F:$F,"-",0) -> 2.2299489e+08 | AK14: =IF(AA14>0,"PPA","-") -> PPA | AL14: {=IFERROR((X14*[2]!Tabla2[Bloque A] + 'BD Centrales 2025'!Y1164*[2]!Tabla2[Bloque B] + 'BD Centrales 2025'!Z1164*[2]!Tabla2[Bloque C])*#REF!,"-")} -> - | AM14: =IFERROR(AH14+AL14,"-") -> - | AN14: =IFERROR((AH14+AI14+AJ14)/(SUMIFS($W$2:$W$1194,$E$2:$E$1194,E14)*1000*#REF!),0) -> 0
A15: 15 | B15: CE01G0022 | C15: PMGD HP AUXILIAR DEL MAIPO | D15: CARBOMET ENERGÍA S.A. | E15: =_xlfn.XLOOKUP(D15,'[2]Coordinados SEN'!$A:$A,'[2]Coordinados SEN'!$B:$B,"-",0) -> 91.066.000-4 | F15: CARBOMET ENERGÍA S.A. | G15: =COUNTIFS($D$2:$D$1194,D15) -> 2 | H15: Alimentador El Mariscal / SE La Pintana | I15: S/E LA PINTANA | J15: =_xlfn.XLOOKUP(I15,'[2]Barras CMg'!$E$2:$E$1527,'[2]Barras CMg'!$A$2:$A$1527,"------",0,1) -> ------ | K15: 3 | L15: 2025 | M15: Hidroeléctrica | N15: Minihidro de pasada | O15: Pequeños medio de generación distribuida o PMGD | P15: Metropolitana de Santiago | Q15: Maipo | R15: San Bernardo | S15: Operativa | T15: 31-07-1962 | U15: 5.12 | V15: 5.1 | W15: =_xlfn.XLOOKUP(C15,#REF!,#REF!,"S/I",0) -> #REF! | X15: =_xlfn.XLOOKUP($D15,[2]Retiros_dinamica!$F:$F,[2]Retiros_dinamica!B:B,"S/I",0) -> S/I | Y15: =_xlfn.XLOOKUP($D15,[2]Retiros_dinamica!$F:$F,[2]Retiros_dinamica!C:C,"S/I",0) -> S/I | Z15: =_xlfn.XLOOKUP($D15,[2]Retiros_dinamica!$F:$F,[2]Retiros_dinamica!D:D,"S/I",0) -> S/I | AA15: =_xlfn.XLOOKUP($D15,[2]Retiros_dinamica!$F:$F,[2]Retiros_dinamica!E:E,"S/I",0) -> S/I | AB15: =_xlfn.XLOOKUP(C15,[2]CMg!$I$4:$I$106,[2]CMg!$M$4:$M$106,"----",0,1) -> ---- | AH15: =_xlfn.XLOOKUP($E15,'[2]Balance económico'!$C:$C,'[2]Balance económico'!$D:$D,"-",0) -> 3.6019824e+09 | AI15: =_xlfn.XLOOKUP($E15,'[2]Balance económico'!$C:$C,'[2]Balance económico'!$E:$E,"-",0) -> 4.573145e+08 | AJ15: =_xlfn.XLOOKUP($E15,'[2]Balance económico'!$C:$C,'[2]Balance económico'!$F:$F,"-",0) -> ---- | AK15: =IF(AA15>0,"PPA","-") -> PPA | AL15: {=IFERROR((X15*[2]!Tabla2[Bloque A] + 'BD Centrales 2025'!Y926*[2]!Tabla2[Bloque B] + 'BD Centrales 2025'!Z926*[2]!Tabla2[Bloque C])*#REF!,"-")} -> - | AM15: =IFERROR(AH15+AL15,"-") -> - | AN15: =IFERROR((AH15+AI15+AJ15)/(SUMIFS($W$2:$W$1194,$E$2:$E$1194,E15)*1000*#REF!),0) -> 0
A16: 16 | B16: CE02G0022 | C16: PMGD HP LOS BAJOS | D16: CARBOMET ENERGÍA S.A. | E16: =_xlfn.XLOOKUP(D16,'[2]Coordinados SEN'!$A:$A,'[2]Coordinados SEN'!$B:$B,"-",0) -> 91.066.000-4 | F16: CARBOMET ENERGÍA S.A. | G16: =COUNTIFS($D$2:$D$1194,D16) -> 2 | H16: S/E CARBOMET 12 KV | I16: S/E CARBOMET 12KV | J16: =_xlfn.XLOOKUP(I16,'[2]Barras CMg'!$E$2:$E$1527,'[2]Barras CMg'!$A$2:$A$1527,"------",0,1) -> ------ | K16: 1 | L16: 2025 | M16: Hidroeléctrica | N16: Minihidro de pasada | O16: Pequeños medio de generación distribuida o PMGD | P16: Metropolitana de Santiago | Q16: Cordillera | R16: Puente Alto | S16: Operativa | T16: 31-07-1944 | U16: 5.5 | V16: 5.4725 | W16: =_xlfn.XLOOKUP(C16,#REF!,#REF!,"S/I",0) -> #REF! | X16: =_xlfn.XLOOKUP($D16,[2]Retiros_dinamica!$F:$F,[2]Retiros_dinamica!B:B,"S/I",0) -> S/I | Y16: =_xlfn.XLOOKUP($D16,[2]Retiros_dinamica!$F:$F,[2]Retiros_dinamica!C:C,"S/I",0) -> S/I | Z16: =_xlfn.XLOOKUP($D16,[2]Retiros_dinamica!$F:$F,[2]Retiros_dinamica!D:D,"S/I",0) -> S/I | AA16: =_xlfn.XLOOKUP($D16,[2]Retiros_dinamica!$F:$F,[2]Retiros_dinamica!E:E,"S/I",0) -> S/I | AB16: =_xlfn.XLOOKUP(C16,[2]CMg!$I$4:$I$106,[2]CMg!$M$4:$M$106,"----",0,1) -> ---- | AH16: =_xlfn.XLOOKUP($E16,'[2]Balance económico'!$C:$C,'[2]Balance económico'!$D:$D,"-",0) -> 3.6019824e+09 | AI16: =_xlfn.XLOOKUP($E16,'[2]Balance económico'!$C:$C,'[2]Balance económico'!$E:$E,"-",0) -> 4.573145e+08 | AJ16: =_xlfn.XLOOKUP($E16,'[2]Balance económico'!$C:$C,'[2]Balance económico'!$F:$F,"-",0) -> ---- | AK16: =IF(AA16>0,"PPA","-") -> PPA | AL16: {=IFERROR((X16*[2]!Tabla2[Bloque A] + 'BD Centrales 2025'!Y927*[2]!Tabla2[Bloque B] + 'BD Centrales 2025'!Z927*[2]!Tabla2[Bloque C])*#REF!,"-")} -> - | AM16: =IFERROR(AH16+AL16,"-") -> - | AN16: =IFERROR((AH16+AI16+AJ16)/(SUMIFS($W$2:$W$1194,$E$2:$E$1194,E16)*1000*#REF!),0) -> 0
A17: 17 | B17: CE01G0023 | C17: PMGD HP LOS MORROS | D17: CIA MOLINERA VILLARRICA LTDA | E17: =_xlfn.XLOOKUP(D17,'[2]Coordinados SEN'!$A:$A,'[2]Coordinados SEN'!$B:$B,"-",0) -> 80.203.400-8 | F17: CIA MOLINERA VILLARRICA LTDA | G17: =COUNTIFS($D$2:$D$1194,D17) -> 2 | H17: S/E LOS MORROS | I17: S/E LOS MORROS | J17: =_xlfn.XLOOKUP(I17,'[2]Barras CMg'!$E$2:$E$1527,'[2]Barras CMg'!$A$2:$A$1527,"------",0,1) -> ------ | K17: 5 | L17: 2025 | M17: Hidroeléctrica | N17: Minihidro de pasada | O17: Pequeños medio de generación distribuida o PMGD | P17: Metropolitana de Santiago | Q17: Maipo | R17: San Bernardo | S17: Operativa | T17: 31-07-1930 | U17: 3.1 | V17: 3.0535 | W17: =_xlfn.XLOOKUP(C17,#REF!,#REF!,"S/I",0) -> #REF! | X17: =_xlfn.XLOOKUP($D17,[2]Retiros_dinamica!$F:$F,[2]Retiros_dinamica!B:B,"S/I",0) -> S/I | Y17: =_xlfn.XLOOKUP($D17,[2]Retiros_dinamica!$F:$F,[2]Retiros_dinamica!C:C,"S/I",0) -> S/I | Z17: =_xlfn.XLOOKUP($D17,[2]Retiros_dinamica!$F:$F,[2]Retiros_dinamica!D:D,"S/I",0) -> S/I | AA17: =_xlfn.XLOOKUP($D17,[2]Retiros_dinamica!$F:$F,[2]Retiros_dinamica!E:E,"S/I",0) -> S/I | AB17: =_xlfn.XLOOKUP(C17,[2]CMg!$I$4:$I$106,[2]CMg!$M$4:$M$106,"----",0,1) -> ---- | AH17: =_xlfn.XLOOKUP($E17,'[2]Balance económico'!$C:$C,'[2]Balance económico'!$D:$D,"-",0) -> 97946755 | AI17: =_xlfn.XLOOKUP($E17,'[2]Balance económico'!$C:$C,'[2]Balance económico'!$E:$E,"-",0) -> 11282345 | AJ17: =_xlfn.XLOOKUP($E17,'[2]Balance económico'!$C:$C,'[2]Balance económico'!$F:$F,"-",0) -> ---- | AK17: =IF(AA17>0,"PPA","-") -> PPA | AL17: {=IFERROR((X17*[2]!Tabla2[Bloque A] + 'BD Centrales 2025'!Y846*[2]!Tabla2[Bloque B] + 'BD Centrales 2025'!Z846*[2]!Tabla2[Bloque C])*#REF!,"-")} -> - | AM17: =IFERROR(AH17+AL17,"-") -> - | AN17: =IFERROR((AH17+AI17+AJ17)/(SUMIFS($W$2:$W$1194,$E$2:$E$1194,E17)*1000*#REF!),0) -> 0
A18: 19 | B18: CE01G0053 | C18: PE LEBU | D18: PARQUE EÓLICO LEBU-TORO SPA | E18: =_xlfn.XLOOKUP(D18,'[2]Coordinados SEN'!$A:$A,'[2]Coordinados SEN'!$B:$B,"-",0) -> 76.416.891-7 | F18: PARQUE EÓLICO LEBU-TORO SPA | G18: =COUNTIFS($D$2:$D$1194,D18) -> 2 | H18: S/E LEBU 66 KV | I18: S/E LEBU 66KV | J18: =_xlfn.XLOOKUP(I18,'[2]Barras CMg'!$E$2:$E$1527,'[2]Barras CMg'!$A$2:$A$1527,"------",0,1) -> LEBU__________066 | K18: 9 | L18: 2025 | M18: Eólica | N18: Parque eólico | O18: Pequeños medio de generación o PMG | P18: Biobío | Q18: Arauco | R18: Lebu | S18: Operativa – Autodespacho DS88 | T18: 25-03-2014 | U18: 10.045 | V18: 9.34 | W18: =_xlfn.XLOOKUP(C18,#REF!,#REF!,"S/I",0) -> #REF! | X18: =_xlfn.XLOOKUP($D18,[2]Retiros_dinamica!$F:$F,[2]Retiros_dinamica!B:B,"S/I",0) -> 672.25883 | Y18: =_xlfn.XLOOKUP($D18,[2]Retiros_dinamica!$F:$F,[2]Retiros_dinamica!C:C,"S/I",0) -> 782.1804 | Z18: =_xlfn.XLOOKUP($D18,[2]Retiros_dinamica!$F:$F,[2]Retiros_dinamica!D:D,"S/I",0) -> 335.7069 | AA18: =_xlfn.XLOOKUP($D18,[2]Retiros_dinamica!$F:$F,[2]Retiros_dinamica!E:E,"S/I",0) -> 1790.1461 | AB18: =_xlfn.XLOOKUP(C18,[2]CMg!$I$4:$I$106,[2]CMg!$M$4:$M$106,"----",0,1) -> ---- | AC18: =_xlfn.XLOOKUP(C18,[2]CMg!$A$4:$A$106,[2]CMg!$B$4:$B$106,"----",0,1) -> ---- | AD18: =_xlfn.XLOOKUP(C18,'[3]Promedio solar Cmg'!$A$4:$A$106,'[3]Promedio solar Cmg'!$B$4:$B$106,"----",0,1) -> ---- | AH18: =_xlfn.XLOOKUP($E18,'[2]Balance económico'!$C:$C,'[2]Balance económico'!$D:$D,"-",0) -> 2.3647287e+08 | AI18: =_xlfn.XLOOKUP($E18,'[2]Balance económico'!$C:$C,'[2]Balance económico'!$E:$E,"-",0) -> -1582155.2 | AJ18: =_xlfn.XLOOKUP($E18,'[2]Balance económico'!$C:$C,'[2]Balance económico'!$F:$F,"-",0) -> 5047447.2 | AK18: =IF(AA18>0,"PPA","-") -> PPA | AL18: {=IFERROR((X18*[2]!Tabla2[Bloque A] + 'BD Centrales 2025'!Y654*[2]!Tabla2[Bloque B] + 'BD Centrales 2025'!Z654*[2]!Tabla2[Bloque C])*#REF!,"-")} -> - | AM18: =IFERROR(AH18+AL18,"-") -> - | AN18: =IFERROR((AH18+AI18+AJ18)/(SUMIFS($W$2:$W$1194,$E$2:$E$1194,E18)*1000*#REF!),0) -> 0
A19: 20 | B19: CE01G0080 | C19: PMGD HP DONGUIL | D19: ENERGY ASSET SPA | E19: =_xlfn.XLOOKUP(D19,'[2]Coordinados SEN'!$A:$A,'[2]Coordinados SEN'!$B:$B,"-",0) -> 76.996.007-4 | F19: DONGUIL ENERGÍA S.A. | G19: =COUNTIFS($D$2:$D$1194,D19) -> 1 | H19: S/E PITRUFQUEN | I19: S/E PITRUFQUEN | J19: =_xlfn.XLOOKUP(I19,'[2]Barras CMg'!$E$2:$E$1527,'[2]Barras CMg'!$A$2:$A$1527,"------",0,1) -> ------ | K19: 1 | L19: 2025 | M19: Hidroeléctrica | N19: Minihidro de pasada | O19: Pequeños medio de generación distribuida o PMGD | P19: La Araucanía | Q19: Cautín | R19: Gorbea | S19: Operativa | T19: 28-05-2011 | U19: 0.25 | V19: 0.2494 | W19: =_xlfn.XLOOKUP(C19,#REF!,#REF!,"S/I",0) -> #REF! | X19: =_xlfn.XLOOKUP($D19,[2]Retiros_dinamica!$F:$F,[2]Retiros_dinamica!B:B,"S/I",0) -> 69889.533 | Y19: =_xlfn.XLOOKUP($D19,[2]Retiros_dinamica!$F:$F,[2]Retiros_dinamica!C:C,"S/I",0) -> 103971.18 | Z19: =_xlfn.XLOOKUP($D19,[2]Retiros_dinamica!$F:$F,[2]Retiros_dinamica!D:D,"S/I",0) -> 34990.618 | AA19: =_xlfn.XLOOKUP($D19,[2]Retiros_dinamica!$F:$F,[2]Retiros_dinamica!E:E,"S/I",0) -> 208851.33 | AB19: =_xlfn.XLOOKUP(C19,[2]CMg!$I$4:$I$106,[2]CMg!$M$4:$M$106,"----",0,1) -> ---- | AH19: =_xlfn.XLOOKUP($E19,'[2]Balance económico'!$C:$C,'[2]Balance económico'!$D:$D,"-",0) -> -1.3323336e+10 | AI19: =_xlfn.XLOOKUP($E19,'[2]Balance económico'!$C:$C,'[2]Balance económico'!$E:$E,"-",0) -> -1.3463716e+09 | AJ19: =_xlfn.XLOOKUP($E19,'[2]Balance económico'!$C:$C,'[2]Balance económico'!$F:$F,"-",0) -> 6.1971068e+08 | AK19: =IF(AA19>0,"PPA","-") -> PPA | AL19: {=IFERROR((X19*[2]!Tabla2[Bloque A] + 'BD Centrales 2025'!Y829*[2]!Tabla2[Bloque B] + 'BD Centrales 2025'!Z829*[2]!Tabla2[Bloque C])*#REF!,"-")} -> - | AM19: =IFERROR(AH19+AL19,"-") -> - | AN19: =IFERROR((AH19+AI19+AJ19)/(SUMIFS($W$2:$W$1194,$E$2:$E$1194,E19)*1000*#REF!),0) -> 0
A20: 21 | B20: CE01G0044 | C20: PMGD HP EL MANZANO (MELIPEUCO) | D20: HIDROELÉCTRICA EL MANZANO S.A. | E20: =_xlfn.XLOOKUP(D20,'[2]Coordinados SEN'!$A:$A,'[2]Coordinados SEN'!$B:$B,"-",0) -> 76.803.940-2 | F20: HIDROELÉCTRICA EL MANZANO S.A. | G20: =COUNTIFS($D$2:$D$1194,D20) -> 1 | H20: S/E LICANCO | I20: S/E LICANCO | J20: =_xlfn.XLOOKUP(I20,'[2]Barras CMg'!$E$2:$E$1527,'[2]Barras CMg'!$A$2:$A$1527,"------",0,1) -> ------ | K20: 1 | L20: 2025 | M20: Hidroeléctrica | N20: Minihidro de pasada | O20: Pequeños medio de generación distribuida o PMGD | P20: La Araucanía | Q20: Cautín | R20: Melipeuco | S20: Operativa | T20: 31-07-2008 | U20: 4.85 | V20: 4.85 | W20: =_xlfn.XLOOKUP(C20,#REF!,#REF!,"S/I",0) -> #REF! | X20: =_xlfn.XLOOKUP($D20,[2]Retiros_dinamica!$F:$F,[2]Retiros_dinamica!B:B,"S/I",0) -> S/I | Y20: =_xlfn.XLOOKUP($D20,[2]Retiros_dinamica!$F:$F,[2]Retiros_dinamica!C:C,"S/I",0) -> S/I | Z20: =_xlfn.XLOOKUP($D20,[2]Retiros_dinamica!$F:$F,[2]Retiros_dinamica!D:D,"S/I",0) -> S/I | AA20: =_xlfn.XLOOKUP($D20,[2]Retiros_dinamica!$F:$F,[2]Retiros_dinamica!E:E,"S/I",0) -> S/I | AB20: =_xlfn.XLOOKUP(C20,[2]CMg!$I$4:$I$106,[2]CMg!$M$4:$M$106,"----",0,1) -> ---- | AH20: =_xlfn.XLOOKUP($E20,'[2]Balance económico'!$C:$C,'[2]Balance económico'!$D:$D,"-",0) -> 5.6023304e+08 | AI20: =_xlfn.XLOOKUP($E20,'[2]Balance económico'!$C:$C,'[2]Balance económico'!$E:$E,"-",0) -> 37905656 | AJ20: =_xlfn.XLOOKUP($E20,'[2]Balance económico'!$C:$C,'[2]Balance económico'!$F:$F,"-",0) -> ---- | AK20: =IF(AA20>0,"PPA","-") -> PPA | AL20: {=IFERROR((X20*[2]!Tabla2[Bloque A] + 'BD Centrales 2025'!Y859*[2]!Tabla2[Bloque B] + 'BD Centrales 2025'!Z859*[2]!Tabla2[Bloque C])*#REF!,"-")} -> - | AM20: =IFERROR(AH20+AL20,"-") -> - | AN20: =IFERROR((AH20+AI20+AJ20)/(SUMIFS($W$2:$W$1194,$E$2:$E$1194,E20)*1000*#REF!),0) -> 0
A21: 22 | B21: CE04G0035 | C21: PMGD TER MONTE PATRIA | D21: ELEKTRA GENERACIÓN S.A. | E21: =_xlfn.XLOOKUP(D21,'[2]Coordinados SEN'!$A:$A,'[2]Coordinados SEN'!$B:$B,"-",0) -> 76.594.660-3 | F21: ELEKTRA GENERACIÓN S.A. | G21: =COUNTIFS($D$2:$D$1194,D21) -> 5 | H21: S/E CENTRAL MONTE PATRIA | I21: S/E CENTRAL MONTE PATRIA | J21: =_xlfn.XLOOKUP(I21,'[2]Barras CMg'!$E$2:$E$1527,'[2]Barras CMg'!$A$2:$A$1527,"------",0,1) -> ------ | K21: 8 | L21: 2025 | M21: Termoeléctrica | N21: Motor de combustión interna | O21: Pequeños medio de generación distribuida o PMGD | P21: Coquimbo | Q21: Limarí | R21: Monte Patria | S21: Operativa | T21: 12-07-2007 | U21: 9 | V21: 9 | W21: =_xlfn.XLOOKUP(C21,#REF!,#REF!,"S/I",0) -> #REF! | X21: =_xlfn.XLOOKUP($D21,[2]Retiros_dinamica!$F:$F,[2]Retiros_dinamica!B:B,"S/I",0) -> S/I | Y21: =_xlfn.XLOOKUP($D21,[2]Retiros_dinamica!$F:$F,[2]Retiros_dinamica!C:C,"S/I",0) -> S/I | Z21: =_xlfn.XLOOKUP($D21,[2]Retiros_dinamica!$F:$F,[2]Retiros_dinamica!D:D,"S/I",0) -> S/I | AA21: =_xlfn.XLOOKUP($D21,[2]Retiros_dinamica!$F:$F,[2]Retiros_dinamica!E:E,"S/I",0) -> S/I | AB21: =_xlfn.XLOOKUP(C21,[2]CMg!$I$4:$I$106,[2]CMg!$M$4:$M$106,"----",0,1) -> ---- | AH21: =_xlfn.XLOOKUP($E21,'[2]Balance económico'!$C:$C,'[2]Balance económico'!$D:$D,"-",0) -> 1.0058747e+09 | AI21: =_xlfn.XLOOKUP($E21,'[2]Balance económico'!$C:$C,'[2]Balance económico'!$E:$E,"-",0) -> 2.3067282e+09 | AJ21: =_xlfn.XLOOKUP($E21,'[2]Balance económico'!$C:$C,'[2]Balance económico'!$F:$F,"-",0) -> ---- | AK21: =IF(AA21>0,"PPA","-") -> PPA | AL21: {=IFERROR((X21*[2]!Tabla2[Bloque A] + 'BD Centrales 2025'!Y1135*[2]!Tabla2[Bloque B] + 'BD Centrales 2025'!Z1135*[2]!Tabla2[Bloque C])*#REF!,"-")} -> - | AM21: =IFERROR(AH21+AL21,"-") -> - | AN21: =IFERROR((AH21+AI21+AJ21)/(SUMIFS($W$2:$W$1194,$E$2:$E$1194,E21)*1000*#REF!),0) -> 0
A22: 23 | B22: CE03G0035 | C22: PMGD TER PUNITAQUI | D22: ELEKTRA GENERACIÓN S.A. | E22: =_xlfn.XLOOKUP(D22,'[2]Coordinados SEN'!$A:$A,'[2]Coordinados SEN'!$B:$B,"-",0) -> 76.594.660-3 | F22: ELEKTRA GENERACIÓN S.A. | G22: =COUNTIFS($D$2:$D$1194,D22) -> 5 | H22: S/E PUNITAQUI | I22: S/E PUNITAQUI | J22: =_xlfn.XLOOKUP(I22,'[2]Barras CMg'!$E$2:$E$1527,'[2]Barras CMg'!$A$2:$A$1527,"------",0,1) -> ------ | K22: 6 | L22: 2025 | M22: Termoeléctrica | N22: Motor de combustión interna | O22: Pequeños medio de generación distribuida o PMGD | P22: Coquimbo | Q22: Limarí | R22: Punitaqui | S22: Operativa | T22: 06-07-2007 | U22: 9 | V22: 9 | W22: =_xlfn.XLOOKUP(C22,#REF!,#REF!,"S/I",0) -> #REF! | X22: =_xlfn.XLOOKUP($D22,[2]Retiros_dinamica!$F:$F,[2]Retiros_dinamica!B:B,"S/I",0) -> S/I | Y22: =_xlfn.XLOOKUP($D22,[2]Retiros_dinamica!$F:$F,[2]Retiros_dinamica!C:C,"S/I",0) -> S/I | Z22: =_xlfn.XLOOKUP($D22,[2]Retiros_dinamica!$F:$F,[2]Retiros_dinamica!D:D,"S/I",0) -> S/I | AA22: =_xlfn.XLOOKUP($D22,[2]Retiros_dinamica!$F:$F,[2]Retiros_dinamica!E:E,"S/I",0) -> S/I | AB22: =_xlfn.XLOOKUP(C22,[2]CMg!$I$4:$I$106,[2]CMg!$M$4:$M$106,"----",0,1) -> ---- | AH22: =_xlfn.XLOOKUP($E22,'[2]Balance económico'!$C:$C,'[2]Balance económico'!$D:$D,"-",0) -> 1.0058747e+09 | AI22: =_xlfn.XLOOKUP($E22,'[2]Balance económico'!$C:$C,'[2]Balance económico'!$E:$E,"-",0) -> 2.3067282e+09 | AJ22: =_xlfn.XLOOKUP($E22,'[2]Balance económico'!$C:$C,'[2]Balance económico'!$F:$F,"-",0) -> ---- | AK22: =IF(AA22>0,"PPA","-") -> PPA | AL22: {=IFERROR((X22*[2]!Tabla2[Bloque A] + 'BD Centrales 2025'!Y1136*[2]!Tabla2[Bloque B] + 'BD Centrales 2025'!Z1136*[2]!Tabla2[Bloque C])*#REF!,"-")} -> - | AM22: =IFERROR(AH22+AL22,"-") -> - | AN22: =IFERROR((AH22+AI22+AJ22)/(SUMIFS($W$2:$W$1194,$E$2:$E$1194,E22)*1000*#REF!),0) -> 0
A23: 24 | B23: CE01G0644 | C23: PMGD HP DOÑA HILDA | D23: SONNEDIX ENERGY CHILE SPA | E23: =_xlfn.XLOOKUP(D23,'[2]Coordinados SEN'!$A:$A,'[2]Coordinados SEN'!$B:$B,"-",0) -> 77.009.353-8 | F23: GANADERA Y FORESTAL CARRAN LIMITADA | G23: =COUNTIFS($D$2:$D$1194,D23) -> 2 | H23: S/E PICHIRROPULLI 23KV | I23: S/E PICHIRROPULLI 23KV | J23: =_xlfn.XLOOKUP(I23,'[2]Barras CMg'!$E$2:$E$1527,'[2]Barras CMg'!$A$2:$A$1527,"------",0,1) -> ------ | K23: 1 | L23: 2025 | M23: Hidroeléctrica | N23: Minihidro de pasada | O23: Pequeños medio de generación distribuida o PMGD | P23: Los Ríos | Q23: Ranco | R23: Lago Ranco | S23: Operativa | T23: 20-11-2010 | U23: 0.42 | V23: 0.419 | W23: =_xlfn.XLOOKUP(C23,#REF!,#REF!,"S/I",0) -> #REF! | X23: =_xlfn.XLOOKUP($D23,[2]Retiros_dinamica!$F:$F,[2]Retiros_dinamica!B:B,"S/I",0) -> S/I | Y23: =_xlfn.XLOOKUP($D23,[2]Retiros_dinamica!$F:$F,[2]Retiros_dinamica!C:C,"S/I",0) -> S/I | Z23: =_xlfn.XLOOKUP($D23,[2]Retiros_dinamica!$F:$F,[2]Retiros_dinamica!D:D,"S/I",0) -> S/I | AA23: =_xlfn.XLOOKUP($D23,[2]Retiros_dinamica!$F:$F,[2]Retiros_dinamica!E:E,"S/I",0) -> S/I | AB23: =_xlfn.XLOOKUP(C23,[2]CMg!$I$4:$I$106,[2]CMg!$M$4:$M$106,"----",0,1) -> ---- | AH23: =_xlfn.XLOOKUP($E23,'[2]Balance económico'!$C:$C,'[2]Balance económico'!$D:$D,"-",0) -> 0 | AI23: =_xlfn.XLOOKUP($E23,'[2]Balance económico'!$C:$C,'[2]Balance económico'!$E:$E,"-",0) -> 4379795.5 | AJ23: =_xlfn.XLOOKUP($E23,'[2]Balance económico'!$C:$C,'[2]Balance económico'!$F:$F,"-",0) -> ---- | AK23: =IF(AA23>0,"PPA","-") -> PPA | AL23: {=IFERROR((X23*[2]!Tabla2[Bloque A] + 'BD Centrales 2025'!Y839*[2]!Tabla2[Bloque B] + 'BD Centrales 2025'!Z839*[2]!Tabla2[Bloque C])*#REF!,"-")} -> - | AM23: =IFERROR(AH23+AL23,"-") -> - | AN23: =IFERROR((AH23+AI23+AJ23)/(SUMIFS($W$2:$W$1194,$E$2:$E$1194,E23)*1000*#REF!),0) -> 0
A24: 25 | B24: CE01G0137 | C24: PMGD HP PEHUI | D24: GENERADORA ELÉCTRICA PEHUI LTDA | E24: =_xlfn.XLOOKUP(D24,'[2]Coordinados SEN'!$A:$A,'[2]Coordinados SEN'!$B:$B,"-",0) -> 76.067.554-7 | F24: GENERADORA ELÉCTRICA PEHUI LTDA | G24: =COUNTIFS($D$2:$D$1194,D24) -> 1 | H24: ALIMENTADOR PILMAIQUEN - MANTIHUE 23 KV | I24: ALIMENTADOR PILMAIQUEN - MANTIHUE 23KV | J24: =_xlfn.XLOOKUP(I24,'[2]Barras CMg'!$E$2:$E$1527,'[2]Barras CMg'!$A$2:$A$1527,"------",0,1) -> ------ | K24: 1 | L24: 2025 | M24: Hidroeléctrica | N24: Minihidro de pasada | O24: Pequeños medio de generación distribuida o PMGD | P24: Los Ríos | Q24: Ranco | R24: Río Bueno | S24: Operativa | T24: 31-07-2001 | U24: 1.1 | V24: 1.1 | W24: =_xlfn.XLOOKUP(C24,#REF!,#REF!,"S/I",0) -> #REF! | X24: =_xlfn.XLOOKUP($D24,[2]Retiros_dinamica!$F:$F,[2]Retiros_dinamica!B:B,"S/I",0) -> S/I | Y24: =_xlfn.XLOOKUP($D24,[2]Retiros_dinamica!$F:$F,[2]Retiros_dinamica!C:C,"S/I",0) -> S/I | Z24: =_xlfn.XLOOKUP($D24,[2]Retiros_dinamica!$F:$F,[2]Retiros_dinamica!D:D,"S/I",0) -> S/I | AA24: =_xlfn.XLOOKUP($D24,[2]Retiros_dinamica!$F:$F,[2]Retiros_dinamica!E:E,"S/I",0) -> S/I | AB24: =_xlfn.XLOOKUP(C24,[2]CMg!$I$4:$I$106,[2]CMg!$M$4:$M$106,"----",0,1) -> ---- | AH24: =_xlfn.XLOOKUP($E24,'[2]Balance económico'!$C:$C,'[2]Balance económico'!$D:$D,"-",0) -> -14095.514 | AI24: =_xlfn.XLOOKUP($E24,'[2]Balance económico'!$C:$C,'[2]Balance económico'!$E:$E,"-",0) -> 42595873 | AJ24: =_xlfn.XLOOKUP($E24,'[2]Balance económico'!$C:$C,'[2]Balance económico'!$F:$F,"-",0) -> ---- | AK24: =IF(AA24>0,"PPA","-") -> PPA | AL24: {=IFERROR((X24*[2]!Tabla2[Bloque A] + 'BD Centrales 2025'!Y864*[2]!Tabla2[Bloque B] + 'BD Centrales 2025'!Z864*[2]!Tabla2[Bloque C])*#REF!,"-")} -> - | AM24: =IFERROR(AH24+AL24,"-") -> - | AN24: =IFERROR((AH24+AI24+AJ24)/(SUMIFS($W$2:$W$1194,$E$2:$E$1194,E24)*1000*#REF!),0) -> 0
A25: 27 | B25: CE17G0004 | C25: HP JUNCALITO | D25: COLBÚN S.A. | E25: =_xlfn.XLOOKUP(D25,'[2]Coordinados SEN'!$A:$A,'[2]Coordinados SEN'!$B:$B,"-",0) -> 96.505.760-9 | F25: COLBÚN S.A. | G25: =COUNTIFS($D$2:$D$1194,D25) -> 29 | H25: S/E HORNITOS 220KV | I25: S/E LOS MAQUIS 220KV | J25: =_xlfn.XLOOKUP(I25,'[2]Barras CMg'!$E$2:$E$1527,'[2]Barras CMg'!$A$2:$A$1527,"------",0,1) -> L.MAQUIS______220 | K25: 1 | L25: 2025 | M25: Hidroeléctrica | N25: Minihidro de pasada | O25: Pequeños medio de generación o PMG | P25: Valparaíso | Q25: Los Andes | R25: Los Andes | S25: Operativa | T25: 31-07-1994 | U25: 1.52 | V25: 1.52 | W25: =_xlfn.XLOOKUP(C25,#REF!,#REF!,"S/I",0) -> #REF! | X25: =_xlfn.XLOOKUP($D25,[2]Retiros_dinamica!$F:$F,[2]Retiros_dinamica!B:B,"S/I",0) -> 3718226.1 | Y25: =_xlfn.XLOOKUP($D25,[2]Retiros_dinamica!$F:$F,[2]Retiros_dinamica!C:C,"S/I",0) -> 3629256.6 | Z25: =_xlfn.XLOOKUP($D25,[2]Retiros_dinamica!$F:$F,[2]Retiros_dinamica!D:D,"S/I",0) -> 1641521.7 | AA25: =_xlfn.XLOOKUP($D25,[2]Retiros_dinamica!$F:$F,[2]Retiros_dinamica!E:E,"S/I",0) -> 8989004.4 | AB25: =_xlfn.XLOOKUP(C25,[2]CMg!$I$4:$I$106,[2]CMg!$M$4:$M$106,"----",0,1) -> ---- | AC25: =_xlfn.XLOOKUP(C25,[2]CMg!$A$4:$A$106,[2]CMg!$B$4:$B$106,"----",0,1) -> ---- | AD25: =_xlfn.XLOOKUP(C25,'[3]Promedio solar Cmg'!$A$4:$A$106,'[3]Promedio solar Cmg'!$B$4:$B$106,"----",0,1) -> ---- | AH25: =_xlfn.XLOOKUP($E25,'[2]Balance económico'!$C:$C,'[2]Balance económico'!$D:$D,"-",0) -> -1.345249e+09 | AI25: =_xlfn.XLOOKUP($E25,'[2]Balance económico'!$C:$C,'[2]Balance económico'!$E:$E,"-",0) -> 1.898617e+09 | AJ25: =_xlfn.XLOOKUP($E25,'[2]Balance económico'!$C:$C,'[2]Balance económico'!$F:$F,"-",0) -> 3.0881173e+10 | AK25: =IF(AA25>0,"PPA","-") -> PPA | AL25: {=IFERROR((X25*[2]!Tabla2[Bloque A] + 'BD Centrales 2025'!Y60*[2]!Tabla2[Bloque B] + 'BD Centrales 2025'!Z60*[2]!Tabla2[Bloque C])*#REF!,"-")} -> - | AM25: =IFERROR(AH25+AL25,"-") -> - | AN25: =IFERROR((AH25+AI25+AJ25)/(SUMIFS($W$2:$W$1194,$E$2:$E$1194,E25)*1000*#REF!),0) -> 0
A26: 28 | B26: CE04G0054 | C26: PMGD HP TRUFULTRUFUL | D26: ENERBOSCH S.A. | E26: =_xlfn.XLOOKUP(D26,'[2]Coordinados SEN'!$A:$A,'[2]Coordinados SEN'!$B:$B,"-",0) -> 76.028.873-K | F26: ENERBOSCH S.A. | G26: =COUNTIFS($D$2:$D$1194,D26) -> 5 | H26: ID 1075 BA S/E LICANCO 23KV | I26: S/E LICANCO 23KV | J26: =_xlfn.XLOOKUP(I26,'[2]Barras CMg'!$E$2:$E$1527,'[2]Barras CMg'!$A$2:$A$1527,"------",0,1) -> ------ | K26: 1 | L26: 2025 | M26: Hidroeléctrica | N26: Minihidro de pasada | O26: Pequeños medio de generación distribuida o PMGD | P26: La Araucanía | Q26: Cautín | R26: Melipeuco | S26: Operativa | T26: 16-09-2009 | U26: 0.836 | V26: 0.819 | W26: =_xlfn.XLOOKUP(C26,#REF!,#REF!,"S/I",0) -> #REF! | X26: =_xlfn.XLOOKUP($D26,[2]Retiros_dinamica!$F:$F,[2]Retiros_dinamica!B:B,"S/I",0) -> S/I | Y26: =_xlfn.XLOOKUP($D26,[2]Retiros_dinamica!$F:$F,[2]Retiros_dinamica!C:C,"S/I",0) -> S/I | Z26: =_xlfn.XLOOKUP($D26,[2]Retiros_dinamica!$F:$F,[2]Retiros_dinamica!D:D,"S/I",0) -> S/I | AA26: =_xlfn.XLOOKUP($D26,[2]Retiros_dinamica!$F:$F,[2]Retiros_dinamica!E:E,"S/I",0) -> S/I | AB26: =_xlfn.XLOOKUP(C26,[2]CMg!$I$4:$I$106,[2]CMg!$M$4:$M$106,"----",0,1) -> ---- | AH26: =_xlfn.XLOOKUP($E26,'[2]Balance económico'!$C:$C,'[2]Balance económico'!$D:$D,"-",0) -> 2.6053849e+08 | AI26: =_xlfn.XLOOKUP($E26,'[2]Balance económico'!$C:$C,'[2]Balance económico'!$E:$E,"-",0) -> 2.2312454e+08 | AJ26: =_xlfn.XLOOKUP($E26,'[2]Balance económico'!$C:$C,'[2]Balance económico'!$F:$F,"-",0) -> ---- | AK26: =IF(AA26>0,"PPA","-") -> PPA | AL26: {=IFERROR((X26*[2]!Tabla2[Bloque A] + 'BD Centrales 2025'!Y914*[2]!Tabla2[Bloque B] + 'BD Centrales 2025'!Z914*[2]!Tabla2[Bloque C])*#REF!,"-")} -> - | AM26: =IFERROR(AH26+AL26,"-") -> - | AN26: =IFERROR((AH26+AI26+AJ26)/(SUMIFS($W$2:$W$1194,$E$2:$E$1194,E26)*1000*#REF!),0) -> 0
A27: 29 | B27: CE01G1002 | C27: PMGD HP DONGO | D27: DONGO ENERGÍA SPA | E27: =_xlfn.XLOOKUP(D27,'[2]Coordinados SEN'!$A:$A,'[2]Coordinados SEN'!$B:$B,"-",0) -> 77.930.796-4 | F27: DONGO ENERGÍA SPA | G27: =COUNTIFS($D$2:$D$1194,D27) -> 1 | H27: S/E CENTRAL EL DONGO | I27: S/E CENTRAL EL DONGO | J27: =_xlfn.XLOOKUP(I27,'[2]Barras CMg'!$E$2:$E$1527,'[2]Barras CMg'!$A$2:$A$1527,"------",0,1) -> ------ | K27: 2 | L27: 2025 | M27: Hidroeléctrica | N27: Minihidro de pasada | O27: Pequeños medio de generación distribuida o PMGD | P27: Los Lagos | Q27: Chiloé | R27: Chonchi | S27: Operativa | T27: 14-12-2010 | U27: 6 | V27: 5.9976 | W27: =_xlfn.XLOOKUP(C27,#REF!,#REF!,"S/I",0) -> #REF! | X27: =_xlfn.XLOOKUP($D27,[2]Retiros_dinamica!$F:$F,[2]Retiros_dinamica!B:B,"S/I",0) -> S/I | Y27: =_xlfn.XLOOKUP($D27,[2]Retiros_dinamica!$F:$F,[2]Retiros_dinamica!C:C,"S/I",0) -> S/I | Z27: =_xlfn.XLOOKUP($D27,[2]Retiros_dinamica!$F:$F,[2]Retiros_dinamica!D:D,"S/I",0) -> S/I | AA27: =_xlfn.XLOOKUP($D27,[2]Retiros_dinamica!$F:$F,[2]Retiros_dinamica!E:E,"S/I",0) -> S/I | AB27: =_xlfn.XLOOKUP(C27,[2]CMg!$I$4:$I$106,[2]CMg!$M$4:$M$106,"----",0,1) -> ---- | AH27: =_xlfn.XLOOKUP($E27,'[2]Balance económico'!$C:$C,'[2]Balance económico'!$D:$D,"-",0) -> 21306501 | AI27: =_xlfn.XLOOKUP($E27,'[2]Balance económico'!$C:$C,'[2]Balance económico'!$E:$E,"-",0) -> 2.3285773e+08 | AJ27: =_xlfn.XLOOKUP($E27,'[2]Balance económico'!$C:$C,'[2]Balance económico'!$F:$F,"-",0) -> ---- | AK27: =IF(AA27>0,"PPA","-") -> PPA | AL27: {=IFERROR((X27*[2]!Tabla2[Bloque A] + 'BD Centrales 2025'!Y920*[2]!Tabla2[Bloque B] + 'BD Centrales 2025'!Z920*[2]!Tabla2[Bloque C])*#REF!,"-")} -> - | AM27: =IFERROR(AH27+AL27,"-") -> - | AN27: =IFERROR((AH27+AI27+AJ27)/(SUMIFS($W$2:$W$1194,$E$2:$E$1194,E27)*1000*#REF!),0) -> 0
A28: 30 | B28: CE01G0083 | C28: PMGD HP MALLARAUCO | D28: HIDROELÉCTRICA MALLARAUCO S.A. | E28: =_xlfn.XLOOKUP(D28,'[2]Coordinados SEN'!$A:$A,'[2]Coordinados SEN'!$B:$B,"-",0) -> 76.055.136-8 | F28: HIDROELÉCTRICA MALLARAUCO S.A. | G28: =COUNTIFS($D$2:$D$1194,D28) -> 1 | H28: S/E EL PAICO 13.2KV | I28: S/E EL PAICO 13.2KV | J28: =_xlfn.XLOOKUP(I28,'[2]Barras CMg'!$E$2:$E$1527,'[2]Barras CMg'!$A$2:$A$1527,"------",0,1) -> ELPAICO_______013 | K28: 1 | L28: 2025 | M28: Hidroeléctrica | N28: Minihidro de pasada | O28: Pequeños medio de generación distribuida o PMGD | P28: Metropolitana de Santiago | Q28: Melipilla | R28: Melipilla | S28: Operativa | T28: 24-06-2011 | U28: 3.4 | V28: 3.3915 | W28: =_xlfn.XLOOKUP(C28,#REF!,#REF!,"S/I",0) -> #REF! | X28: =_xlfn.XLOOKUP($D28,[2]Retiros_dinamica!$F:$F,[2]Retiros_dinamica!B:B,"S/I",0) -> S/I | Y28: =_xlfn.XLOOKUP($D28,[2]Retiros_dinamica!$F:$F,[2]Retiros_dinamica!C:C,"S/I",0) -> S/I | Z28: =_xlfn.XLOOKUP($D28,[2]Retiros_dinamica!$F:$F,[2]Retiros_dinamica!D:D,"S/I",0) -> S/I | AA28: =_xlfn.XLOOKUP($D28,[2]Retiros_dinamica!$F:$F,[2]Retiros_dinamica!E:E,"S/I",0) -> S/I | AB28: =_xlfn.XLOOKUP(C28,[2]CMg!$I$4:$I$106,[2]CMg!$M$4:$M$106,"----",0,1) -> ---- | AH28: =_xlfn.XLOOKUP($E28,'[2]Balance económico'!$C:$C,'[2]Balance económico'!$D:$D,"-",0) -> 3.2747515e+08 | AI28: =_xlfn.XLOOKUP($E28,'[2]Balance económico'!$C:$C,'[2]Balance económico'!$E:$E,"-",0) -> 1.9464081e+08 | AJ28: =_xlfn.XLOOKUP($E28,'[2]Balance económico'!$C:$C,'[2]Balance económico'!$F:$F,"-",0) -> ---- | AK28: =IF(AA28>0,"PPA","-") -> PPA | AL28: {=IFERROR((X28*[2]!Tabla2[Bloque A] + 'BD Centrales 2025'!Y907*[2]!Tabla2[Bloque B] + 'BD Centrales 2025'!Z907*[2]!Tabla2[Bloque C])*#REF!,"-")} -> - | AM28: =IFERROR(AH28+AL28,"-") -> - | AN28: =IFERROR((AH28+AI28+AJ28)/(SUMIFS($W$2:$W$1194,$E$2:$E$1194,E28)*1000*#REF!),0) -> 0
A29: 31 | B29: CE01G0063 | C29: PMGD HP RIO TRUENO | D29: HIDROELÉCTRICA TRUENO S.A. | E29: =_xlfn.XLOOKUP(D29,'[2]Coordinados SEN'!$A:$A,'[2]Coordinados SEN'!$B:$B,"-",0) -> 76.834.000-5 | F29: HIDROELÉCTRICA TRUENO S.A. | G29: =COUNTIFS($D$2:$D$1194,D29) -> 1 | H29: S/E LAUTARO 13.2KV | I29: S/E LAUTARO 13.2KV | J29: =_xlfn.XLOOKUP(I29,'[2]Barras CMg'!$E$2:$E$1527,'[2]Barras CMg'!$A$2:$A$1527,"------",0,1) -> LAUTARO_______013 | K29: 2 | L29: 2025 | M29: Hidroeléctrica | N29: Minihidro de pasada | O29: Pequeños medio de generación distribuida o PMGD | P29: La Araucanía | Q29: Cautín | R29: Vilcún | S29: Operativa | T29: 06-06-2010 | U29: 5.6 | V29: 5.59 | W29: =_xlfn.XLOOKUP(C29,#REF!,#REF!,"S/I",0) -> #REF! | X29: =_xlfn.XLOOKUP($D29,[2]Retiros_dinamica!$F:$F,[2]Retiros_dinamica!B:B,"S/I",0) -> S/I | Y29: =_xlfn.XLOOKUP($D29,[2]Retiros_dinamica!$F:$F,[2]Retiros_dinamica!C:C,"S/I",0) -> S/I | Z29: =_xlfn.XLOOKUP($D29,[2]Retiros_dinamica!$F:$F,[2]Retiros_dinamica!D:D,"S/I",0) -> S/I | AA29: =_xlfn.XLOOKUP($D29,[2]Retiros_dinamica!$F:$F,[2]Retiros_dinamica!E:E,"S/I",0) -> S/I | AB29: =_xlfn.XLOOKUP(C29,[2]CMg!$I$4:$I$106,[2]CMg!$M$4:$M$106,"----",0,1) -> ---- | AH29: =_xlfn.XLOOKUP($E29,'[2]Balance económico'!$C:$C,'[2]Balance económico'!$D:$D,"-",0) -> 2.1821042e+08 | AI29: =_xlfn.XLOOKUP($E29,'[2]Balance económico'!$C:$C,'[2]Balance económico'!$E:$E,"-",0) -> 1.197106e+08 | AJ29: =_xlfn.XLOOKUP($E29,'[2]Balance económico'!$C:$C,'[2]Balance económico'!$F:$F,"-",0) -> ---- | AK29: =IF(AA29>0,"PPA","-") -> PPA | AL29: {=IFERROR((X29*[2]!Tabla2[Bloque A] + 'BD Centrales 2025'!Y894*[2]!Tabla2[Bloque B] + 'BD Centrales 2025'!Z894*[2]!Tabla2[Bloque C])*#REF!,"-")} -> - | AM29: =IFERROR(AH29+AL29,"-") -> - | AN29: =IFERROR((AH29+AI29+AJ29)/(SUMIFS($W$2:$W$1194,$E$2:$E$1194,E29)*1000*#REF!),0) -> 0
A30: 32 | B30: CE01G0060 | C30: PMGD HP LA PALOMA | D30: HIDROPALOMA S.A. | E30: =_xlfn.XLOOKUP(D30,'[2]Coordinados SEN'!$A:$A,'[2]Coordinados SEN'!$B:$B,"-",0) -> 76.849.580-7 | F30: HIDROPALOMA S.A. | G30: =COUNTIFS($D$2:$D$1194,D30) -> 1 | H30: S/E MONTE PATRIA 13.2KV | I30: S/E MONTE PATRIA 13.2KV | J30: =_xlfn.XLOOKUP(I30,'[2]Barras CMg'!$E$2:$E$1527,'[2]Barras CMg'!$A$2:$A$1527,"------",0,1) -> M.PATRIA______013 | K30: 2 | L30: 2025 | M30: Hidroeléctrica | N30: Minihidro de pasada | O30: Pequeños medio de generación distribuida o PMGD | P30: Coquimbo | Q30: Limarí | R30: Ovalle | S30: Operativa | T30: 29-03-2010 | U30: 4.6 | V30: 4.416 | W30: =_xlfn.XLOOKUP(C30,#REF!,#REF!,"S/I",0) -> #REF! | X30: =_xlfn.XLOOKUP($D30,[2]Retiros_dinamica!$F:$F,[2]Retiros_dinamica!B:B,"S/I",0) -> S/I | Y30: =_xlfn.XLOOKUP($D30,[2]Retiros_dinamica!$F:$F,[2]Retiros_dinamica!C:C,"S/I",0) -> S/I | Z30: =_xlfn.XLOOKUP($D30,[2]Retiros_dinamica!$F:$F,[2]Retiros_dinamica!D:D,"S/I",0) -> S/I | AA30: =_xlfn.XLOOKUP($D30,[2]Retiros_dinamica!$F:$F,[2]Retiros_dinamica!E:E,"S/I",0) -> S/I | AB30: =_xlfn.XLOOKUP(C30,[2]CMg!$I$4:$I$106,[2]CMg!$M$4:$M$106,"----",0,1) -> ---- | AH30: =_xlfn.XLOOKUP($E30,'[2]Balance económico'!$C:$C,'[2]Balance económico'!$D:$D,"-",0) -> 0 | AI30: =_xlfn.XLOOKUP($E30,'[2]Balance económico'!$C:$C,'[2]Balance económico'!$E:$E,"-",0) -> 1.3552885e+08 | AJ30: =_xlfn.XLOOKUP($E30,'[2]Balance económico'!$C:$C,'[2]Balance económico'!$F:$F,"-",0) -> ---- | AK30: =IF(AA30>0,"PPA","-") -> PPA | AL30: {=IFERROR((X30*[2]!Tabla2[Bloque A] + 'BD Centrales 2025'!Y899*[2]!Tabla2[Bloque B] + 'BD Centrales 2025'!Z899*[2]!Tabla2[Bloque C])*#REF!,"-")} -> - | AM30: =IFERROR(AH30+AL30,"-") -> - | AN30: =IFERROR((AH30+AI30+AJ30)/(SUMIFS($W$2:$W$1194,$E$2:$E$1194,E30)*1000*#REF!),0) -> 0
A31: 35 | B31: CE01G0109 | C31: PMGD HP EL TARTARO | D31: ON-GROUP S.A. | E31: =_xlfn.XLOOKUP(D31,'[2]Coordinados SEN'!$A:$A,'[2]Coordinados SEN'!$B:$B,"-",0) -> 96.827.870-3 | F31: WENKE Y CIA LTDA | G31: =COUNTIFS($D$2:$D$1194,D31) -> 2 | H31: ALIMENTADOR PUTAENDO 12 KV | I31: ALIMENTADOR PUTAENDO 12KV | J31: =_xlfn.XLOOKUP(I31,'[2]Barras CMg'!$E$2:$E$1527,'[2]Barras CMg'!$A$2:$A$1527,"------",0,1) -> ------ | K31: 1 | L31: 2025 | M31: Hidroeléctrica | N31: Minihidro de pasada | O31: Pequeños medio de generación distribuida o PMGD | P31: Valparaíso | Q31: San Felipe de Aconcagua | R31: Putaendo | S31: Operativa | T31: 01-09-2010 | U31: 0.104 | V31: 0.1037 | W31: =_xlfn.XLOOKUP(C31,#REF!,#REF!,"S/I",0) -> #REF! | X31: =_xlfn.XLOOKUP($D31,[2]Retiros_dinamica!$F:$F,[2]Retiros_dinamica!B:B,"S/I",0) -> 8734.4032 | Y31: =_xlfn.XLOOKUP($D31,[2]Retiros_dinamica!$F:$F,[2]Retiros_dinamica!C:C,"S/I",0) -> 9511.5209 | Z31: =_xlfn.XLOOKUP($D31,[2]Retiros_dinamica!$F:$F,[2]Retiros_dinamica!D:D,"S/I",0) -> 4851.7833 | AA31: =_xlfn.XLOOKUP($D31,[2]Retiros_dinamica!$F:$F,[2]Retiros_dinamica!E:E,"S/I",0) -> 23097.707 | AB31: =_xlfn.XLOOKUP(C31,[2]CMg!$I$4:$I$106,[2]CMg!$M$4:$M$106,"----",0,1) -> ---- | AH31: =_xlfn.XLOOKUP($E31,'[2]Balance económico'!$C:$C,'[2]Balance económico'!$D:$D,"-",0) -> -9.6924181e+08 | AI31: =_xlfn.XLOOKUP($E31,'[2]Balance económico'!$C:$C,'[2]Balance económico'!$E:$E,"-",0) -> -1.6593366e+08 | AJ31: =_xlfn.XLOOKUP($E31,'[2]Balance económico'!$C:$C,'[2]Balance económico'!$F:$F,"-",0) -> 65657881 | AK31: =IF(AA31>0,"PPA","-") -> PPA | AL31: {=IFERROR((X31*[2]!Tabla2[Bloque A] + 'BD Centrales 2025'!Y835*[2]!Tabla2[Bloque B] + 'BD Centrales 2025'!Z835*[2]!Tabla2[Bloque C])*#REF!,"-")} -> - | AM31: =IFERROR(AH31+AL31,"-") -> - | AN31: =IFERROR((AH31+AI31+AJ31)/(SUMIFS($W$2:$W$1194,$E$2:$E$1194,E31)*1000*#REF!),0) -> 0
A32: 36 | B32: CE01G0056 | C32: PMGD TER ORAFTI | D32: ORAFTI CHILE S.A. | E32: =_xlfn.XLOOKUP(D32,'[2]Coordinados SEN'!$A:$A,'[2]Coordinados SEN'!$B:$B,"-",0) -> 77.894.990-3 | F32: ORAFTI CHILE S.A. | G32: =COUNTIFS($D$2:$D$1194,D32) -> 1 | H32: Alimentador Bulnes / SE Cabrero | I32: S/E CABRERO | J32: =_xlfn.XLOOKUP(I32,'[2]Barras CMg'!$E$2:$E$1527,'[2]Barras CMg'!$A$2:$A$1527,"------",0,1) -> ------ | K32: 3 | L32: 2025 | M32: Termoeléctrica | N32: Motor de combustión interna | O32: Pequeños medio de generación distribuida o PMGD | P32: Ñuble | Q32: Diguillín | R32: Pemuco | S32: Operativa | T32: 27-02-2009 | U32: 8.2 | V32: 7.2 | W32: =_xlfn.XLOOKUP(C32,#REF!,#REF!,"S/I",0) -> #REF! | X32: =_xlfn.XLOOKUP($D32,[2]Retiros_dinamica!$F:$F,[2]Retiros_dinamica!B:B,"S/I",0) -> S/I | Y32: =_xlfn.XLOOKUP($D32,[2]Retiros_dinamica!$F:$F,[2]Retiros_dinamica!C:C,"S/I",0) -> S/I | Z32: =_xlfn.XLOOKUP($D32,[2]Retiros_dinamica!$F:$F,[2]Retiros_dinamica!D:D,"S/I",0) -> S/I | AA32: =_xlfn.XLOOKUP($D32,[2]Retiros_dinamica!$F:$F,[2]Retiros_dinamica!E:E,"S/I",0) -> S/I | AB32: =_xlfn.XLOOKUP(C32,[2]CMg!$I$4:$I$106,[2]CMg!$M$4:$M$106,"----",0,1) -> ---- | AH32: =_xlfn.XLOOKUP($E32,'[2]Balance económico'!$C:$C,'[2]Balance económico'!$D:$D,"-",0) -> 1.0068583e+08 | AI32: =_xlfn.XLOOKUP($E32,'[2]Balance económico'!$C:$C,'[2]Balance económico'!$E:$E,"-",0) -> ---- | AJ32: =_xlfn.XLOOKUP($E32,'[2]Balance económico'!$C:$C,'[2]Balance económico'!$F:$F,"-",0) -> ---- | AK32: =IF(AA32>0,"PPA","-") -> PPA | AL32: {=IFERROR((X32*[2]!Tabla2[Bloque A] + 'BD Centrales 2025'!Y1193*[2]!Tabla2[Bloque B] + 'BD Centrales 2025'!Z1193*[2]!Tabla2[Bloque C])*#REF!,"-")} -> - | AM32: =IFERROR(AH32+AL32,"-") -> - | AN32: =IFERROR((AH32+AI32+AJ32)/(SUMIFS($W$2:$W$1194,$E$2:$E$1194,E32)*1000*#REF!),0) -> 0
A33: 37 | B33: CE01G0040 | C33: PMGD HP PUCLARO | D33: HIDROELECTRICA PUCLARO S.A. | E33: =_xlfn.XLOOKUP(D33,'[2]Coordinados SEN'!$A:$A,'[2]Coordinados SEN'!$B:$B,"-",0) -> 99.589.620-6 | F33: HIDROELECTRICA PUCLARO S.A. | G33: =COUNTIFS($D$2:$D$1194,D33) -> 1 | H33: MARQUESA 23 KV | I33: MARQUESA 23KV | J33: =_xlfn.XLOOKUP(I33,'[2]Barras CMg'!$E$2:$E$1527,'[2]Barras CMg'!$A$2:$A$1527,"------",0,1) -> ------ | K33: 2 | L33: 2025 | M33: Hidroeléctrica | N33: Minihidro de pasada | O33: Pequeños medio de generación distribuida o PMGD | P33: Coquimbo | Q33: Elqui | R33: Vicuña | S33: Operativa | T33: 01-05-2008 | U33: 5.6 | V33: 5.376 | W33: =_xlfn.XLOOKUP(C33,#REF!,#REF!,"S/I",0) -> #REF! | X33: =_xlfn.XLOOKUP($D33,[2]Retiros_dinamica!$F:$F,[2]Retiros_dinamica!B:B,"S/I",0) -> S/I | Y33: =_xlfn.XLOOKUP($D33,[2]Retiros_dinamica!$F:$F,[2]Retiros_dinamica!C:C,"S/I",0) -> S/I | Z33: =_xlfn.XLOOKUP($D33,[2]Retiros_dinamica!$F:$F,[2]Retiros_dinamica!D:D,"S/I",0) -> S/I | AA33: =_xlfn.XLOOKUP($D33,[2]Retiros_dinamica!$F:$F,[2]Retiros_dinamica!E:E,"S/I",0) -> S/I | AB33: =_xlfn.XLOOKUP(C33,[2]CMg!$I$4:$I$106,[2]CMg!$M$4:$M$106,"----",0,1) -> ---- | AH33: =_xlfn.XLOOKUP($E33,'[2]Balance económico'!$C:$C,'[2]Balance económico'!$D:$D,"-",0) -> 2.9514139e+08 | AI33: =_xlfn.XLOOKUP($E33,'[2]Balance económico'!$C:$C,'[2]Balance económico'!$E:$E,"-",0) -> 2.5817632e+08 | AJ33: =_xlfn.XLOOKUP($E33,'[2]Balance económico'!$C:$C,'[2]Balance económico'!$F:$F,"-",0) -> ---- | AK33: =IF(AA33>0,"PPA","-") -> PPA | AL33: {=IFERROR((X33*[2]!Tabla2[Bloque A] + 'BD Centrales 2025'!Y921*[2]!Tabla2[Bloque B] + 'BD Centrales 2025'!Z921*[2]!Tabla2[Bloque C])*#REF!,"-")} -> - | AM33: =IFERROR(AH33+AL33,"-") -> - | AN33: =IFERROR((AH33+AI33+AJ33)/(SUMIFS($W$2:$W$1194,$E$2:$E$1194,E33)*1000*#REF!),0) -> 0
A34: 39 | B34: CE02G0018 | C34: PMGD TER CAÑETE | D34: SOCIEDAD GENERADORA AUSTRAL S.A. | E34: =_xlfn.XLOOKUP(D34,'[2]Coordinados SEN'!$A:$A,'[2]Coordinados SEN'!$B:$B,"-",0) -> 99.528.750-1 | F34: SAGESA S.A. | G34: =COUNTIFS($D$2:$D$1194,D34) -> 23 | H34: S/E TRES PINOS 23KV | I34: S/E TRES PINOS 23KV | J34: =_xlfn.XLOOKUP(I34,'[2]Barras CMg'!$E$2:$E$1527,'[2]Barras CMg'!$A$2:$A$1527,"------",0,1) -> ------ | K34: 6 | L34: 2025 | M34: Termoeléctrica | N34: Motor de combustión interna | O34: Pequeños medio de generación distribuida o PMGD | P34: Biobío | Q34: Arauco | R34: Cañete | S34: Operativa | T34: 29-05-2007 | U34: 4.4 | V34: 4 | W34: =_xlfn.XLOOKUP(C34,#REF!,#REF!,"S/I",0) -> #REF! | X34: =_xlfn.XLOOKUP($D34,[2]Retiros_dinamica!$F:$F,[2]Retiros_dinamica!B:B,"S/I",0) -> S/I | Y34: =_xlfn.XLOOKUP($D34,[2]Retiros_dinamica!$F:$F,[2]Retiros_dinamica!C:C,"S/I",0) -> S/I | Z34: =_xlfn.XLOOKUP($D34,[2]Retiros_dinamica!$F:$F,[2]Retiros_dinamica!D:D,"S/I",0) -> S/I | AA34: =_xlfn.XLOOKUP($D34,[2]Retiros_dinamica!$F:$F,[2]Retiros_dinamica!E:E,"S/I",0) -> S/I | AB34: =_xlfn.XLOOKUP(C34,[2]CMg!$I$4:$I$106,[2]CMg!$M$4:$M$106,"----",0,1) -> ---- | AH34: =_xlfn.XLOOKUP($E34,'[2]Balance económico'!$C:$C,'[2]Balance económico'!$D:$D,"-",0) -> -5.0996618e+09 | AI34: =_xlfn.XLOOKUP($E34,'[2]Balance económico'!$C:$C,'[2]Balance económico'!$E:$E,"-",0) -> 1.7619185e+09 | AJ34: =_xlfn.XLOOKUP($E34,'[2]Balance económico'!$C:$C,'[2]Balance económico'!$F:$F,"-",0) -> 5.7097079e+08 | AK34: =IF(AA34>0,"PPA","-") -> PPA | AL34: {=IFERROR((X34*[2]!Tabla2[Bloque A] + 'BD Centrales 2025'!Y1085*[2]!Tabla2[Bloque B] + 'BD Centrales 2025'!Z1085*[2]!Tabla2[Bloque C])*#REF!,"-")} -> - | AM34: =IFERROR(AH34+AL34,"-") -> - | AN34: =IFERROR((AH34+AI34+AJ34)/(SUMIFS($W$2:$W$1194,$E$2:$E$1194,E34)*1000*#REF!),0) -> 0
A35: 40 | B35: CE03G0018 | C35: PMGD TER CHUFKEN | D35: SOCIEDAD GENERADORA AUSTRAL S.A. | E35: =_xlfn.XLOOKUP(D35,'[2]Coordinados SEN'!$A:$A,'[2]Coordinados SEN'!$B:$B,"-",0) -> 99.528.750-1 | F35: SAGESA S.A. | G35: =COUNTIFS($D$2:$D$1194,D35) -> 23 | H35: S/E TRAIGUEN 13.2KV | I35: S/E TRAIGUEN 13.2KV | J35: =_xlfn.XLOOKUP(I35,'[2]Barras CMg'!$E$2:$E$1527,'[2]Barras CMg'!$A$2:$A$1527,"------",0,1) -> TRAIGUEN______013 | K35: 2 | L35: 2025 | M35: Termoeléctrica | N35: Motor de combustión interna | O35: Pequeños medio de generación distribuida o PMGD | P35: La Araucanía | Q35: Malleco | R35: Traiguén | S35: Operativa | T35: 29-05-2007 | U35: 2.4 | V35: 2.4 | W35: =_xlfn.XLOOKUP(C35,#REF!,#REF!,"S/I",0) -> #REF! | X35: =_xlfn.XLOOKUP($D35,[2]Retiros_dinamica!$F:$F,[2]Retiros_dinamica!B:B,"S/I",0) -> S/I | Y35: =_xlfn.XLOOKUP($D35,[2]Retiros_dinamica!$F:$F,[2]Retiros_dinamica!C:C,"S/I",0) -> S/I | Z35: =_xlfn.XLOOKUP($D35,[2]Retiros_dinamica!$F:$F,[2]Retiros_dinamica!D:D,"S/I",0) -> S/I | AA35: =_xlfn.XLOOKUP($D35,[2]Retiros_dinamica!$F:$F,[2]Retiros_dinamica!E:E,"S/I",0) -> S/I | AB35: =_xlfn.XLOOKUP(C35,[2]CMg!$I$4:$I$106,[2]CMg!$M$4:$M$106,"----",0,1) -> ---- | AH35: =_xlfn.XLOOKUP($E35,'[2]Balance económico'!$C:$C,'[2]Balance económico'!$D:$D,"-",0) -> -5.0996618e+09 | AI35: =_xlfn.XLOOKUP($E35,'[2]Balance económico'!$C:$C,'[2]Balance económico'!$E:$E,"-",0) -> 1.7619185e+09 | AJ35: =_xlfn.XLOOKUP($E35,'[2]Balance económico'!$C:$C,'[2]Balance económico'!$F:$F,"-",0) -> 5.7097079e+08 | AK35: =IF(AA35>0,"PPA","-") -> PPA | AL35: {=IFERROR((X35*[2]!Tabla2[Bloque A] + 'BD Centrales 2025'!Y1086*[2]!Tabla2[Bloque B] + 'BD Centrales 2025'!Z1086*[2]!Tabla2[Bloque C])*#REF!,"-")} -> - | AM35: =IFERROR(AH35+AL35,"-") -> - | AN35: =IFERROR((AH35+AI35+AJ35)/(SUMIFS($W$2:$W$1194,$E$2:$E$1194,E35)*1000*#REF!),0) -> 0
A36: 42 | B36: CE06G0018 | C36: PMGD TER CURACAUTIN | D36: SOCIEDAD GENERADORA AUSTRAL S.A. | E36: =_xlfn.XLOOKUP(D36,'[2]Coordinados SEN'!$A:$A,'[2]Coordinados SEN'!$B:$B,"-",0) -> 99.528.750-1 | F36: SAGESA S.A. | G36: =COUNTIFS($D$2:$D$1194,D36) -> 23 | H36: S/E CURACAUTIN 13.2KV | I36: S/E CURACAUTIN 13.2KV | J36: =_xlfn.XLOOKUP(I36,'[2]Barras CMg'!$E$2:$E$1527,'[2]Barras CMg'!$A$2:$A$1527,"------",0,1) -> CURACAUTIN____013 | K36: 3 | L36: 2025 | M36: Termoeléctrica | N36: Motor de combustión interna | O36: Pequeños medio de generación distribuida o PMGD | P36: La Araucanía | Q36: Malleco | R36: Curacautín | S36: Operativa | T36: 29-05-2007 | U36: 2.4 | V36: 2.4 | W36: =_xlfn.XLOOKUP(C36,#REF!,#REF!,"S/I",0) -> #REF! | X36: =_xlfn.XLOOKUP($D36,[2]Retiros_dinamica!$F:$F,[2]Retiros_dinamica!B:B,"S/I",0) -> S/I | Y36: =_xlfn.XLOOKUP($D36,[2]Retiros_dinamica!$F:$F,[2]Retiros_dinamica!C:C,"S/I",0) -> S/I | Z36: =_xlfn.XLOOKUP($D36,[2]Retiros_dinamica!$F:$F,[2]Retiros_dinamica!D:D,"S/I",0) -> S/I | AA36: =_xlfn.XLOOKUP($D36,[2]Retiros_dinamica!$F:$F,[2]Retiros_dinamica!E:E,"S/I",0) -> S/I | AB36: =_xlfn.XLOOKUP(C36,[2]CMg!$I$4:$I$106,[2]CMg!$M$4:$M$106,"----",0,1) -> ---- | AH36: =_xlfn.XLOOKUP($E36,'[2]Balance económico'!$C:$C,'[2]Balance económico'!$D:$D,"-",0) -> -5.0996618e+09 | AI36: =_xlfn.XLOOKUP($E36,'[2]Balance económico'!$C:$C,'[2]Balance económico'!$E:$E,"-",0) -> 1.7619185e+09 | AJ36: =_xlfn.XLOOKUP($E36,'[2]Balance económico'!$C:$C,'[2]Balance económico'!$F:$F,"-",0) -> 5.7097079e+08 | AK36: =IF(AA36>0,"PPA","-") -> PPA | AL36: {=IFERROR((X36*[2]!Tabla2[Bloque A] + 'BD Centrales 2025'!Y1087*[2]!Tabla2[Bloque B] + 'BD Centrales 2025'!Z1087*[2]!Tabla2[Bloque C])*#REF!,"-")} -> - | AM36: =IFERROR(AH36+AL36,"-") -> - | AN36: =IFERROR((AH36+AI36+AJ36)/(SUMIFS($W$2:$W$1194,$E$2:$E$1194,E36)*1000*#REF!),0) -> 0
A37: 43 | B37: CE12G0018 | C37: PMGD TER LONQUIMAY | D37: SOCIEDAD GENERADORA AUSTRAL S.A. | E37: =_xlfn.XLOOKUP(D37,'[2]Coordinados SEN'!$A:$A,'[2]Coordinados SEN'!$B:$B,"-",0) -> 99.528.750-1 | F37: SAGESA S.A. | G37: =COUNTIFS($D$2:$D$1194,D37) -> 23 | H37: S/E CURACAUTIN 13.2KV | I37: S/E CURACAUTIN 13.2KV | J37: =_xlfn.XLOOKUP(I37,'[2]Barras CMg'!$E$2:$E$1527,'[2]Barras CMg'!$A$2:$A$1527,"------",0,1) -> CURACAUTIN____013 | K37: 2 | L37: 2025 | M37: Termoeléctrica | N37: Motor de combustión interna | O37: Pequeños medio de generación distribuida o PMGD | P37: La Araucanía | Q37: Malleco | R37: Lonquimay | S37: Operativa | T37: 21-07-2011 | U37: 1.2 | V37: 1.2 | W37: =_xlfn.XLOOKUP(C37,#REF!,#REF!,"S/I",0) -> #REF! | X37: =_xlfn.XLOOKUP($D37,[2]Retiros_dinamica!$F:$F,[2]Retiros_dinamica!B:B,"S/I",0) -> S/I | Y37: =_xlfn.XLOOKUP($D37,[2]Retiros_dinamica!$F:$F,[2]Retiros_dinamica!C:C,"S/I",0) -> S/I | Z37: =_xlfn.XLOOKUP($D37,[2]Retiros_dinamica!$F:$F,[2]Retiros_dinamica!D:D,"S/I",0) -> S/I | AA37: =_xlfn.XLOOKUP($D37,[2]Retiros_dinamica!$F:$F,[2]Retiros_dinamica!E:E,"S/I",0) -> S/I | AB37: =_xlfn.XLOOKUP(C37,[2]CMg!$I$4:$I$106,[2]CMg!$M$4:$M$106,"----",0,1) -> ---- | AH37: =_xlfn.XLOOKUP($E37,'[2]Balance económico'!$C:$C,'[2]Balance económico'!$D:$D,"-",0) -> -5.0996618e+09 | AI37: =_xlfn.XLOOKUP($E37,'[2]Balance económico'!$C:$C,'[2]Balance económico'!$E:$E,"-",0) -> 1.7619185e+09 | AJ37: =_xlfn.XLOOKUP($E37,'[2]Balance económico'!$C:$C,'[2]Balance económico'!$F:$F,"-",0) -> 5.7097079e+08 | AK37: =IF(AA37>0,"PPA","-") -> PPA | AL37: {=IFERROR((X37*[2]!Tabla2[Bloque A] + 'BD Centrales 2025'!Y1088*[2]!Tabla2[Bloque B] + 'BD Centrales 2025'!Z1088*[2]!Tabla2[Bloque C])*#REF!,"-")} -> - | AM37: =IFERROR(AH37+AL37,"-") -> - | AN37: =IFERROR((AH37+AI37+AJ37)/(SUMIFS($W$2:$W$1194,$E$2:$E$1194,E37)*1000*#REF!),0) -> 0
A38: 47 | B38: CE13G0018 | C38: PMGD TER TIRUA | D38: SOCIEDAD GENERADORA AUSTRAL S.A. | E38: =_xlfn.XLOOKUP(D38,'[2]Coordinados SEN'!$A:$A,'[2]Coordinados SEN'!$B:$B,"-",0) -> 99.528.750-1 | F38: SAGESA S.A. | G38: =COUNTIFS($D$2:$D$1194,D38) -> 23 | H38: S/E TRES PINOS 13.2KV | I38: S/E TRES PINOS 13.2KV | J38: =_xlfn.XLOOKUP(I38,'[2]Barras CMg'!$E$2:$E$1527,'[2]Barras CMg'!$A$2:$A$1527,"------",0,1) -> T.PINOS_______013 | K38: 1 | L38: 2025 | M38: Termoeléctrica | N38: Motor de combustión interna | O38: Pequeños medio de generación distribuida o PMGD | P38: Biobío | Q38: Arauco | R38: Tirúa | S38: Operativa | T38: 21-07-2011 | U38: 1.9 | V38: 1.9 | W38: =_xlfn.XLOOKUP(C38,#REF!,#REF!,"S/I",0) -> #REF! | X38: =_xlfn.XLOOKUP($D38,[2]Retiros_dinamica!$F:$F,[2]Retiros_dinamica!B:B,"S/I",0) -> S/I | Y38: =_xlfn.XLOOKUP($D38,[2]Retiros_dinamica!$F:$F,[2]Retiros_dinamica!C:C,"S/I",0) -> S/I | Z38: =_xlfn.XLOOKUP($D38,[2]Retiros_dinamica!$F:$F,[2]Retiros_dinamica!D:D,"S/I",0) -> S/I | AA38: =_xlfn.XLOOKUP($D38,[2]Retiros_dinamica!$F:$F,[2]Retiros_dinamica!E:E,"S/I",0) -> S/I | AB38: =_xlfn.XLOOKUP(C38,[2]CMg!$I$4:$I$106,[2]CMg!$M$4:$M$106,"----",0,1) -> ---- | AH38: =_xlfn.XLOOKUP($E38,'[2]Balance económico'!$C:$C,'[2]Balance económico'!$D:$D,"-",0) -> -5.0996618e+09 | AI38: =_xlfn.XLOOKUP($E38,'[2]Balance económico'!$C:$C,'[2]Balance económico'!$E:$E,"-",0) -> 1.7619185e+09 | AJ38: =_xlfn.XLOOKUP($E38,'[2]Balance económico'!$C:$C,'[2]Balance económico'!$F:$F,"-",0) -> 5.7097079e+08 | AK38: =IF(AA38>0,"PPA","-") -> PPA | AL38: {=IFERROR((X38*[2]!Tabla2[Bloque A] + 'BD Centrales 2025'!Y1089*[2]!Tabla2[Bloque B] + 'BD Centrales 2025'!Z1089*[2]!Tabla2[Bloque C])*#REF!,"-")} -> - | AM38: =IFERROR(AH38+AL38,"-") -> - | AN38: =IFERROR((AH38+AI38+AJ38)/(SUMIFS($W$2:$W$1194,$E$2:$E$1194,E38)*1000*#REF!),0) -> 0
A39: 52 | B39: CE02G0125 | C39: PMGD HP LOS CORRALES | D39: LÁGRIMAS DEL SUR SPA | E39: =_xlfn.XLOOKUP(D39,'[2]Coordinados SEN'!$A:$A,'[2]Coordinados SEN'!$B:$B,"-",0) -> 76.738.520-K | F39: LÁGRIMAS DEL SUR SPA | G39: =COUNTIFS($D$2:$D$1194,D39) -> 2 | H39: ALIMENTADOR PILMAIQUEN - MANTIHUE 23 KV | I39: ALIMENTADOR PILMAIQUEN - MANTIHUE 23KV | J39: =_xlfn.XLOOKUP(I39,'[2]Barras CMg'!$E$2:$E$1527,'[2]Barras CMg'!$A$2:$A$1527,"------",0,1) -> ------ | K39: 1 | L39: 2025 | M39: Hidroeléctrica | N39: Minihidro de pasada | O39: Pequeños medio de generación distribuida o PMGD | P39: Los Ríos | Q39: Ranco | R39: Río Bueno | S39: Operativa | T39: 18-09-2010 | U39: 0.8 | V39: 0.8 | W39: =_xlfn.XLOOKUP(C39,#REF!,#REF!,"S/I",0) -> #REF! | X39: =_xlfn.XLOOKUP($D39,[2]Retiros_dinamica!$F:$F,[2]Retiros_dinamica!B:B,"S/I",0) -> S/I | Y39: =_xlfn.XLOOKUP($D39,[2]Retiros_dinamica!$F:$F,[2]Retiros_dinamica!C:C,"S/I",0) -> S/I | Z39: =_xlfn.XLOOKUP($D39,[2]Retiros_dinamica!$F:$F,[2]Retiros_dinamica!D:D,"S/I",0) -> S/I | AA39: =_xlfn.XLOOKUP($D39,[2]Retiros_dinamica!$F:$F,[2]Retiros_dinamica!E:E,"S/I",0) -> S/I | AB39: =_xlfn.XLOOKUP(C39,[2]CMg!$I$4:$I$106,[2]CMg!$M$4:$M$106,"----",0,1) -> ---- | AH39: =_xlfn.XLOOKUP($E39,'[2]Balance económico'!$C:$C,'[2]Balance económico'!$D:$D,"-",0) -> 92261.015 | AI39: =_xlfn.XLOOKUP($E39,'[2]Balance económico'!$C:$C,'[2]Balance económico'!$E:$E,"-",0) -> 98510206 | AJ39: =_xlfn.XLOOKUP($E39,'[2]Balance económico'!$C:$C,'[2]Balance económico'!$F:$F,"-",0) -> ---- | AK39: =IF(AA39>0,"PPA","-") -> PPA | AL39: {=IFERROR((X39*[2]!Tabla2[Bloque A] + 'BD Centrales 2025'!Y885*[2]!Tabla2[Bloque B] + 'BD Centrales 2025'!Z885*[2]!Tabla2[Bloque C])*#REF!,"-")} -> - | AM39: =IFERROR(AH39+AL39,"-") -> - | AN39: =IFERROR((AH39+AI39+AJ39)/(SUMIFS($W$2:$W$1194,$E$2:$E$1194,E39)*1000*#REF!),0) -> 0
A40: 53 | B40: CE32G0018 | C40: PMGD TER LOUSIANA PACIFIC | D40: SOCIEDAD GENERADORA AUSTRAL S.A. | E40: =_xlfn.XLOOKUP(D40,'[2]Coordinados SEN'!$A:$A,'[2]Coordinados SEN'!$B:$B,"-",0) -> 99.528.750-1 | F40: SAGESA S.A. | G40: =COUNTIFS($D$2:$D$1194,D40) -> 23 | H40: S/E PANGUIPULLI 23KV | I40: S/E PANGUIPULLI 23KV | J40: =_xlfn.XLOOKUP(I40,'[2]Barras CMg'!$E$2:$E$1527,'[2]Barras CMg'!$A$2:$A$1527,"------",0,1) -> PANGUIPULLI___023 | K40: 4 | L40: 2025 | M40: Termoeléctrica | N40: Motor de combustión interna | O40: Pequeños medio de generación distribuida o PMGD | P40: Los Ríos | Q40: Valdivia | R40: Panguipulli | S40: Operativa | T40: 15-06-2009 | U40: 3 | V40: 3 | W40: =_xlfn.XLOOKUP(C40,#REF!,#REF!,"S/I",0) -> #REF! | X40: =_xlfn.XLOOKUP($D40,[2]Retiros_dinamica!$F:$F,[2]Retiros_dinamica!B:B,"S/I",0) -> S/I | Y40: =_xlfn.XLOOKUP($D40,[2]Retiros_dinamica!$F:$F,[2]Retiros_dinamica!C:C,"S/I",0) -> S/I | Z40: =_xlfn.XLOOKUP($D40,[2]Retiros_dinamica!$F:$F,[2]Retiros_dinamica!D:D,"S/I",0) -> S/I | AA40: =_xlfn.XLOOKUP($D40,[2]Retiros_dinamica!$F:$F,[2]Retiros_dinamica!E:E,"S/I",0) -> S/I | AB40: =_xlfn.XLOOKUP(C40,[2]CMg!$I$4:$I$106,[2]CMg!$M$4:$M$106,"----",0,1) -> ---- | AH40: =_xlfn.XLOOKUP($E40,'[2]Balance económico'!$C:$C,'[2]Balance económico'!$D:$D,"-",0) -> -5.0996618e+09 | AI40: =_xlfn.XLOOKUP($E40,'[2]Balance económico'!$C:$C,'[2]Balance económico'!$E:$E,"-",0) -> 1.7619185e+09 | AJ40: =_xlfn.XLOOKUP($E40,'[2]Balance económico'!$C:$C,'[2]Balance económico'!$F:$F,"-",0) -> 5.7097079e+08 | AK40: =IF(AA40>0,"PPA","-") -> PPA | AL40: {=IFERROR((X40*[2]!Tabla2[Bloque A] + 'BD Centrales 2025'!Y1090*[2]!Tabla2[Bloque B] + 'BD Centrales 2025'!Z1090*[2]!Tabla2[Bloque C])*#REF!,"-")} -> - | AM40: =IFERROR(AH40+AL40,"-") -> - | AN40: =IFERROR((AH40+AI40+AJ40)/(SUMIFS($W$2:$W$1194,$E$2:$E$1194,E40)*1000*#REF!),0) -> 0
A41: 54 | B41: CE23G0018 | C41: PMGD TER LOUSIANA PACIFIC II | D41: SOCIEDAD GENERADORA AUSTRAL S.A. | E41: =_xlfn.XLOOKUP(D41,'[2]Coordinados SEN'!$A:$A,'[2]Coordinados SEN'!$B:$B,"-",0) -> 99.528.750-1 | F41: SAGESA S.A. | G41: =COUNTIFS($D$2:$D$1194,D41) -> 23 | H41: S/E LAUTARO | I41: S/E LAUTARO | J41: =_xlfn.XLOOKUP(I41,'[2]Barras CMg'!$E$2:$E$1527,'[2]Barras CMg'!$A$2:$A$1527,"------",0,1) -> ------ | K41: 4 | L41: 2025 | M41: Termoeléctrica | N41: Motor de combustión interna | O41: Pequeños medio de generación distribuida o PMGD | P41: La Araucanía | Q41: Cautín | R41: Lautaro | S41: Operativa | T41: 21-02-2011 | U41: 3 | V41: 3 | W41: =_xlfn.XLOOKUP(C41,#REF!,#REF!,"S/I",0) -> #REF! | X41: =_xlfn.XLOOKUP($D41,[2]Retiros_dinamica!$F:$F,[2]Retiros_dinamica!B:B,"S/I",0) -> S/I | Y41: =_xlfn.XLOOKUP($D41,[2]Retiros_dinamica!$F:$F,[2]Retiros_dinamica!C:C,"S/I",0) -> S/I | Z41: =_xlfn.XLOOKUP($D41,[2]Retiros_dinamica!$F:$F,[2]Retiros_dinamica!D:D,"S/I",0) -> S/I | AA41: =_xlfn.XLOOKUP($D41,[2]Retiros_dinamica!$F:$F,[2]Retiros_dinamica!E:E,"S/I",0) -> S/I | AB41: =_xlfn.XLOOKUP(C41,[2]CMg!$I$4:$I$106,[2]CMg!$M$4:$M$106,"----",0,1) -> ---- | AH41: =_xlfn.XLOOKUP($E41,'[2]Balance económico'!$C:$C,'[2]Balance económico'!$D:$D,"-",0) -> -5.0996618e+09 | AI41: =_xlfn.XLOOKUP($E41,'[2]Balance económico'!$C:$C,'[2]Balance económico'!$E:$E,"-",0) -> 1.7619185e+09 | AJ41: =_xlfn.XLOOKUP($E41,'[2]Balance económico'!$C:$C,'[2]Balance económico'!$F:$F,"-",0) -> 5.7097079e+08 | AK41: =IF(AA41>0,"PPA","-") -> PPA | AL41: {=IFERROR((X41*[2]!Tabla2[Bloque A] + 'BD Centrales 2025'!Y1091*[2]!Tabla2[Bloque B] + 'BD Centrales 2025'!Z1091*[2]!Tabla2[Bloque C])*#REF!,"-")} -> - | AM41: =IFERROR(AH41+AL41,"-") -> - | AN41: =IFERROR((AH41+AI41+AJ41)/(SUMIFS($W$2:$W$1194,$E$2:$E$1194,E41)*1000*#REF!),0) -> 0
A42: 55 | B42: CE24G0018 | C42: PMGD TER MULTIEXPORT | D42: SOCIEDAD GENERADORA AUSTRAL S.A. | E42: =_xlfn.XLOOKUP(D42,'[2]Coordinados SEN'!$A:$A,'[2]Coordinados SEN'!$B:$B,"-",0) -> 99.528.750-1 | F42: SAGESA S.A. | G42: =COUNTIFS($D$2:$D$1194,D42) -> 23 | H42: S/E MELIPULLI 23KV | I42: S/E MELIPULLI 23KV | J42: =_xlfn.XLOOKUP(I42,'[2]Barras CMg'!$E$2:$E$1527,'[2]Barras CMg'!$A$2:$A$1527,"------",0,1) -> MELIPULLI_____023 | K42: 1 | L42: 2025 | M42: Termoeléctrica | N42: Motor de combustión interna | O42: Pequeños medio de generación distribuida o PMGD | P42: Los Lagos | Q42: Llanquihue | R42: Puerto Montt | S42: Operativa | T42: 31-07-2009 | U42: 0.8 | V42: 0.8 | W42: =_xlfn.XLOOKUP(C42,#REF!,#REF!,"S/I",0) -> #REF! | X42: =_xlfn.XLOOKUP($D42,[2]Retiros_dinamica!$F:$F,[2]Retiros_dinamica!B:B,"S/I",0) -> S/I | Y42: =_xlfn.XLOOKUP($D42,[2]Retiros_dinamica!$F:$F,[2]Retiros_dinamica!C:C,"S/I",0) -> S/I | Z42: =_xlfn.XLOOKUP($D42,[2]Retiros_dinamica!$F:$F,[2]Retiros_dinamica!D:D,"S/I",0) -> S/I | AA42: =_xlfn.XLOOKUP($D42,[2]Retiros_dinamica!$F:$F,[2]Retiros_dinamica!E:E,"S/I",0) -> S/I | AB42: =_xlfn.XLOOKUP(C42,[2]CMg!$I$4:$I$106,[2]CMg!$M$4:$M$106,"----",0,1) -> ---- | AH42: =_xlfn.XLOOKUP($E42,'[2]Balance económico'!$C:$C,'[2]Balance económico'!$D:$D,"-",0) -> -5.0996618e+09 | AI42: =_xlfn.XLOOKUP($E42,'[2]Balance económico'!$C:$C,'[2]Balance económico'!$E:$E,"-",0) -> 1.7619185e+09 | AJ42: =_xlfn.XLOOKUP($E42,'[2]Balance económico'!$C:$C,'[2]Balance económico'!$F:$F,"-",0) -> 5.7097079e+08 | AK42: =IF(AA42>0,"PPA","-") -> PPA | AL42: {=IFERROR((X42*[2]!Tabla2[Bloque A] + 'BD Centrales 2025'!Y1092*[2]!Tabla2[Bloque B] + 'BD Centrales 2025'!Z1092*[2]!Tabla2[Bloque C])*#REF!,"-")} -> - | AM42: =IFERROR(AH42+AL42,"-") -> - | AN42: =IFERROR((AH42+AI42+AJ42)/(SUMIFS($W$2:$W$1194,$E$2:$E$1194,E42)*1000*#REF!),0) -> 0
A43: 56 | B43: CE25G0018 | C43: PMGD TER MULTIEXPORT II | D43: SOCIEDAD GENERADORA AUSTRAL S.A. | E43: =_xlfn.XLOOKUP(D43,'[2]Coordinados SEN'!$A:$A,'[2]Coordinados SEN'!$B:$B,"-",0) -> 99.528.750-1 | F43: SAGESA S.A. | G43: =COUNTIFS($D$2:$D$1194,D43) -> 23 | H43: S/E MELIPULLI 23KV | I43: S/E MELIPULLI 23KV | J43: =_xlfn.XLOOKUP(I43,'[2]Barras CMg'!$E$2:$E$1527,'[2]Barras CMg'!$A$2:$A$1527,"------",0,1) -> MELIPULLI_____023 | K43: 2 | L43: 2025 | M43: Termoeléctrica | N43: Motor de combustión interna | O43: Pequeños medio de generación distribuida o PMGD | P43: Los Lagos | Q43: Llanquihue | R43: Puerto Montt | S43: Operativa | T43: 31-07-2009 | U43: 1.6 | V43: 1.6 | W43: =_xlfn.XLOOKUP(C43,#REF!,#REF!,"S/I",0) -> #REF! | X43: =_xlfn.XLOOKUP($D43,[2]Retiros_dinamica!$F:$F,[2]Retiros_dinamica!B:B,"S/I",0) -> S/I | Y43: =_xlfn.XLOOKUP($D43,[2]Retiros_dinamica!$F:$F,[2]Retiros_dinamica!C:C,"S/I",0) -> S/I | Z43: =_xlfn.XLOOKUP($D43,[2]Retiros_dinamica!$F:$F,[2]Retiros_dinamica!D:D,"S/I",0) -> S/I | AA43: =_xlfn.XLOOKUP($D43,[2]Retiros_dinamica!$F:$F,[2]Retiros_dinamica!E:E,"S/I",0) -> S/I | AB43: =_xlfn.XLOOKUP(C43,[2]CMg!$I$4:$I$106,[2]CMg!$M$4:$M$106,"----",0,1) -> ---- | AH43: =_xlfn.XLOOKUP($E43,'[2]Balance económico'!$C:$C,'[2]Balance económico'!$D:$D,"-",0) -> -5.0996618e+09 | AI43: =_xlfn.XLOOKUP($E43,'[2]Balance económico'!$C:$C,'[2]Balance económico'!$E:$E,"-",0) -> 1.7619185e+09 | AJ43: =_xlfn.XLOOKUP($E43,'[2]Balance económico'!$C:$C,'[2]Balance económico'!$F:$F,"-",0) -> 5.7097079e+08 | AK43: =IF(AA43>0,"PPA","-") -> PPA | AL43: {=IFERROR((X43*[2]!Tabla2[Bloque A] + 'BD Centrales 2025'!Y1093*[2]!Tabla2[Bloque B] + 'BD Centrales 2025'!Z1093*[2]!Tabla2[Bloque C])*#REF!,"-")} -> - | AM43: =IFERROR(AH43+AL43,"-") -> - | AN43: =IFERROR((AH43+AI43+AJ43)/(SUMIFS($W$2:$W$1194,$E$2:$E$1194,E43)*1000*#REF!),0) -> 0
A44: 58 | B44: CE06G0124 | C44: PMGD TER SALMOFOOD | D44: SOCIEDAD GENERADORA AUSTRAL S.A. | E44: =_xlfn.XLOOKUP(D44,'[2]Coordinados SEN'!$A:$A,'[2]Coordinados SEN'!$B:$B,"-",0) -> 99.528.750-1 | F44: SALMOFOOD S.A. | G44: =COUNTIFS($D$2:$D$1194,D44) -> 23 | H44: S/E OSORNO 23 KV | I44: S/E OSORNO 23KV | J44: =_xlfn.XLOOKUP(I44,'[2]Barras CMg'!$E$2:$E$1527,'[2]Barras CMg'!$A$2:$A$1527,"------",0,1) -> ------ | K44: 1 | L44: 2025 | M44: Termoeléctrica | N44: Motor de combustión interna | O44: Pequeños medio de generación distribuida o PMGD | P44: Los Lagos | Q44: Chiloé | R44: Castro | S44: Operativa | T44: 31-07-2009 | U44: 1.6 | V44: 1.6 | W44: =_xlfn.XLOOKUP(C44,#REF!,#REF!,"S/I",0) -> #REF! | X44: =_xlfn.XLOOKUP($D44,[2]Retiros_dinamica!$F:$F,[2]Retiros_dinamica!B:B,"S/I",0) -> S/I | Y44: =_xlfn.XLOOKUP($D44,[2]Retiros_dinamica!$F:$F,[2]Retiros_dinamica!C:C,"S/I",0) -> S/I | Z44: =_xlfn.XLOOKUP($D44,[2]Retiros_dinamica!$F:$F,[2]Retiros_dinamica!D:D,"S/I",0) -> S/I | AA44: =_xlfn.XLOOKUP($D44,[2]Retiros_dinamica!$F:$F,[2]Retiros_dinamica!E:E,"S/I",0) -> S/I | AB44: =_xlfn.XLOOKUP(C44,[2]CMg!$I$4:$I$106,[2]CMg!$M$4:$M$106,"----",0,1) -> ---- | AH44: =_xlfn.XLOOKUP($E44,'[2]Balance económico'!$C:$C,'[2]Balance económico'!$D:$D,"-",0) -> -5.0996618e+09 | AI44: =_xlfn.XLOOKUP($E44,'[2]Balance económico'!$C:$C,'[2]Balance económico'!$E:$E,"-",0) -> 1.7619185e+09 | AJ44: =_xlfn.XLOOKUP($E44,'[2]Balance económico'!$C:$C,'[2]Balance económico'!$F:$F,"-",0) -> 5.7097079e+08 | AK44: =IF(AA44>0,"PPA","-") -> PPA | AL44: {=IFERROR((X44*[2]!Tabla2[Bloque A] + 'BD Centrales 2025'!Y1094*[2]!Tabla2[Bloque B] + 'BD Centrales 2025'!Z1094*[2]!Tabla2[Bloque C])*#REF!,"-")} -> - | AM44: =IFERROR(AH44+AL44,"-") -> - | AN44: =IFERROR((AH44+AI44+AJ44)/(SUMIFS($W$2:$W$1194,$E$2:$E$1194,E44)*1000*#REF!),0) -> 0
A45: 65 | B45: CE04G0031 | C45: PMGD TER CASABLANCA | D45: FENSTER ENERGY TRADING SPA | E45: =_xlfn.XLOOKUP(D45,'[2]Coordinados SEN'!$A:$A,'[2]Coordinados SEN'!$B:$B,"-",0) -> 78.195.762-3 | F45: TECNORED S.A. | G45: =COUNTIFS($D$2:$D$1194,D45) -> 1 | H45: S/E CASABLANCA 12KV | I45: S/E CASABLANCA 12KV | J45: =_xlfn.XLOOKUP(I45,'[2]Barras CMg'!$E$2:$E$1527,'[2]Barras CMg'!$A$2:$A$1527,"------",0,1) -> CASABLANCA____013 | K45: 2 | L45: 2025 | M45: Termoeléctrica | N45: Motor de combustión interna | O45: Pequeños medio de generación distribuida o PMGD | P45: Valparaíso | Q45: Valparaíso | R45: Casablanca | S45: Operativa | T45: 13-04-2007 | U45: 1.6 | V45: 1.6 | W45: =_xlfn.XLOOKUP(C45,#REF!,#REF!,"S/I",0) -> #REF! | X45: =_xlfn.XLOOKUP($D45,[2]Retiros_dinamica!$F:$F,[2]Retiros_dinamica!B:B,"S/I",0) -> S/I | Y45: =_xlfn.XLOOKUP($D45,[2]Retiros_dinamica!$F:$F,[2]Retiros_dinamica!C:C,"S/I",0) -> S/I | Z45: =_xlfn.XLOOKUP($D45,[2]Retiros_dinamica!$F:$F,[2]Retiros_dinamica!D:D,"S/I",0) -> S/I | AA45: =_xlfn.XLOOKUP($D45,[2]Retiros_dinamica!$F:$F,[2]Retiros_dinamica!E:E,"S/I",0) -> S/I | AB45: =_xlfn.XLOOKUP(C45,[2]CMg!$I$4:$I$106,[2]CMg!$M$4:$M$106,"----",0,1) -> ---- | AH45: =_xlfn.XLOOKUP($E45,'[2]Balance económico'!$C:$C,'[2]Balance económico'!$D:$D,"-",0) -> 74502.14 | AI45: =_xlfn.XLOOKUP($E45,'[2]Balance económico'!$C:$C,'[2]Balance económico'!$E:$E,"-",0) -> 12002441 | AJ45: =_xlfn.XLOOKUP($E45,'[2]Balance económico'!$C:$C,'[2]Balance económico'!$F:$F,"-",0) -> ---- | AK45: =IF(AA45>0,"PPA","-") -> PPA | AL45: {=IFERROR((X45*[2]!Tabla2[Bloque A] + 'BD Centrales 2025'!Y1016*[2]!Tabla2[Bloque B] + 'BD Centrales 2025'!Z1016*[2]!Tabla2[Bloque C])*#REF!,"-")} -> - | AM45: =IFERROR(AH45+AL45,"-") -> - | AN45: =IFERROR((AH45+AI45+AJ45)/(SUMIFS($W$2:$W$1194,$E$2:$E$1194,E45)*1000*#REF!),0) -> 0
A46: 66 | B46: CE11G0031 | C46: PMGD TER CASABLANCA II | D46: TECNORED S.A. | E46: =_xlfn.XLOOKUP(D46,'[2]Coordinados SEN'!$A:$A,'[2]Coordinados SEN'!$B:$B,"-",0) -> 77.302.440-5 | F46: TECNORED S.A. | G46: =COUNTIFS($D$2:$D$1194,D46) -> 7 | H46: S/E CASABLANCA 12KV | I46: S/E CASABLANCA 12KV | J46: =_xlfn.XLOOKUP(I46,'[2]Barras CMg'!$E$2:$E$1527,'[2]Barras CMg'!$A$2:$A$1527,"------",0,1) -> CASABLANCA____013 | K46: 2 | L46: 2025 | M46: Termoeléctrica | N46: Motor de combustión interna | O46: Pequeños medio de generación distribuida o PMGD | P46: Valparaíso | Q46: Valparaíso | R46: Casablanca | S46: Operativa | T46: 13-04-2007 | U46: 0.9 | V46: 0.9 | W46: =_xlfn.XLOOKUP(C46,#REF!,#REF!,"S/I",0) -> #REF! | X46: =_xlfn.XLOOKUP($D46,[2]Retiros_dinamica!$F:$F,[2]Retiros_dinamica!B:B,"S/I",0) -> 25998.519 | Y46: =_xlfn.XLOOKUP($D46,[2]Retiros_dinamica!$F:$F,[2]Retiros_dinamica!C:C,"S/I",0) -> 36744.498 | Z46: =_xlfn.XLOOKUP($D46,[2]Retiros_dinamica!$F:$F,[2]Retiros_dinamica!D:D,"S/I",0) -> 13134.763 | AA46: =_xlfn.XLOOKUP($D46,[2]Retiros_dinamica!$F:$F,[2]Retiros_dinamica!E:E,"S/I",0) -> 75877.78 | AB46: =_xlfn.XLOOKUP(C46,[2]CMg!$I$4:$I$106,[2]CMg!$M$4:$M$106,"----",0,1) -> ---- | AH46: =_xlfn.XLOOKUP($E46,'[2]Balance económico'!$C:$C,'[2]Balance económico'!$D:$D,"-",0) -> -4.1482077e+09 | AI46: =_xlfn.XLOOKUP($E46,'[2]Balance económico'!$C:$C,'[2]Balance económico'!$E:$E,"-",0) -> 5.9046621e+08 | AJ46: =_xlfn.XLOOKUP($E46,'[2]Balance económico'!$C:$C,'[2]Balance económico'!$F:$F,"-",0) -> 2.2299489e+08 | AK46: =IF(AA46>0,"PPA","-") -> PPA | AL46: {=IFERROR((X46*[2]!Tabla2[Bloque A] + 'BD Centrales 2025'!Y1064*[2]!Tabla2[Bloque B] + 'BD Centrales 2025'!Z1064*[2]!Tabla2[Bloque C])*#REF!,"-")} -> - | AM46: =IFERROR(AH46+AL46,"-") -> - | AN46: =IFERROR((AH46+AI46+AJ46)/(SUMIFS($W$2:$W$1194,$E$2:$E$1194,E46)*1000*#REF!),0) -> 0
A47: 67 | B47: CE03G0031 | C47: PMGD TER CURAUMA | D47: TECNORED S.A. | E47: =_xlfn.XLOOKUP(D47,'[2]Coordinados SEN'!$A:$A,'[2]Coordinados SEN'!$B:$B,"-",0) -> 77.302.440-5 | F47: TECNORED S.A. | G47: =COUNTIFS($D$2:$D$1194,D47) -> 7 | H47: S/E CURAUMA | I47: S/E CURAUMA | J47: =_xlfn.XLOOKUP(I47,'[2]Barras CMg'!$E$2:$E$1527,'[2]Barras CMg'!$A$2:$A$1527,"------",0,1) -> ------ | K47: 3 | L47: 2025 | M47: Termoeléctrica | N47: Motor de combustión interna | O47: Pequeños medio de generación distribuida o PMGD | P47: Valparaíso | Q47: Valparaíso | R47: Valparaíso | S47: Operativa | T47: 14-04-2007 | U47: 2.5 | V47: 2.5 | W47: =_xlfn.XLOOKUP(C47,#REF!,#REF!,"S/I",0) -> #REF! | X47: =_xlfn.XLOOKUP($D47,[2]Retiros_dinamica!$F:$F,[2]Retiros_dinamica!B:B,"S/I",0) -> 25998.519 | Y47: =_xlfn.XLOOKUP($D47,[2]Retiros_dinamica!$F:$F,[2]Retiros_dinamica!C:C,"S/I",0) -> 36744.498 | Z47: =_xlfn.XLOOKUP($D47,[2]Retiros_dinamica!$F:$F,[2]Retiros_dinamica!D:D,"S/I",0) -> 13134.763 | AA47: =_xlfn.XLOOKUP($D47,[2]Retiros_dinamica!$F:$F,[2]Retiros_dinamica!E:E,"S/I",0) -> 75877.78 | AB47: =_xlfn.XLOOKUP(C47,[2]CMg!$I$4:$I$106,[2]CMg!$M$4:$M$106,"----",0,1) -> ---- | AH47: =_xlfn.XLOOKUP($E47,'[2]Balance económico'!$C:$C,'[2]Balance económico'!$D:$D,"-",0) -> -4.1482077e+09 | AI47: =_xlfn.XLOOKUP($E47,'[2]Balance económico'!$C:$C,'[2]Balance económico'!$E:$E,"-",0) -> 5.9046621e+08 | AJ47: =_xlfn.XLOOKUP($E47,'[2]Balance económico'!$C:$C,'[2]Balance económico'!$F:$F,"-",0) -> 2.2299489e+08 | AK47: =IF(AA47>0,"PPA","-") -> PPA | AL47: {=IFERROR((X47*[2]!Tabla2[Bloque A] + 'BD Centrales 2025'!Y1065*[2]!Tabla2[Bloque B] + 'BD Centrales 2025'!Z1065*[2]!Tabla2[Bloque C])*#REF!,"-")} -> - | AM47: =IFERROR(AH47+AL47,"-") -> - | AN47: =IFERROR((AH47+AI47+AJ47)/(SUMIFS($W$2:$W$1194,$E$2:$E$1194,E47)*1000*#REF!),0) -> 0
A48: 68 | B48: CE10G0031 | C48: PMGD TER TAPIHUE | D48: TECNORED S.A. | E48: =_xlfn.XLOOKUP(D48,'[2]Coordinados SEN'!$A:$A,'[2]Coordinados SEN'!$B:$B,"-",0) -> 77.302.440-5 | F48: TECNORED S.A. | G48: =COUNTIFS($D$2:$D$1194,D48) -> 7 | H48: S/E CASABLANCA | I48: S/E CASABLANCA | J48: =_xlfn.XLOOKUP(I48,'[2]Barras CMg'!$E$2:$E$1527,'[2]Barras CMg'!$A$2:$A$1527,"------",0,1) -> ------ | K48: 2 | L48: 2025 | M48: Termoeléctrica | N48: Motor de combustión interna | O48: Pequeños medio de generación distribuida o PMGD | P48: Valparaíso | Q48: Valparaíso | R48: Casablanca | S48: Operativa | T48: 27-08-2009 | U48: 6.4 | V48: 6.4 | W48: =_xlfn.XLOOKUP(C48,#REF!,#REF!,"S/I",0) -> #REF! | X48: =_xlfn.XLOOKUP($D48,[2]Retiros_dinamica!$F:$F,[2]Retiros_dinamica!B:B,"S/I",0) -> 25998.519 | Y48: =_xlfn.XLOOKUP($D48,[2]Retiros_dinamica!$F:$F,[2]Retiros_dinamica!C:C,"S/I",0) -> 36744.498 | Z48: =_xlfn.XLOOKUP($D48,[2]Retiros_dinamica!$F:$F,[2]Retiros_dinamica!D:D,"S/I",0) -> 13134.763 | AA48: =_xlfn.XLOOKUP($D48,[2]Retiros_dinamica!$F:$F,[2]Retiros_dinamica!E:E,"S/I",0) -> 75877.78 | AB48: =_xlfn.XLOOKUP(C48,[2]CMg!$I$4:$I$106,[2]CMg!$M$4:$M$106,"----",0,1) -> ---- | AH48: =_xlfn.XLOOKUP($E48,'[2]Balance económico'!$C:$C,'[2]Balance económico'!$D:$D,"-",0) -> -4.1482077e+09 | AI48: =_xlfn.XLOOKUP($E48,'[2]Balance económico'!$C:$C,'[2]Balance económico'!$E:$E,"-",0) -> 5.9046621e+08 | AJ48: =_xlfn.XLOOKUP($E48,'[2]Balance económico'!$C:$C,'[2]Balance económico'!$F:$F,"-",0) -> 2.2299489e+08 | AK48: =IF(AA48>0,"PPA","-") -> PPA | AL48: {=IFERROR((X48*[2]!Tabla2[Bloque A] + 'BD Centrales 2025'!Y1066*[2]!Tabla2[Bloque B] + 'BD Centrales 2025'!Z1066*[2]!Tabla2[Bloque C])*#REF!,"-")} -> - | AM48: =IFERROR(AH48+AL48,"-") -> - | AN48: =IFERROR((AH48+AI48+AJ48)/(SUMIFS($W$2:$W$1194,$E$2:$E$1194,E48)*1000*#REF!),0) -> 0
A49: 69 | B49: CE01G0010 | C49: HP ALFALFAL | D49: AES ANDES S.A. | E49: =_xlfn.XLOOKUP(D49,'[2]Coordinados SEN'!$A:$A,'[2]Coordinados SEN'!$B:$B,"-",0) -> 94.272.000-9 | F49: AES ANDES S.A. | G49: =COUNTIFS($D$2:$D$1194,D49) -> 6 | H49: S/E CENTRAL ALFALFAL 220KV | I49: S/E CENTRAL ALFALFAL 220KV | J49: =_xlfn.XLOOKUP(I49,'[2]Barras CMg'!$E$2:$E$1527,'[2]Barras CMg'!$A$2:$A$1527,"------",0,1) -> ALFALFAL______220 | K49: 2 | L49: 2025 | M49: Hidroeléctrica | N49: Hidroeléctrica de pasada | O49: Instalaciones de generación | P49: Metropolitana de Santiago | Q49: Cordillera | R49: San José de Maipo | S49: Operativa | T49: 31-07-1991 | U49: 187.1236 | V49: 184.5534 | W49: =_xlfn.XLOOKUP(C49,#REF!,#REF!,"S/I",0) -> #REF! | X49: =_xlfn.XLOOKUP($D49,[2]Retiros_dinamica!$F:$F,[2]Retiros_dinamica!B:B,"S/I",0) -> 1941802 | Y49: =_xlfn.XLOOKUP($D49,[2]Retiros_dinamica!$F:$F,[2]Retiros_dinamica!C:C,"S/I",0) -> 2207177.4 | Z49: =_xlfn.XLOOKUP($D49,[2]Retiros_dinamica!$F:$F,[2]Retiros_dinamica!D:D,"S/I",0) -> 1185924 | AA49: =_xlfn.XLOOKUP($D49,[2]Retiros_dinamica!$F:$F,[2]Retiros_dinamica!E:E,"S/I",0) -> 5334903.4 | AB49: =_xlfn.XLOOKUP(C49,[2]CMg!$I$4:$I$106,[2]CMg!$M$4:$M$106,"----",0,1) -> ---- | AC49: =_xlfn.XLOOKUP(C49,[2]CMg!$A$4:$A$106,[2]CMg!$B$4:$B$106,"----",0,1) -> ---- | AD49: =_xlfn.XLOOKUP(C49,'[3]Promedio solar Cmg'!$A$4:$A$106,'[3]Promedio solar Cmg'!$B$4:$B$106,"----",0,1) -> ---- | AH49: =_xlfn.XLOOKUP($E49,'[2]Balance económico'!$C:$C,'[2]Balance económico'!$D:$D,"-",0) -> 2.7456229e+10 | AI49: =_xlfn.XLOOKUP($E49,'[2]Balance económico'!$C:$C,'[2]Balance económico'!$E:$E,"-",0) -> -6.9728796e+10 | AJ49: =_xlfn.XLOOKUP($E49,'[2]Balance económico'!$C:$C,'[2]Balance económico'!$F:$F,"-",0) -> 1.7439365e+10 | AK49: =IF(AA49>0,"PPA","-") -> PPA | AL49: {=IFERROR((X49*[2]!Tabla2[Bloque A] + 'BD Centrales 2025'!Y19*[2]!Tabla2[Bloque B] + 'BD Centrales 2025'!Z19*[2]!Tabla2[Bloque C])*#REF!,"-")} -> - | AM49: =IFERROR(AH49+AL49,"-") -> - | AN49: =IFERROR((AH49+AI49+AJ49)/(SUMIFS($W$2:$W$1194,$E$2:$E$1194,E49)*1000*#REF!),0) -> 0
A50: 72 | B50: CE07G0434 | C50: TER LOS VIENTOS | D50: GM HOLDINGS S.A. | E50: =_xlfn.XLOOKUP(D50,'[2]Coordinados SEN'!$A:$A,'[2]Coordinados SEN'!$B:$B,"-",0) -> 76.240.103-7 | F50: GENERADORA METROPOLITANA SPA | G50: =COUNTIFS($D$2:$D$1194,D50) -> 3 | H50: S/E LAS VEGAS 110KV | I50: S/E LAS VEGAS (CHILQUINTA) 110KV | J50: =_xlfn.XLOOKUP(I50,'[2]Barras CMg'!$E$2:$E$1527,'[2]Barras CMg'!$A$2:$A$1527,"------",0,1) -> L.VEGAS2______110 | K50: 1 | L50: 2025 | M50: Termoeléctrica | N50: Termoeléctrica de turbina a gas | O50: Instalaciones de generación | P50: Valparaíso | Q50: San Felipe de Aconcagua | R50: Llaillay | S50: Operativa | T50: 03-01-2007 | U50: 129,378 (Diesel) / 134,971 (GNL) | V50: 127,762 (Diesel) / 133,704 (GNL) | W50: =_xlfn.XLOOKUP(C50,#REF!,#REF!,"S/I",0) -> #REF! | X50: =_xlfn.XLOOKUP($D50,[2]Retiros_dinamica!$F:$F,[2]Retiros_dinamica!B:B,"S/I",0) -> 777731.54 | Y50: =_xlfn.XLOOKUP($D50,[2]Retiros_dinamica!$F:$F,[2]Retiros_dinamica!C:C,"S/I",0) -> 922797.71 | Z50: =_xlfn.XLOOKUP($D50,[2]Retiros_dinamica!$F:$F,[2]Retiros_dinamica!D:D,"S/I",0) -> 511925.91 | AA50: =_xlfn.XLOOKUP($D50,[2]Retiros_dinamica!$F:$F,[2]Retiros_dinamica!E:E,"S/I",0) -> 2212455.2 | AB50: =_xlfn.XLOOKUP(C50,[2]CMg!$I$4:$I$106,[2]CMg!$M$4:$M$106,"----",0,1) -> ---- | AH50: =_xlfn.XLOOKUP($E50,'[2]Balance económico'!$C:$C,'[2]Balance económico'!$D:$D,"-",0) -> -6.1321669e+10 | AI50: =_xlfn.XLOOKUP($E50,'[2]Balance económico'!$C:$C,'[2]Balance económico'!$E:$E,"-",0) -> -4.5573628e+10 | AJ50: =_xlfn.XLOOKUP($E50,'[2]Balance económico'!$C:$C,'[2]Balance económico'!$F:$F,"-",0) -> 1.0642872e+10 | AK50: =IF(AA50>0,"PPA","-") -> PPA | AL50: {=IFERROR((X50*[2]!Tabla2[Bloque A] + 'BD Centrales 2025'!Y1139*[2]!Tabla2[Bloque B] + 'BD Centrales 2025'!Z1139*[2]!Tabla2[Bloque C])*#REF!,"-")} -> - | AM50: =IFERROR(AH50+AL50,"-") -> - | AN50: =IFERROR((AH50+AI50+AJ50)/(SUMIFS($W$2:$W$1194,$E$2:$E$1194,E50)*1000*#REF!),0) -> 0
A51: 73 | B51: CE04G0010 | C51: HP MAITENES | D51: AES ANDES S.A. | E51: =_xlfn.XLOOKUP(D51,'[2]Coordinados SEN'!$A:$A,'[2]Coordinados SEN'!$B:$B,"-",0) -> 94.272.000-9 | F51: AES ANDES S.A. | G51: =COUNTIFS($D$2:$D$1194,D51) -> 6 | H51: S/E CENTRAL MAITENES 110KV | I51: S/E CENTRAL MAITENES 110KV | J51: =_xlfn.XLOOKUP(I51,'[2]Barras CMg'!$E$2:$E$1527,'[2]Barras CMg'!$A$2:$A$1527,"------",0,1) -> ENL.MAITENES__110 | K51: 3 | L51: 2025 | M51: Hidroeléctrica | N51: Hidroeléctrica de pasada | O51: Instalaciones de generación | P51: Metropolitana de Santiago | Q51: Cordillera | R51: San José de Maipo | S51: Operativa | T51: 31-07-1923 | U51: 27 | V51: 26.92 | W51: =_xlfn.XLOOKUP(C51,#REF!,#REF!,"S/I",0) -> #REF! | X51: =_xlfn.XLOOKUP($D51,[2]Retiros_dinamica!$F:$F,[2]Retiros_dinamica!B:B,"S/I",0) -> 1941802 | Y51: =_xlfn.XLOOKUP($D51,[2]Retiros_dinamica!$F:$F,[2]Retiros_dinamica!C:C,"S/I",0) -> 2207177.4 | Z51: =_xlfn.XLOOKUP($D51,[2]Retiros_dinamica!$F:$F,[2]Retiros_dinamica!D:D,"S/I",0) -> 1185924 | AA51: =_xlfn.XLOOKUP($D51,[2]Retiros_dinamica!$F:$F,[2]Retiros_dinamica!E:E,"S/I",0) -> 5334903.4 | AB51: =_xlfn.XLOOKUP(C51,[2]CMg!$I$4:$I$106,[2]CMg!$M$4:$M$106,"----",0,1) -> ---- | AC51: =_xlfn.XLOOKUP(C51,[2]CMg!$A$4:$A$106,[2]CMg!$B$4:$B$106,"----",0,1) -> ---- | AD51: =_xlfn.XLOOKUP(C51,'[3]Promedio solar Cmg'!$A$4:$A$106,'[3]Promedio solar Cmg'!$B$4:$B$106,"----",0,1) -> ---- | AH51: =_xlfn.XLOOKUP($E51,'[2]Balance económico'!$C:$C,'[2]Balance económico'!$D:$D,"-",0) -> 2.7456229e+10 | AI51: =_xlfn.XLOOKUP($E51,'[2]Balance económico'!$C:$C,'[2]Balance económico'!$E:$E,"-",0) -> -6.9728796e+10 | AJ51: =_xlfn.XLOOKUP($E51,'[2]Balance económico'!$C:$C,'[2]Balance económico'!$F:$F,"-",0) -> 1.7439365e+10 | AK51: =IF(AA51>0,"PPA","-") -> PPA | AL51: {=IFERROR((X51*[2]!Tabla2[Bloque A] + 'BD Centrales 2025'!Y74*[2]!Tabla2[Bloque B] + 'BD Centrales 2025'!Z74*[2]!Tabla2[Bloque C])*#REF!,"-")} -> - | AM51: =IFERROR(AH51+AL51,"-") -> - | AN51: =IFERROR((AH51+AI51+AJ51)/(SUMIFS($W$2:$W$1194,$E$2:$E$1194,E51)*1000*#REF!),0) -> 0
A52: 74 | B52: CE05G0010 | C52: HP QUELTEHUES | D52: AES ANDES S.A. | E52: =_xlfn.XLOOKUP(D52,'[2]Coordinados SEN'!$A:$A,'[2]Coordinados SEN'!$B:$B,"-",0) -> 94.272.000-9 | F52: AES ANDES S.A. | G52: =COUNTIFS($D$2:$D$1194,D52) -> 6 | H52: S/E CENTRAL QUELTEHUES 110KV | I52: S/E CENTRAL QUELTEHUES 110KV | J52: =_xlfn.XLOOKUP(I52,'[2]Barras CMg'!$E$2:$E$1527,'[2]Barras CMg'!$A$2:$A$1527,"------",0,1) -> QUELTEHUES____110 | K52: 3 | L52: 2025 | M52: Hidroeléctrica | N52: Hidroeléctrica de pasada | O52: Instalaciones de generación | P52: Metropolitana de Santiago | Q52: Cordillera | R52: San José de Maipo | S52: Operativa | T52: 14-02-2024 | U52: 49 | V52: 48.9412 | W52: =_xlfn.XLOOKUP(C52,#REF!,#REF!,"S/I",0) -> #REF! | X52: =_xlfn.XLOOKUP($D52,[2]Retiros_dinamica!$F:$F,[2]Retiros_dinamica!B:B,"S/I",0) -> 1941802 | Y52: =_xlfn.XLOOKUP($D52,[2]Retiros_dinamica!$F:$F,[2]Retiros_dinamica!C:C,"S/I",0) -> 2207177.4 | Z52: =_xlfn.XLOOKUP($D52,[2]Retiros_dinamica!$F:$F,[2]Retiros_dinamica!D:D,"S/I",0) -> 1185924 | AA52: =_xlfn.XLOOKUP($D52,[2]Retiros_dinamica!$F:$F,[2]Retiros_dinamica!E:E,"S/I",0) -> 5334903.4 | AB52: =_xlfn.XLOOKUP(C52,[2]CMg!$I$4:$I$106,[2]CMg!$M$4:$M$106,"----",0,1) -> ---- | AC52: =_xlfn.XLOOKUP(C52,[2]CMg!$A$4:$A$106,[2]CMg!$B$4:$B$106,"----",0,1) -> ---- | AD52: =_xlfn.XLOOKUP(C52,'[3]Promedio solar Cmg'!$A$4:$A$106,'[3]Promedio solar Cmg'!$B$4:$B$106,"----",0,1) -> ---- | AH52: =_xlfn.XLOOKUP($E52,'[2]Balance económico'!$C:$C,'[2]Balance económico'!$D:$D,"-",0) -> 2.7456229e+10 | AI52: =_xlfn.XLOOKUP($E52,'[2]Balance económico'!$C:$C,'[2]Balance económico'!$E:$E,"-",0) -> -6.9728796e+10 | AJ52: =_xlfn.XLOOKUP($E52,'[2]Balance económico'!$C:$C,'[2]Balance económico'!$F:$F,"-",0) -> 1.7439365e+10 | AK52: =IF(AA52>0,"PPA","-") -> PPA | AL52: {=IFERROR((X52*[2]!Tabla2[Bloque A] + 'BD Centrales 2025'!Y298*[2]!Tabla2[Bloque B] + 'BD Centrales 2025'!Z298*[2]!Tabla2[Bloque C])*#REF!,"-")} -> - | AM52: =IFERROR(AH52+AL52,"-") -> - | AN52: =IFERROR((AH52+AI52+AJ52)/(SUMIFS($W$2:$W$1194,$E$2:$E$1194,E52)*1000*#REF!),0) -> 0
A53: 75 | B53: CE08G0434 | C53: TER SANTA LIDIA | D53: GM HOLDINGS S.A. | E53: =_xlfn.XLOOKUP(D53,'[2]Coordinados SEN'!$A:$A,'[2]Coordinados SEN'!$B:$B,"-",0) -> 76.240.103-7 | F53: GENERADORA METROPOLITANA SPA | G53: =COUNTIFS($D$2:$D$1194,D53) -> 3 | H53: S/E CHARRUA 220KV B2 | I53: S/E CHARRUA 220KV | J53: =_xlfn.XLOOKUP(I53,'[2]Barras CMg'!$E$2:$E$1527,'[2]Barras CMg'!$A$2:$A$1527,"------",0,1) -> CHARRUA_______220 | K53: 1 | L53: 2025 | M53: Termoeléctrica | N53: Termoeléctrica de turbina a gas | O53: Instalaciones de generación | P53: Biobío | Q53: Biobío | R53: Cabrero | S53: Operativa | T53: 24-04-2009 | U53: 142.36 | V53: 140.88 | W53: =_xlfn.XLOOKUP(C53,#REF!,#REF!,"S/I",0) -> #REF! | X53: =_xlfn.XLOOKUP($D53,[2]Retiros_dinamica!$F:$F,[2]Retiros_dinamica!B:B,"S/I",0) -> 777731.54 | Y53: =_xlfn.XLOOKUP($D53,[2]Retiros_dinamica!$F:$F,[2]Retiros_dinamica!C:C,"S/I",0) -> 922797.71 | Z53: =_xlfn.XLOOKUP($D53,[2]Retiros_dinamica!$F:$F,[2]Retiros_dinamica!D:D,"S/I",0) -> 511925.91 | AA53: =_xlfn.XLOOKUP($D53,[2]Retiros_dinamica!$F:$F,[2]Retiros_dinamica!E:E,"S/I",0) -> 2212455.2 | AB53: =_xlfn.XLOOKUP(C53,[2]CMg!$I$4:$I$106,[2]CMg!$M$4:$M$106,"----",0,1) -> ---- | AH53: =_xlfn.XLOOKUP($E53,'[2]Balance económico'!$C:$C,'[2]Balance económico'!$D:$D,"-",0) -> -6.1321669e+10 | AI53: =_xlfn.XLOOKUP($E53,'[2]Balance económico'!$C:$C,'[2]Balance económico'!$E:$E,"-",0) -> -4.5573628e+10 | AJ53: =_xlfn.XLOOKUP($E53,'[2]Balance económico'!$C:$C,'[2]Balance económico'!$F:$F,"-",0) -> 1.0642872e+10 | AK53: =IF(AA53>0,"PPA","-") -> PPA | AL53: {=IFERROR((X53*[2]!Tabla2[Bloque A] + 'BD Centrales 2025'!Y1175*[2]!Tabla2[Bloque B] + 'BD Centrales 2025'!Z1175*[2]!Tabla2[Bloque C])*#REF!,"-")} -> - | AM53: =IFERROR(AH53+AL53,"-") -> - | AN53: =IFERROR((AH53+AI53+AJ53)/(SUMIFS($W$2:$W$1194,$E$2:$E$1194,E53)*1000*#REF!),0) -> 0
A54: 77 | B54: CE02G0010 | C54: HP VOLCAN | D54: AES ANDES S.A. | E54: =_xlfn.XLOOKUP(D54,'[2]Coordinados SEN'!$A:$A,'[2]Coordinados SEN'!$B:$B,"-",0) -> 94.272.000-9 | F54: AES ANDES S.A. | G54: =COUNTIFS($D$2:$D$1194,D54) -> 6 | H54: S/E CENTRAL QUELTEHUES 110KV | I54: S/E CENTRAL QUELTEHUES 110KV | J54: =_xlfn.XLOOKUP(I54,'[2]Barras CMg'!$E$2:$E$1527,'[2]Barras CMg'!$A$2:$A$1527,"------",0,1) -> QUELTEHUES____110 | K54: 1 | L54: 2025 | M54: Hidroeléctrica | N54: Minihidro de pasada | O54: Instalaciones de generación | P54: Metropolitana de Santiago | Q54: Cordillera | R54: San José de Maipo | S54: Operativa | T54: 31-07-1944 | U54: 13 | V54: 12.997 | W54: =_xlfn.XLOOKUP(C54,#REF!,#REF!,"S/I",0) -> #REF! | X54: =_xlfn.XLOOKUP($D54,[2]Retiros_dinamica!$F:$F,[2]Retiros_dinamica!B:B,"S/I",0) -> 1941802 | Y54: =_xlfn.XLOOKUP($D54,[2]Retiros_dinamica!$F:$F,[2]Retiros_dinamica!C:C,"S/I",0) -> 2207177.4 | Z54: =_xlfn.XLOOKUP($D54,[2]Retiros_dinamica!$F:$F,[2]Retiros_dinamica!D:D,"S/I",0) -> 1185924 | AA54: =_xlfn.XLOOKUP($D54,[2]Retiros_dinamica!$F:$F,[2]Retiros_dinamica!E:E,"S/I",0) -> 5334903.4 | AB54: =_xlfn.XLOOKUP(C54,[2]CMg!$I$4:$I$106,[2]CMg!$M$4:$M$106,"----",0,1) -> ---- | AC54: =_xlfn.XLOOKUP(C54,[2]CMg!$A$4:$A$106,[2]CMg!$B$4:$B$106,"----",0,1) -> ---- | AD54: =_xlfn.XLOOKUP(C54,'[3]Promedio solar Cmg'!$A$4:$A$106,'[3]Promedio solar Cmg'!$B$4:$B$106,"----",0,1) -> ---- | AH54: =_xlfn.XLOOKUP($E54,'[2]Balance económico'!$C:$C,'[2]Balance económico'!$D:$D,"-",0) -> 2.7456229e+10 | AI54: =_xlfn.XLOOKUP($E54,'[2]Balance económico'!$C:$C,'[2]Balance económico'!$E:$E,"-",0) -> -6.9728796e+10 | AJ54: =_xlfn.XLOOKUP($E54,'[2]Balance económico'!$C:$C,'[2]Balance económico'!$F:$F,"-",0) -> 1.7439365e+10 | AK54: =IF(AA54>0,"PPA","-") -> PPA | AL54: {=IFERROR((X54*[2]!Tabla2[Bloque A] + 'BD Centrales 2025'!Y506*[2]!Tabla2[Bloque B] + 'BD Centrales 2025'!Z506*[2]!Tabla2[Bloque C])*#REF!,"-")} -> - | AM54: =IFERROR(AH54+AL54,"-") -> - | AN54: =IFERROR((AH54+AI54+AJ54)/(SUMIFS($W$2:$W$1194,$E$2:$E$1194,E54)*1000*#REF!),0) -> 0
A55: 78 | B55: CE22G0003 | C55: TER ANTILHUE | D55: GENERADORA ANTILHUE SPA | E55: =_xlfn.XLOOKUP(D55,'[2]Coordinados SEN'!$A:$A,'[2]Coordinados SEN'!$B:$B,"-",0) -> 76.009.904-K | F55: GENERADORA ANTILHUE SPA | G55: =COUNTIFS($D$2:$D$1194,D55) -> 1 | H55: S/E ANTILHUE 220KV | I55: S/E VALDIVIA 220KV | J55: =_xlfn.XLOOKUP(I55,'[2]Barras CMg'!$E$2:$E$1527,'[2]Barras CMg'!$A$2:$A$1527,"------",0,1) -> VALDIVIA______220 | K55: 2 | L55: 2025 | M55: Termoeléctrica | N55: Termoeléctrica de turbina a gas | O55: Instalaciones de generación | P55: Los Ríos | Q55: Valdivia | R55: Valdivia | S55: Operativa | T55: 07-01-2005 | U55: 95.923 | V55: 94.403 | W55: =_xlfn.XLOOKUP(C55,#REF!,#REF!,"S/I",0) -> #REF! | X55: =_xlfn.XLOOKUP($D55,[2]Retiros_dinamica!$F:$F,[2]Retiros_dinamica!B:B,"S/I",0) -> S/I | Y55: =_xlfn.XLOOKUP($D55,[2]Retiros_dinamica!$F:$F,[2]Retiros_dinamica!C:C,"S/I",0) -> S/I | Z55: =_xlfn.XLOOKUP($D55,[2]Retiros_dinamica!$F:$F,[2]Retiros_dinamica!D:D,"S/I",0) -> S/I | AA55: =_xlfn.XLOOKUP($D55,[2]Retiros_dinamica!$F:$F,[2]Retiros_dinamica!E:E,"S/I",0) -> S/I | AB55: =_xlfn.XLOOKUP(C55,[2]CMg!$I$4:$I$106,[2]CMg!$M$4:$M$106,"----",0,1) -> ---- | AH55: =_xlfn.XLOOKUP($E55,'[2]Balance económico'!$C:$C,'[2]Balance económico'!$D:$D,"-",0) -> 8.8964682e+08 | AI55: =_xlfn.XLOOKUP($E55,'[2]Balance económico'!$C:$C,'[2]Balance económico'!$E:$E,"-",0) -> 4.8978966e+09 | AJ55: =_xlfn.XLOOKUP($E55,'[2]Balance económico'!$C:$C,'[2]Balance económico'!$F:$F,"-",0) -> ---- | AK55: =IF(AA55>0,"PPA","-") -> PPA | AL55: {=IFERROR((X55*[2]!Tabla2[Bloque A] + 'BD Centrales 2025'!Y990*[2]!Tabla2[Bloque B] + 'BD Centrales 2025'!Z990*[2]!Tabla2[Bloque C])*#REF!,"-")} -> - | AM55: =IFERROR(AH55+AL55,"-") -> - | AN55: =IFERROR((AH55+AI55+AJ55)/(SUMIFS($W$2:$W$1194,$E$2:$E$1194,E55)*1000*#REF!),0) -> 0
A56: 79 | B56: CE01G0002 | C56: TER HORCONES | D56: ARAUCO BIOENERGÍA SPA | E56: =_xlfn.XLOOKUP(D56,'[2]Coordinados SEN'!$A:$A,'[2]Coordinados SEN'!$B:$B,"-",0) -> 96.547.510-9 | F56: ARAUCO BIOENERGÍA SPA | G56: =COUNTIFS($D$2:$D$1194,D56) -> 10 | H56: S/E CENTRAL HORCONES 66KV | I56: S/E HORCONES 66KV | J56: =_xlfn.XLOOKUP(I56,'[2]Barras CMg'!$E$2:$E$1527,'[2]Barras CMg'!$A$2:$A$1527,"------",0,1) -> HORCONES______066 | K56: 1 | L56: 2025 | M56: Termoeléctrica | N56: Termoeléctrica de turbina a gas | O56: Instalaciones de generación | P56: Biobío | Q56: Arauco | R56: Arauco | S56: Operativa | T56: 22-09-2004 | U56: 24.3 | V56: 24.3 | W56: =_xlfn.XLOOKUP(C56,#REF!,#REF!,"S/I",0) -> #REF! | X56: =_xlfn.XLOOKUP($D56,[2]Retiros_dinamica!$F:$F,[2]Retiros_dinamica!B:B,"S/I",0) -> 193066.55 | Y56: =_xlfn.XLOOKUP($D56,[2]Retiros_dinamica!$F:$F,[2]Retiros_dinamica!C:C,"S/I",0) -> 213650.33 | Z56: =_xlfn.XLOOKUP($D56,[2]Retiros_dinamica!$F:$F,[2]Retiros_dinamica!D:D,"S/I",0) -> 90934.152 | AA56: =_xlfn.XLOOKUP($D56,[2]Retiros_dinamica!$F:$F,[2]Retiros_dinamica!E:E,"S/I",0) -> 497651.03 | AB56: =_xlfn.XLOOKUP(C56,[2]CMg!$I$4:$I$106,[2]CMg!$M$4:$M$106,"----",0,1) -> ---- | AH56: =_xlfn.XLOOKUP($E56,'[2]Balance económico'!$C:$C,'[2]Balance económico'!$D:$D,"-",0) -> 3.9346943e+10 | AI56: =_xlfn.XLOOKUP($E56,'[2]Balance económico'!$C:$C,'[2]Balance económico'!$E:$E,"-",0) -> 5.7403554e+09 | AJ56: =_xlfn.XLOOKUP($E56,'[2]Balance económico'!$C:$C,'[2]Balance económico'!$F:$F,"-",0) -> 1.4375479e+09 | AK56: =IF(AA56>0,"PPA","-") -> PPA | AL56: {=IFERROR((X56*[2]!Tabla2[Bloque A] + 'BD Centrales 2025'!Y1119*[2]!Tabla2[Bloque B] + 'BD Centrales 2025'!Z1119*[2]!Tabla2[Bloque C])*#REF!,"-")} -> - | AM56: =IFERROR(AH56+AL56,"-") -> - | AN56: =IFERROR((AH56+AI56+AJ56)/(SUMIFS($W$2:$W$1194,$E$2:$E$1194,E56)*1000*#REF!),0) -> 0
A57: 80 | B57: CE02G0002 | C57: TER NUEVA ALDEA II | D57: ARAUCO BIOENERGÍA SPA | E57: =_xlfn.XLOOKUP(D57,'[2]Coordinados SEN'!$A:$A,'[2]Coordinados SEN'!$B:$B,"-",0) -> 96.547.510-9 | F57: ARAUCO BIOENERGÍA SPA | G57: =COUNTIFS($D$2:$D$1194,D57) -> 10 | H57: S/E NUEVA ALDEA 15KV | I57: S/E NUEVA ALDEA 15KV | J57: =_xlfn.XLOOKUP(I57,'[2]Barras CMg'!$E$2:$E$1527,'[2]Barras CMg'!$A$2:$A$1527,"------",0,1) -> NVA_ALDEA3____015 | K57: 1 | L57: 2025 | M57: Termoeléctrica | N57: Termoeléctrica de turbina a gas | O57: Instalaciones de generación | P57: Ñuble | Q57: Itata | R57: Ranquil | S57: Operativa | T57: 01-05-2006 | U57: 10.31388 | V57: 9.88555 | W57: =_xlfn.XLOOKUP(C57,#REF!,#REF!,"S/I",0) -> #REF! | X57: =_xlfn.XLOOKUP($D57,[2]Retiros_dinamica!$F:$F,[2]Retiros_dinamica!B:B,"S/I",0) -> 193066.55 | Y57: =_xlfn.XLOOKUP($D57,[2]Retiros_dinamica!$F:$F,[2]Retiros_dinamica!C:C,"S/I",0) -> 213650.33 | Z57: =_xlfn.XLOOKUP($D57,[2]Retiros_dinamica!$F:$F,[2]Retiros_dinamica!D:D,"S/I",0) -> 90934.152 | AA57: =_xlfn.XLOOKUP($D57,[2]Retiros_dinamica!$F:$F,[2]Retiros_dinamica!E:E,"S/I",0) -> 497651.03 | AB57: =_xlfn.XLOOKUP(C57,[2]CMg!$I$4:$I$106,[2]CMg!$M$4:$M$106,"----",0,1) -> ---- | AH57: =_xlfn.XLOOKUP($E57,'[2]Balance económico'!$C:$C,'[2]Balance económico'!$D:$D,"-",0) -> 3.9346943e+10 | AI57: =_xlfn.XLOOKUP($E57,'[2]Balance económico'!$C:$C,'[2]Balance económico'!$E:$E,"-",0) -> 5.7403554e+09 | AJ57: =_xlfn.XLOOKUP($E57,'[2]Balance económico'!$C:$C,'[2]Balance económico'!$F:$F,"-",0) -> 1.4375479e+09 | AK57: =IF(AA57>0,"PPA","-") -> PPA | AL57: {=IFERROR((X57*[2]!Tabla2[Bloque A] + 'BD Centrales 2025'!Y1153*[2]!Tabla2[Bloque B] + 'BD Centrales 2025'!Z1153*[2]!Tabla2[Bloque C])*#REF!,"-")} -> - | AM57: =IFERROR(AH57+AL57,"-") -> - | AN57: =IFERROR((AH57+AI57+AJ57)/(SUMIFS($W$2:$W$1194,$E$2:$E$1194,E57)*1000*#REF!),0) -> 0
A58: 81 | B58: CE02G0062 | C58: TER PUNTA COLORADA | D58: COMPAÑÍA BARRICK CHILE GENERACIÓN SPA | E58: =_xlfn.XLOOKUP(D58,'[2]Coordinados SEN'!$A:$A,'[2]Coordinados SEN'!$B:$B,"-",0) -> 96.576.920-K | F58: COMPAÑÍA BARRICK CHILE GENERACIÓN SPA | G58: =COUNTIFS($D$2:$D$1194,D58) -> 2 | H58: S/E PUNTA COLORADA 220KV | I58: S/E PUNTA COLORADA 220KV | J58: =_xlfn.XLOOKUP(I58,'[2]Barras CMg'!$E$2:$E$1527,'[2]Barras CMg'!$A$2:$A$1527,"------",0,1) -> P.COLORADA____220 | K58: 1 | L58: 2025 | M58: Termoeléctrica | N58: Termoeléctrica de turbina a gas | O58: Instalaciones de generación | P58: Coquimbo | Q58: Elqui | R58: La Higuera | S58: Operativa | T58: 03-12-2010 | U58: 16.056 | V58: 15.856 | W58: =_xlfn.XLOOKUP(C58,#REF!,#REF!,"S/I",0) -> #REF! | X58: =_xlfn.XLOOKUP($D58,[2]Retiros_dinamica!$F:$F,[2]Retiros_dinamica!B:B,"S/I",0) -> S/I | Y58: =_xlfn.XLOOKUP($D58,[2]Retiros_dinamica!$F:$F,[2]Retiros_dinamica!C:C,"S/I",0) -> S/I | Z58: =_xlfn.XLOOKUP($D58,[2]Retiros_dinamica!$F:$F,[2]Retiros_dinamica!D:D,"S/I",0) -> S/I | AA58: =_xlfn.XLOOKUP($D58,[2]Retiros_dinamica!$F:$F,[2]Retiros_dinamica!E:E,"S/I",0) -> S/I | AB58: =_xlfn.XLOOKUP(C58,[2]CMg!$I$4:$I$106,[2]CMg!$M$4:$M$106,"----",0,1) -> ---- | AH58: =_xlfn.XLOOKUP($E58,'[2]Balance económico'!$C:$C,'[2]Balance económico'!$D:$D,"-",0) -> -50870753 | AI58: =_xlfn.XLOOKUP($E58,'[2]Balance económico'!$C:$C,'[2]Balance económico'!$E:$E,"-",0) -> 7.9485139e+08 | AJ58: =_xlfn.XLOOKUP($E58,'[2]Balance económico'!$C:$C,'[2]Balance económico'!$F:$F,"-",0) -> ---- | AK58: =IF(AA58>0,"PPA","-") -> PPA | AL58: {=IFERROR((X58*[2]!Tabla2[Bloque A] + 'BD Centrales 2025'!Y1162*[2]!Tabla2[Bloque B] + 'BD Centrales 2025'!Z1162*[2]!Tabla2[Bloque C])*#REF!,"-")} -> - | AM58: =IFERROR(AH58+AL58,"-") -> - | AN58: =IFERROR((AH58+AI58+AJ58)/(SUMIFS($W$2:$W$1194,$E$2:$E$1194,E58)*1000*#REF!),0) -> 0
A59: 82 | B59: CE01G0598 | C59: TER YUNGAY | D59: CENTRAL YUNGAY S.A. | E59: =_xlfn.XLOOKUP(D59,'[2]Coordinados SEN'!$A:$A,'[2]Coordinados SEN'!$B:$B,"-",0) -> 76.060.441-0 | F59: CENTRAL YUNGAY S.A. | G59: =COUNTIFS($D$2:$D$1194,D59) -> 1 | H59: S/E YUNGAY 154KV | I59: S/E CHARRUA 154KV | J59: =_xlfn.XLOOKUP(I59,'[2]Barras CMg'!$E$2:$E$1527,'[2]Barras CMg'!$A$2:$A$1527,"------",0,1) -> CHARRUA_______154 | K59: 4 | L59: 2025 | M59: Termoeléctrica | N59: Termoeléctrica de turbina a gas | O59: Instalaciones de generación | P59: Biobío | Q59: Biobío | R59: Cabrero | S59: Operativa | T59: 21-03-2007 | U59: 200.01 | V59: 198.775 | W59: =_xlfn.XLOOKUP(C59,#REF!,#REF!,"S/I",0) -> #REF! | X59: =_xlfn.XLOOKUP($D59,[2]Retiros_dinamica!$F:$F,[2]Retiros_dinamica!B:B,"S/I",0) -> S/I | Y59: =_xlfn.XLOOKUP($D59,[2]Retiros_dinamica!$F:$F,[2]Retiros_dinamica!C:C,"S/I",0) -> S/I | Z59: =_xlfn.XLOOKUP($D59,[2]Retiros_dinamica!$F:$F,[2]Retiros_dinamica!D:D,"S/I",0) -> S/I | AA59: =_xlfn.XLOOKUP($D59,[2]Retiros_dinamica!$F:$F,[2]Retiros_dinamica!E:E,"S/I",0) -> S/I | AB59: =_xlfn.XLOOKUP(C59,[2]CMg!$I$4:$I$106,[2]CMg!$M$4:$M$106,"----",0,1) -> ---- | AH59: =_xlfn.XLOOKUP($E59,'[2]Balance económico'!$C:$C,'[2]Balance económico'!$D:$D,"-",0) -> 1.6031812e+10 | AI59: =_xlfn.XLOOKUP($E59,'[2]Balance económico'!$C:$C,'[2]Balance económico'!$E:$E,"-",0) -> 8.4922606e+09 | AJ59: =_xlfn.XLOOKUP($E59,'[2]Balance económico'!$C:$C,'[2]Balance económico'!$F:$F,"-",0) -> ---- | AK59: =IF(AA59>0,"PPA","-") -> PPA | AL59: {=IFERROR((X59*[2]!Tabla2[Bloque A] + 'BD Centrales 2025'!Y1192*[2]!Tabla2[Bloque B] + 'BD Centrales 2025'!Z1192*[2]!Tabla2[Bloque C])*#REF!,"-")} -> - | AM59: =IFERROR(AH59+AL59,"-") -> - | AN59: =IFERROR((AH59+AI59+AJ59)/(SUMIFS($W$2:$W$1194,$E$2:$E$1194,E59)*1000*#REF!),0) -> 0
A60: 83 | B60: CE25G0021 | C60: PE CANELA II | D60: ENEL GENERACIÓN CHILE S.A. | E60: =_xlfn.XLOOKUP(D60,'[2]Coordinados SEN'!$A:$A,'[2]Coordinados SEN'!$B:$B,"-",0) -> 91.081.000-6 | F60: ENEL GENERACIÓN CHILE S.A. | G60: =COUNTIFS($D$2:$D$1194,D60) -> 21 | H60: S/E LAS PALMAS 220KV BA-A | I60: S/E LAS PALMAS 220KV | J60: =_xlfn.XLOOKUP(I60,'[2]Barras CMg'!$E$2:$E$1527,'[2]Barras CMg'!$A$2:$A$1527,"------",0,1) -> L.PALMAS______220 | K60: 40 | L60: 2025 | M60: Eólica | N60: Parque eólico | O60: Instalaciones de generación | P60: Coquimbo | Q60: Choapa | R60: Canela | S60: Operativa | T60: 11-12-2009 | U60: 60 | V60: 59.4 | W60: =_xlfn.XLOOKUP(C60,#REF!,#REF!,"S/I",0) -> #REF! | X60: =_xlfn.XLOOKUP($D60,[2]Retiros_dinamica!$F:$F,[2]Retiros_dinamica!B:B,"S/I",0) -> 7639445.9 | Y60: =_xlfn.XLOOKUP($D60,[2]Retiros_dinamica!$F:$F,[2]Retiros_dinamica!C:C,"S/I",0) -> 9104617.6 | Z60: =_xlfn.XLOOKUP($D60,[2]Retiros_dinamica!$F:$F,[2]Retiros_dinamica!D:D,"S/I",0) -> 4255877.2 | AA60: =_xlfn.XLOOKUP($D60,[2]Retiros_dinamica!$F:$F,[2]Retiros_dinamica!E:E,"S/I",0) -> 20999941 | AB60: =_xlfn.XLOOKUP(C60,[2]CMg!$I$4:$I$106,[2]CMg!$M$4:$M$106,"----",0,1) -> ---- | AC60: =_xlfn.XLOOKUP(C60,[2]CMg!$A$4:$A$106,[2]CMg!$B$4:$B$106,"----",0,1) -> ---- | AD60: =_xlfn.XLOOKUP(C60,'[3]Promedio solar Cmg'!$A$4:$A$106,'[3]Promedio solar Cmg'!$B$4:$B$106,"----",0,1) -> ---- | AH60: =_xlfn.XLOOKUP($E60,'[2]Balance económico'!$C:$C,'[2]Balance económico'!$D:$D,"-",0) -> -5.15558e+11 | AI60: =_xlfn.XLOOKUP($E60,'[2]Balance económico'!$C:$C,'[2]Balance económico'!$E:$E,"-",0) -> -1.8754195e+11 | AJ60: =_xlfn.XLOOKUP($E60,'[2]Balance económico'!$C:$C,'[2]Balance económico'!$F:$F,"-",0) -> 7.2834825e+10 | AK60: =IF(AA60>0,"PPA","-") -> PPA | AL60: {=IFERROR((X60*[2]!Tabla2[Bloque A] + 'BD Centrales 2025'!Y609*[2]!Tabla2[Bloque B] + 'BD Centrales 2025'!Z609*[2]!Tabla2[Bloque C])*#REF!,"-")} -> - | AM60: =IFERROR(AH60+AL60,"-") -> - | AN60: =IFERROR((AH60+AI60+AJ60)/(SUMIFS($W$2:$W$1194,$E$2:$E$1194,E60)*1000*#REF!),0) -> 0
A61: 84 | B61: CE07L0089 | C61: TER ARAUCO | D61: ARAUCO BIOENERGÍA SPA | E61: =_xlfn.XLOOKUP(D61,'[2]Coordinados SEN'!$A:$A,'[2]Coordinados SEN'!$B:$B,"-",0) -> 96.547.510-9 | F61: CELULOSA ARAUCO Y CONSTITUCIÓN S.A. | G61: =COUNTIFS($D$2:$D$1194,D61) -> 10 | H61: S/E PLANTA ARAUCO 66KV | I61: S/E PLANTA ARAUCO 66KV | J61: =_xlfn.XLOOKUP(I61,'[2]Barras CMg'!$E$2:$E$1527,'[2]Barras CMg'!$A$2:$A$1527,"------",0,1) -> PARAUCO_______066 | K61: 2 | L61: 2025 | M61: Termoeléctrica | N61: Termoeléctrica de turbina a vapor | O61: Instalaciones de generación | P61: Biobío | Q61: Arauco | R61: Arauco | S61: Operativa | T61: 10-04-1996 | U61: 67 | V61: 57 | W61: =_xlfn.XLOOKUP(C61,#REF!,#REF!,"S/I",0) -> #REF! | X61: =_xlfn.XLOOKUP($D61,[2]Retiros_dinamica!$F:$F,[2]Retiros_dinamica!B:B,"S/I",0) -> 193066.55 | Y61: =_xlfn.XLOOKUP($D61,[2]Retiros_dinamica!$F:$F,[2]Retiros_dinamica!C:C,"S/I",0) -> 213650.33 | Z61: =_xlfn.XLOOKUP($D61,[2]Retiros_dinamica!$F:$F,[2]Retiros_dinamica!D:D,"S/I",0) -> 90934.152 | AA61: =_xlfn.XLOOKUP($D61,[2]Retiros_dinamica!$F:$F,[2]Retiros_dinamica!E:E,"S/I",0) -> 497651.03 | AB61: =_xlfn.XLOOKUP(C61,[2]CMg!$I$4:$I$106,[2]CMg!$M$4:$M$106,"----",0,1) -> ---- | AH61: =_xlfn.XLOOKUP($E61,'[2]Balance económico'!$C:$C,'[2]Balance económico'!$D:$D,"-",0) -> 3.9346943e+10 | AI61: =_xlfn.XLOOKUP($E61,'[2]Balance económico'!$C:$C,'[2]Balance económico'!$E:$E,"-",0) -> 5.7403554e+09 | AJ61: =_xlfn.XLOOKUP($E61,'[2]Balance económico'!$C:$C,'[2]Balance económico'!$F:$F,"-",0) -> 1.4375479e+09 | AK61: =IF(AA61>0,"PPA","-") -> PPA | AL61: {=IFERROR((X61*[2]!Tabla2[Bloque A] + 'BD Centrales 2025'!Y991*[2]!Tabla2[Bloque B] + 'BD Centrales 2025'!Z991*[2]!Tabla2[Bloque C])*#REF!,"-")} -> - | AM61: =IFERROR(AH61+AL61,"-") -> - | AN61: =IFERROR((AH61+AI61+AJ61)/(SUMIFS($W$2:$W$1194,$E$2:$E$1194,E61)*1000*#REF!),0) -> 0
A62: 86 | B62: CE04L0089 | C62: TER LICANTEN | D62: ARAUCO BIOENERGÍA SPA | E62: =_xlfn.XLOOKUP(D62,'[2]Coordinados SEN'!$A:$A,'[2]Coordinados SEN'!$B:$B,"-",0) -> 96.547.510-9 | F62: CELULOSA ARAUCO Y CONSTITUCIÓN S.A. | G62: =COUNTIFS($D$2:$D$1194,D62) -> 10 | H62: S/E Licanten 66KV | I62: S/E LICANTEN 66KV | J62: =_xlfn.XLOOKUP(I62,'[2]Barras CMg'!$E$2:$E$1527,'[2]Barras CMg'!$A$2:$A$1527,"------",0,1) -> LICANTEN______066 | K62: 1 | L62: 2025 | M62: Termoeléctrica | N62: Termoeléctrica de turbina a vapor | O62: Pequeños medio de generación o PMG | P62: Maule | Q62: Curicó | R62: Licantén | S62: Operativa | T62: 28-04-2004 | U62: 6 | V62: 6 | W62: =_xlfn.XLOOKUP(C62,#REF!,#REF!,"S/I",0) -> #REF! | X62: =_xlfn.XLOOKUP($D62,[2]Retiros_dinamica!$F:$F,[2]Retiros_dinamica!B:B,"S/I",0) -> 193066.55 | Y62: =_xlfn.XLOOKUP($D62,[2]Retiros_dinamica!$F:$F,[2]Retiros_dinamica!C:C,"S/I",0) -> 213650.33 | Z62: =_xlfn.XLOOKUP($D62,[2]Retiros_dinamica!$F:$F,[2]Retiros_dinamica!D:D,"S/I",0) -> 90934.152 | AA62: =_xlfn.XLOOKUP($D62,[2]Retiros_dinamica!$F:$F,[2]Retiros_dinamica!E:E,"S/I",0) -> 497651.03 | AB62: =_xlfn.XLOOKUP(C62,[2]CMg!$I$4:$I$106,[2]CMg!$M$4:$M$106,"----",0,1) -> ---- | AH62: =_xlfn.XLOOKUP($E62,'[2]Balance económico'!$C:$C,'[2]Balance económico'!$D:$D,"-",0) -> 3.9346943e+10 | AI62: =_xlfn.XLOOKUP($E62,'[2]Balance económico'!$C:$C,'[2]Balance económico'!$E:$E,"-",0) -> 5.7403554e+09 | AJ62: =_xlfn.XLOOKUP($E62,'[2]Balance económico'!$C:$C,'[2]Balance económico'!$F:$F,"-",0) -> 1.4375479e+09 | AK62: =IF(AA62>0,"PPA","-") -> PPA | AL62: {=IFERROR((X62*[2]!Tabla2[Bloque A] + 'BD Centrales 2025'!Y1128*[2]!Tabla2[Bloque B] + 'BD Centrales 2025'!Z1128*[2]!Tabla2[Bloque C])*#REF!,"-")} -> - | AM62: =IFERROR(AH62+AL62,"-") -> - | AN62: =IFERROR((AH62+AI62+AJ62)/(SUMIFS($W$2:$W$1194,$E$2:$E$1194,E62)*1000*#REF!),0) -> 0
A63: 88 | B63: CE05L0089 | C63: TER VALDIVIA | D63: ARAUCO BIOENERGÍA SPA | E63: =_xlfn.XLOOKUP(D63,'[2]Coordinados SEN'!$A:$A,'[2]Coordinados SEN'!$B:$B,"-",0) -> 96.547.510-9 | F63: CELULOSA ARAUCO Y CONSTITUCIÓN S.A. | G63: =COUNTIFS($D$2:$D$1194,D63) -> 10 | H63: S/E CIRUELOS 220KV | I63: S/E CIRUELOS 220KV | J63: =_xlfn.XLOOKUP(I63,'[2]Barras CMg'!$E$2:$E$1527,'[2]Barras CMg'!$A$2:$A$1527,"------",0,1) -> CIRUELOS______220 | K63: 1 | L63: 2025 | M63: Termoeléctrica | N63: Termoeléctrica de turbina a vapor | O63: Instalaciones de generación | P63: Los Ríos | Q63: Valdivia | R63: Mariquina | S63: Operativa | T63: 12-05-2004 | U63: 61 | V63: 61 | W63: =_xlfn.XLOOKUP(C63,#REF!,#REF!,"S/I",0) -> #REF! | X63: =_xlfn.XLOOKUP($D63,[2]Retiros_dinamica!$F:$F,[2]Retiros_dinamica!B:B,"S/I",0) -> 193066.55 | Y63: =_xlfn.XLOOKUP($D63,[2]Retiros_dinamica!$F:$F,[2]Retiros_dinamica!C:C,"S/I",0) -> 213650.33 | Z63: =_xlfn.XLOOKUP($D63,[2]Retiros_dinamica!$F:$F,[2]Retiros_dinamica!D:D,"S/I",0) -> 90934.152 | AA63: =_xlfn.XLOOKUP($D63,[2]Retiros_dinamica!$F:$F,[2]Retiros_dinamica!E:E,"S/I",0) -> 497651.03 | AB63: =_xlfn.XLOOKUP(C63,[2]CMg!$I$4:$I$106,[2]CMg!$M$4:$M$106,"----",0,1) -> ---- | AH63: =_xlfn.XLOOKUP($E63,'[2]Balance económico'!$C:$C,'[2]Balance económico'!$D:$D,"-",0) -> 3.9346943e+10 | AI63: =_xlfn.XLOOKUP($E63,'[2]Balance económico'!$C:$C,'[2]Balance económico'!$E:$E,"-",0) -> 5.7403554e+09 | AJ63: =_xlfn.XLOOKUP($E63,'[2]Balance económico'!$C:$C,'[2]Balance económico'!$F:$F,"-",0) -> 1.4375479e+09 | AK63: =IF(AA63>0,"PPA","-") -> PPA | AL63: {=IFERROR((X63*[2]!Tabla2[Bloque A] + 'BD Centrales 2025'!Y1188*[2]!Tabla2[Bloque B] + 'BD Centrales 2025'!Z1188*[2]!Tabla2[Bloque C])*#REF!,"-")} -> - | AM63: =IFERROR(AH63+AL63,"-") -> - | AN63: =IFERROR((AH63+AI63+AJ63)/(SUMIFS($W$2:$W$1194,$E$2:$E$1194,E63)*1000*#REF!),0) -> 0
A64: 89 | B64: CE02G0004 | C64: TER CANDELARIA | D64: COLBÚN S.A. | E64: =_xlfn.XLOOKUP(D64,'[2]Coordinados SEN'!$A:$A,'[2]Coordinados SEN'!$B:$B,"-",0) -> 96.505.760-9 | F64: COLBÚN S.A. | G64: =COUNTIFS($D$2:$D$1194,D64) -> 29 | H64: S/E CANDELARIA 220KV | I64: S/E CANDELARIA 220KV | J64: =_xlfn.XLOOKUP(I64,'[2]Barras CMg'!$E$2:$E$1527,'[2]Barras CMg'!$A$2:$A$1527,"------",0,1) -> CANDELARIA____220 | K64: 2 | L64: 2025 | M64: Termoeléctrica | N64: Termoeléctrica de turbina a gas | O64: Instalaciones de generación | P64: Libertador General Bernardo O'Higgins | Q64: Cachapoal | R64: Mostazal | S64: Operativa | T64: 02-05-2005 | U64: 239,4 (DIESEL) / 249,71 (GN) | V64: 237,61 (DIESEL) / 247,9 (GN) | W64: =_xlfn.XLOOKUP(C64,#REF!,#REF!,"S/I",0) -> #REF! | X64: =_xlfn.XLOOKUP($D64,[2]Retiros_dinamica!$F:$F,[2]Retiros_dinamica!B:B,"S/I",0) -> 3718226.1 | Y64: =_xlfn.XLOOKUP($D64,[2]Retiros_dinamica!$F:$F,[2]Retiros_dinamica!C:C,"S/I",0) -> 3629256.6 | Z64: =_xlfn.XLOOKUP($D64,[2]Retiros_dinamica!$F:$F,[2]Retiros_dinamica!D:D,"S/I",0) -> 1641521.7 | AA64: =_xlfn.XLOOKUP($D64,[2]Retiros_dinamica!$F:$F,[2]Retiros_dinamica!E:E,"S/I",0) -> 8989004.4 | AB64: =_xlfn.XLOOKUP(C64,[2]CMg!$I$4:$I$106,[2]CMg!$M$4:$M$106,"----",0,1) -> ---- | AH64: =_xlfn.XLOOKUP($E64,'[2]Balance económico'!$C:$C,'[2]Balance económico'!$D:$D,"-",0) -> -1.345249e+09 | AI64: =_xlfn.XLOOKUP($E64,'[2]Balance económico'!$C:$C,'[2]Balance económico'!$E:$E,"-",0) -> 1.898617e+09 | AJ64: =_xlfn.XLOOKUP($E64,'[2]Balance económico'!$C:$C,'[2]Balance económico'!$F:$F,"-",0) -> 3.0881173e+10 | AK64: =IF(AA64>0,"PPA","-") -> PPA | AL64: {=IFERROR((X64*[2]!Tabla2[Bloque A] + 'BD Centrales 2025'!Y997*[2]!Tabla2[Bloque B] + 'BD Centrales 2025'!Z997*[2]!Tabla2[Bloque C])*#REF!,"-")} -> - | AM64: =IFERROR(AH64+AL64,"-") -> - | AN64: =IFERROR((AH64+AI64+AJ64)/(SUMIFS($W$2:$W$1194,$E$2:$E$1194,E64)*1000*#REF!),0) -> 0
A65: 90 | B65: CE13G0004 | C65: HE CANUTILLAR | D65: COLBÚN S.A. | E65: =_xlfn.XLOOKUP(D65,'[2]Coordinados SEN'!$A:$A,'[2]Coordinados SEN'!$B:$B,"-",0) -> 96.505.760-9 | F65: COLBÚN S.A. | G65: =COUNTIFS($D$2:$D$1194,D65) -> 29 | H65: S/E CENTRAL CANUTILLAR 220KV | I65: S/E CANUTILLAR 220KV | J65: =_xlfn.XLOOKUP(I65,'[2]Barras CMg'!$E$2:$E$1527,'[2]Barras CMg'!$A$2:$A$1527,"------",0,1) -> CANUTILLAR____220 | K65: 2 | L65: 2025 | M65: Hidroeléctrica | N65: Hidroeléctrica de embalse | O65: Instalaciones de generación | P65: Los Lagos | Q65: Llanquihue | R65: Cochamó | S65: Operativa | T65: 31-07-1990 | U65: 172 | V65: 171.57 | W65: =_xlfn.XLOOKUP(C65,#REF!,#REF!,"S/I",0) -> #REF! | X65: =_xlfn.XLOOKUP($D65,[2]Retiros_dinamica!$F:$F,[2]Retiros_dinamica!B:B,"S/I",0) -> 3718226.1 | Y65: =_xlfn.XLOOKUP($D65,[2]Retiros_dinamica!$F:$F,[2]Retiros_dinamica!C:C,"S/I",0) -> 3629256.6 | Z65: =_xlfn.XLOOKUP($D65,[2]Retiros_dinamica!$F:$F,[2]Retiros_dinamica!D:D,"S/I",0) -> 1641521.7 | AA65: =_xlfn.XLOOKUP($D65,[2]Retiros_dinamica!$F:$F,[2]Retiros_dinamica!E:E,"S/I",0) -> 8989004.4 | AB65: =_xlfn.XLOOKUP(C65,[2]CMg!$I$4:$I$106,[2]CMg!$M$4:$M$106,"----",0,1) -> ---- | AC65: =_xlfn.XLOOKUP(C65,[2]CMg!$A$4:$A$106,[2]CMg!$B$4:$B$106,"----",0,1) -> ---- | AD65: =_xlfn.XLOOKUP(C65,'[3]Promedio solar Cmg'!$A$4:$A$106,'[3]Promedio solar Cmg'!$B$4:$B$106,"----",0,1) -> ---- | AH65: =_xlfn.XLOOKUP($E65,'[2]Balance económico'!$C:$C,'[2]Balance económico'!$D:$D,"-",0) -> -1.345249e+09 | AI65: =_xlfn.XLOOKUP($E65,'[2]Balance económico'!$C:$C,'[2]Balance económico'!$E:$E,"-",0) -> 1.898617e+09 | AJ65: =_xlfn.XLOOKUP($E65,'[2]Balance económico'!$C:$C,'[2]Balance económico'!$F:$F,"-",0) -> 3.0881173e+10 | AK65: =IF(AA65>0,"PPA","-") -> PPA | AL65: {=IFERROR((X65*[2]!Tabla2[Bloque A] + 'BD Centrales 2025'!Y6*[2]!Tabla2[Bloque B] + 'BD Centrales 2025'!Z6*[2]!Tabla2[Bloque C])*#REF!,"-")} -> - | AM65: =IFERROR(AH65+AL65,"-") -> - | AN65: =IFERROR((AH65+AI65+AJ65)/(SUMIFS($W$2:$W$1194,$E$2:$E$1194,E65)*1000*#REF!),0) -> 0
A66: 91 | B66: CE10G0004 | C66: HP CHIBURGO | D66: COLBÚN S.A. | E66: =_xlfn.XLOOKUP(D66,'[2]Coordinados SEN'!$A:$A,'[2]Coordinados SEN'!$B:$B,"-",0) -> 96.505.760-9 | F66: COLBÚN S.A. | G66: =COUNTIFS($D$2:$D$1194,D66) -> 29 | H66: S/E CENTRAL CHIBURGO 66KV | I66: S/E COLBUN 220KV | J66: =_xlfn.XLOOKUP(I66,'[2]Barras CMg'!$E$2:$E$1527,'[2]Barras CMg'!$A$2:$A$1527,"------",0,1) -> COLBUN________220 | K66: 2 | L66: 2025 | M66: Hidroeléctrica | N66: Minihidro de pasada | O66: Instalaciones de generación | P66: Maule | Q66: Linares | R66: Colbún | S66: Operativa | T66: 19-07-2007 | U66: 19.4 | V66: 19.1575 | W66: =_xlfn.XLOOKUP(C66,#REF!,#REF!,"S/I",0) -> #REF! | X66: =_xlfn.XLOOKUP($D66,[2]Retiros_dinamica!$F:$F,[2]Retiros_dinamica!B:B,"S/I",0) -> 3718226.1 | Y66: =_xlfn.XLOOKUP($D66,[2]Retiros_dinamica!$F:$F,[2]Retiros_dinamica!C:C,"S/I",0) -> 3629256.6 | Z66: =_xlfn.XLOOKUP($D66,[2]Retiros_dinamica!$F:$F,[2]Retiros_dinamica!D:D,"S/I",0) -> 1641521.7 | AA66: =_xlfn.XLOOKUP($D66,[2]Retiros_dinamica!$F:$F,[2]Retiros_dinamica!E:E,"S/I",0) -> 8989004.4 | AB66: =_xlfn.XLOOKUP(C66,[2]CMg!$I$4:$I$106,[2]CMg!$M$4:$M$106,"----",0,1) -> ---- | AC66: =_xlfn.XLOOKUP(C66,[2]CMg!$A$4:$A$106,[2]CMg!$B$4:$B$106,"----",0,1) -> ---- | AD66: =_xlfn.XLOOKUP(C66,'[3]Promedio solar Cmg'!$A$4:$A$106,'[3]Promedio solar Cmg'!$B$4:$B$106,"----",0,1) -> ---- | AH66: =_xlfn.XLOOKUP($E66,'[2]Balance económico'!$C:$C,'[2]Balance económico'!$D:$D,"-",0) -> -1.345249e+09 | AI66: =_xlfn.XLOOKUP($E66,'[2]Balance económico'!$C:$C,'[2]Balance económico'!$E:$E,"-",0) -> 1.898617e+09 | AJ66: =_xlfn.XLOOKUP($E66,'[2]Balance económico'!$C:$C,'[2]Balance económico'!$F:$F,"-",0) -> 3.0881173e+10 | AK66: =IF(AA66>0,"PPA","-") -> PPA | AL66: {=IFERROR((X66*[2]!Tabla2[Bloque A] + 'BD Centrales 2025'!Y37*[2]!Tabla2[Bloque B] + 'BD Centrales 2025'!Z37*[2]!Tabla2[Bloque C])*#REF!,"-")} -> - | AM66: =IFERROR(AH66+AL66,"-") -> - | AN66: =IFERROR((AH66+AI66+AJ66)/(SUMIFS($W$2:$W$1194,$E$2:$E$1194,E66)*1000*#REF!),0) -> 0
A67: 92 | B67: CE01G0004 | C67: HE COLBUN | D67: COLBÚN S.A. | E67: =_xlfn.XLOOKUP(D67,'[2]Coordinados SEN'!$A:$A,'[2]Coordinados SEN'!$B:$B,"-",0) -> 96.505.760-9 | F67: COLBÚN S.A. | G67: =COUNTIFS($D$2:$D$1194,D67) -> 29 | H67: S/E COLBUN 220KV | I67: S/E COLBUN 220KV | J67: =_xlfn.XLOOKUP(I67,'[2]Barras CMg'!$E$2:$E$1527,'[2]Barras CMg'!$A$2:$A$1527,"------",0,1) -> COLBUN________220 | K67: 2 | L67: 2025 | M67: Hidroeléctrica | N67: Hidroeléctrica de embalse | O67: Instalaciones de generación | P67: Maule | Q67: Linares | R67: Colbún | S67: Operativa | T67: 31-07-1985 | U67: 467.3 | V67: 460.8 | W67: =_xlfn.XLOOKUP(C67,#REF!,#REF!,"S/I",0) -> #REF! | X67: =_xlfn.XLOOKUP($D67,[2]Retiros_dinamica!$F:$F,[2]Retiros_dinamica!B:B,"S/I",0) -> 3718226.1 | Y67: =_xlfn.XLOOKUP($D67,[2]Retiros_dinamica!$F:$F,[2]Retiros_dinamica!C:C,"S/I",0) -> 3629256.6 | Z67: =_xlfn.XLOOKUP($D67,[2]Retiros_dinamica!$F:$F,[2]Retiros_dinamica!D:D,"S/I",0) -> 1641521.7 | AA67: =_xlfn.XLOOKUP($D67,[2]Retiros_dinamica!$F:$F,[2]Retiros_dinamica!E:E,"S/I",0) -> 8989004.4 | AB67: =_xlfn.XLOOKUP(C67,[2]CMg!$I$4:$I$106,[2]CMg!$M$4:$M$106,"----",0,1) -> ---- | AC67: =_xlfn.XLOOKUP(C67,[2]CMg!$A$4:$A$106,[2]CMg!$B$4:$B$106,"----",0,1) -> ---- | AD67: =_xlfn.XLOOKUP(C67,'[3]Promedio solar Cmg'!$A$4:$A$106,'[3]Promedio solar Cmg'!$B$4:$B$106,"----",0,1) -> ---- | AH67: =_xlfn.XLOOKUP($E67,'[2]Balance económico'!$C:$C,'[2]Balance económico'!$D:$D,"-",0) -> -1.345249e+09 | AI67: =_xlfn.XLOOKUP($E67,'[2]Balance económico'!$C:$C,'[2]Balance económico'!$E:$E,"-",0) -> 1.898617e+09 | AJ67: =_xlfn.XLOOKUP($E67,'[2]Balance económico'!$C:$C,'[2]Balance económico'!$F:$F,"-",0) -> 3.0881173e+10 | AK67: =IF(AA67>0,"PPA","-") -> PPA | AL67: {=IFERROR((X67*[2]!Tabla2[Bloque A] + 'BD Centrales 2025'!Y8*[2]!Tabla2[Bloque B] + 'BD Centrales 2025'!Z8*[2]!Tabla2[Bloque C])*#REF!,"-")} -> - | AM67: =IFERROR(AH67+AL67,"-") -> - | AN67: =IFERROR((AH67+AI67+AJ67)/(SUMIFS($W$2:$W$1194,$E$2:$E$1194,E67)*1000*#REF!),0) -> 0
A68: 93 | B68: CE11G0004 | C68: TER LOS PINOS | D68: COLBÚN S.A. | E68: =_xlfn.XLOOKUP(D68,'[2]Coordinados SEN'!$A:$A,'[2]Coordinados SEN'!$B:$B,"-",0) -> 96.505.760-9 | F68: COLBÚN S.A. | G68: =COUNTIFS($D$2:$D$1194,D68) -> 29 | H68: S/E CENTRAL LOS PINOS 220KV | I68: S/E CHARRUA 220KV | J68: =_xlfn.XLOOKUP(I68,'[2]Barras CMg'!$E$2:$E$1527,'[2]Barras CMg'!$A$2:$A$1527,"------",0,1) -> CHARRUA_______220 | K68: 1 | L68: 2025 | M68: Termoeléctrica | N68: Termoeléctrica de turbina a gas | O68: Instalaciones de generación | P68: Biobío | Q68: Biobío | R68: Cabrero | S68: Operativa | T68: 07-04-2009 | U68: 107.7 | V68: 106.41 | W68: =_xlfn.XLOOKUP(C68,#REF!,#REF!,"S/I",0) -> #REF! | X68: =_xlfn.XLOOKUP($D68,[2]Retiros_dinamica!$F:$F,[2]Retiros_dinamica!B:B,"S/I",0) -> 3718226.1 | Y68: =_xlfn.XLOOKUP($D68,[2]Retiros_dinamica!$F:$F,[2]Retiros_dinamica!C:C,"S/I",0) -> 3629256.6 | Z68: =_xlfn.XLOOKUP($D68,[2]Retiros_dinamica!$F:$F,[2]Retiros_dinamica!D:D,"S/I",0) -> 1641521.7 | AA68: =_xlfn.XLOOKUP($D68,[2]Retiros_dinamica!$F:$F,[2]Retiros_dinamica!E:E,"S/I",0) -> 8989004.4 | AB68: =_xlfn.XLOOKUP(C68,[2]CMg!$I$4:$I$106,[2]CMg!$M$4:$M$106,"----",0,1) -> ---- | AH68: =_xlfn.XLOOKUP($E68,'[2]Balance económico'!$C:$C,'[2]Balance económico'!$D:$D,"-",0) -> -1.345249e+09 | AI68: =_xlfn.XLOOKUP($E68,'[2]Balance económico'!$C:$C,'[2]Balance económico'!$E:$E,"-",0) -> 1.898617e+09 | AJ68: =_xlfn.XLOOKUP($E68,'[2]Balance económico'!$C:$C,'[2]Balance económico'!$F:$F,"-",0) -> 3.0881173e+10 | AK68: =IF(AA68>0,"PPA","-") -> PPA | AL68: {=IFERROR((X68*[2]!Tabla2[Bloque A] + 'BD Centrales 2025'!Y1138*[2]!Tabla2[Bloque B] + 'BD Centrales 2025'!Z1138*[2]!Tabla2[Bloque C])*#REF!,"-")} -> - | AM68: =IFERROR(AH68+AL68,"-") -> - | AN68: =IFERROR((AH68+AI68+AJ68)/(SUMIFS($W$2:$W$1194,$E$2:$E$1194,E68)*1000*#REF!),0) -> 0
A69: 94 | B69: CE03G0004 | C69: HE MACHICURA | D69: COLBÚN S.A. | E69: =_xlfn.XLOOKUP(D69,'[2]Coordinados SEN'!$A:$A,'[2]Coordinados SEN'!$B:$B,"-",0) -> 96.505.760-9 | F69: COLBÚN S.A. | G69: =COUNTIFS($D$2:$D$1194,D69) -> 29 | H69: S/E MACHICURA 220KV | I69: S/E CENTRAL MACHICURA 220KV | J69: =_xlfn.XLOOKUP(I69,'[2]Barras CMg'!$E$2:$E$1527,'[2]Barras CMg'!$A$2:$A$1527,"------",0,1) -> CTR_MACHICURA_220 | K69: 2 | L69: 2025 | M69: Hidroeléctrica | N69: Hidroeléctrica de embalse | O69: Instalaciones de generación | P69: Maule | Q69: Linares | R69: Colbún | S69: Operativa | T69: 31-07-1985 | U69: 95 | V69: 94.7625 | W69: =_xlfn.XLOOKUP(C69,#REF!,#REF!,"S/I",0) -> #REF! | X69: =_xlfn.XLOOKUP($D69,[2]Retiros_dinamica!$F:$F,[2]Retiros_dinamica!B:B,"S/I",0) -> 3718226.1 | Y69: =_xlfn.XLOOKUP($D69,[2]Retiros_dinamica!$F:$F,[2]Retiros_dinamica!C:C,"S/I",0) -> 3629256.6 | Z69: =_xlfn.XLOOKUP($D69,[2]Retiros_dinamica!$F:$F,[2]Retiros_dinamica!D:D,"S/I",0) -> 1641521.7 | AA69: =_xlfn.XLOOKUP($D69,[2]Retiros_dinamica!$F:$F,[2]Retiros_dinamica!E:E,"S/I",0) -> 8989004.4 | AB69: =_xlfn.XLOOKUP(C69,[2]CMg!$I$4:$I$106,[2]CMg!$M$4:$M$106,"----",0,1) -> ---- | AC69: =_xlfn.XLOOKUP(C69,[2]CMg!$A$4:$A$106,[2]CMg!$B$4:$B$106,"----",0,1) -> ---- | AD69: =_xlfn.XLOOKUP(C69,'[3]Promedio solar Cmg'!$A$4:$A$106,'[3]Promedio solar Cmg'!$B$4:$B$106,"----",0,1) -> ---- | AH69: =_xlfn.XLOOKUP($E69,'[2]Balance económico'!$C:$C,'[2]Balance económico'!$D:$D,"-",0) -> -1.345249e+09 | AI69: =_xlfn.XLOOKUP($E69,'[2]Balance económico'!$C:$C,'[2]Balance económico'!$E:$E,"-",0) -> 1.898617e+09 | AJ69: =_xlfn.XLOOKUP($E69,'[2]Balance económico'!$C:$C,'[2]Balance económico'!$F:$F,"-",0) -> 3.0881173e+10 | AK69: =IF(AA69>0,"PPA","-") -> PPA | AL69: {=IFERROR((X69*[2]!Tabla2[Bloque A] + 'BD Centrales 2025'!Y12*[2]!Tabla2[Bloque B] + 'BD Centrales 2025'!Z12*[2]!Tabla2[Bloque C])*#REF!,"-")} -> - | AM69: =IFERROR(AH69+AL69,"-") -> - | AN69: =IFERROR((AH69+AI69+AJ69)/(SUMIFS($W$2:$W$1194,$E$2:$E$1194,E69)*1000*#REF!),0) -> 0
A70: 99 | B70: CE06G0004 | C70: TER NEHUENCO 9B | D70: COLBÚN S.A. | E70: =_xlfn.XLOOKUP(D70,'[2]Coordinados SEN'!$A:$A,'[2]Coordinados SEN'!$B:$B,"-",0) -> 96.505.760-9 | F70: COLBÚN S.A. | G70: =COUNTIFS($D$2:$D$1194,D70) -> 29 | H70: S/E SAN LUIS 220KV | I70: S/E SAN LUIS 220KV | J70: =_xlfn.XLOOKUP(I70,'[2]Barras CMg'!$E$2:$E$1527,'[2]Barras CMg'!$A$2:$A$1527,"------",0,1) -> S.LUIS2_______220 | K70: 1 | L70: 2025 | M70: Termoeléctrica | N70: Termoeléctrica de turbina a gas | O70: Instalaciones de generación | P70: Valparaíso | Q70: Quillota | R70: Quillota | S70: Operativa | T70: 15-05-2002 | U70: 89.2038 | V70: 88.2043 | W70: =_xlfn.XLOOKUP(C70,#REF!,#REF!,"S/I",0) -> #REF! | X70: =_xlfn.XLOOKUP($D70,[2]Retiros_dinamica!$F:$F,[2]Retiros_dinamica!B:B,"S/I",0) -> 3718226.1 | Y70: =_xlfn.XLOOKUP($D70,[2]Retiros_dinamica!$F:$F,[2]Retiros_dinamica!C:C,"S/I",0) -> 3629256.6 | Z70: =_xlfn.XLOOKUP($D70,[2]Retiros_dinamica!$F:$F,[2]Retiros_dinamica!D:D,"S/I",0) -> 1641521.7 | AA70: =_xlfn.XLOOKUP($D70,[2]Retiros_dinamica!$F:$F,[2]Retiros_dinamica!E:E,"S/I",0) -> 8989004.4 | AB70: =_xlfn.XLOOKUP(C70,[2]CMg!$I$4:$I$106,[2]CMg!$M$4:$M$106,"----",0,1) -> ---- | AH70: =_xlfn.XLOOKUP($E70,'[2]Balance económico'!$C:$C,'[2]Balance económico'!$D:$D,"-",0) -> -1.345249e+09 | AI70: =_xlfn.XLOOKUP($E70,'[2]Balance económico'!$C:$C,'[2]Balance económico'!$E:$E,"-",0) -> 1.898617e+09 | AJ70: =_xlfn.XLOOKUP($E70,'[2]Balance económico'!$C:$C,'[2]Balance económico'!$F:$F,"-",0) -> 3.0881173e+10 | AK70: =IF(AA70>0,"PPA","-") -> PPA | AL70: {=IFERROR((X70*[2]!Tabla2[Bloque A] + 'BD Centrales 2025'!Y1149*[2]!Tabla2[Bloque B] + 'BD Centrales 2025'!Z1149*[2]!Tabla2[Bloque C])*#REF!,"-")} -> - | AM70: =IFERROR(AH70+AL70,"-") -> - | AN70: =IFERROR((AH70+AI70+AJ70)/(SUMIFS($W$2:$W$1194,$E$2:$E$1194,E70)*1000*#REF!),0) -> 0
A71: 100 | B71: CE09G0004 | C71: HP QUILLECO | D71: COLBÚN S.A. | E71: =_xlfn.XLOOKUP(D71,'[2]Coordinados SEN'!$A:$A,'[2]Coordinados SEN'!$B:$B,"-",0) -> 96.505.760-9 | F71: COLBÚN S.A. | G71: =COUNTIFS($D$2:$D$1194,D71) -> 29 | H71: S/E CENTRAL QUILLECO 220KV | I71: S/E CENTRAL QUILLECO 220KV | J71: =_xlfn.XLOOKUP(I71,'[2]Barras CMg'!$E$2:$E$1527,'[2]Barras CMg'!$A$2:$A$1527,"------",0,1) -> QUILLECO______220 | K71: 2 | L71: 2025 | M71: Hidroeléctrica | N71: Hidroeléctrica de pasada | O71: Instalaciones de generación | P71: Biobío | Q71: Biobío | R71: Quilleco | S71: Operativa | T71: 30-04-2007 | U71: 70.8 | V71: 70.6513 | W71: =_xlfn.XLOOKUP(C71,#REF!,#REF!,"S/I",0) -> #REF! | X71: =_xlfn.XLOOKUP($D71,[2]Retiros_dinamica!$F:$F,[2]Retiros_dinamica!B:B,"S/I",0) -> 3718226.1 | Y71: =_xlfn.XLOOKUP($D71,[2]Retiros_dinamica!$F:$F,[2]Retiros_dinamica!C:C,"S/I",0) -> 3629256.6 | Z71: =_xlfn.XLOOKUP($D71,[2]Retiros_dinamica!$F:$F,[2]Retiros_dinamica!D:D,"S/I",0) -> 1641521.7 | AA71: =_xlfn.XLOOKUP($D71,[2]Retiros_dinamica!$F:$F,[2]Retiros_dinamica!E:E,"S/I",0) -> 8989004.4 | AB71: =_xlfn.XLOOKUP(C71,[2]CMg!$I$4:$I$106,[2]CMg!$M$4:$M$106,"----",0,1) -> ---- | AC71: =_xlfn.XLOOKUP(C71,[2]CMg!$A$4:$A$106,[2]CMg!$B$4:$B$106,"----",0,1) -> ---- | AD71: =_xlfn.XLOOKUP(C71,'[3]Promedio solar Cmg'!$A$4:$A$106,'[3]Promedio solar Cmg'!$B$4:$B$106,"----",0,1) -> ---- | AH71: =_xlfn.XLOOKUP($E71,'[2]Balance económico'!$C:$C,'[2]Balance económico'!$D:$D,"-",0) -> -1.345249e+09 | AI71: =_xlfn.XLOOKUP($E71,'[2]Balance económico'!$C:$C,'[2]Balance económico'!$E:$E,"-",0) -> 1.898617e+09 | AJ71: =_xlfn.XLOOKUP($E71,'[2]Balance económico'!$C:$C,'[2]Balance económico'!$F:$F,"-",0) -> 3.0881173e+10 | AK71: =IF(AA71>0,"PPA","-") -> PPA | AL71: {=IFERROR((X71*[2]!Tabla2[Bloque A] + 'BD Centrales 2025'!Y299*[2]!Tabla2[Bloque B] + 'BD Centrales 2025'!Z299*[2]!Tabla2[Bloque C])*#REF!,"-")} -> - | AM71: =IFERROR(AH71+AL71,"-") -> - | AN71: =IFERROR((AH71+AI71+AJ71)/(SUMIFS($W$2:$W$1194,$E$2:$E$1194,E71)*1000*#REF!),0) -> 0
A72: 101 | B72: CE07G0004 | C72: HP RUCUE | D72: COLBÚN S.A. | E72: =_xlfn.XLOOKUP(D72,'[2]Coordinados SEN'!$A:$A,'[2]Coordinados SEN'!$B:$B,"-",0) -> 96.505.760-9 | F72: COLBÚN S.A. | G72: =COUNTIFS($D$2:$D$1194,D72) -> 29 | H72: S/E CENTRAL RUCUE 220KV B2 | I72: S/E CENTRAL RUCUE 220KV | J72: =_xlfn.XLOOKUP(I72,'[2]Barras CMg'!$E$2:$E$1527,'[2]Barras CMg'!$A$2:$A$1527,"------",0,1) -> RUCUE_________220 | K72: 2 | L72: 2025 | M72: Hidroeléctrica | N72: Hidroeléctrica de pasada | O72: Instalaciones de generación | P72: Biobío | Q72: Biobío | R72: Quilleco | S72: Operativa | T72: 31-07-1998 | U72: 178.4 | V72: 178.1324 | W72: =_xlfn.XLOOKUP(C72,#REF!,#REF!,"S/I",0) -> #REF! | X72: =_xlfn.XLOOKUP($D72,[2]Retiros_dinamica!$F:$F,[2]Retiros_dinamica!B:B,"S/I",0) -> 3718226.1 | Y72: =_xlfn.XLOOKUP($D72,[2]Retiros_dinamica!$F:$F,[2]Retiros_dinamica!C:C,"S/I",0) -> 3629256.6 | Z72: =_xlfn.XLOOKUP($D72,[2]Retiros_dinamica!$F:$F,[2]Retiros_dinamica!D:D,"S/I",0) -> 1641521.7 | AA72: =_xlfn.XLOOKUP($D72,[2]Retiros_dinamica!$F:$F,[2]Retiros_dinamica!E:E,"S/I",0) -> 8989004.4 | AB72: =_xlfn.XLOOKUP(C72,[2]CMg!$I$4:$I$106,[2]CMg!$M$4:$M$106,"----",0,1) -> ---- | AC72: =_xlfn.XLOOKUP(C72,[2]CMg!$A$4:$A$106,[2]CMg!$B$4:$B$106,"----",0,1) -> ---- | AD72: =_xlfn.XLOOKUP(C72,'[3]Promedio solar Cmg'!$A$4:$A$106,'[3]Promedio solar Cmg'!$B$4:$B$106,"----",0,1) -> ---- | AH72: =_xlfn.XLOOKUP($E72,'[2]Balance económico'!$C:$C,'[2]Balance económico'!$D:$D,"-",0) -> -1.345249e+09 | AI72: =_xlfn.XLOOKUP($E72,'[2]Balance económico'!$C:$C,'[2]Balance económico'!$E:$E,"-",0) -> 1.898617e+09 | AJ72: =_xlfn.XLOOKUP($E72,'[2]Balance económico'!$C:$C,'[2]Balance económico'!$F:$F,"-",0) -> 3.0881173e+10 | AK72: =IF(AA72>0,"PPA","-") -> PPA | AL72: {=IFERROR((X72*[2]!Tabla2[Bloque A] + 'BD Centrales 2025'!Y353*[2]!Tabla2[Bloque B] + 'BD Centrales 2025'!Z353*[2]!Tabla2[Bloque C])*#REF!,"-")} -> - | AM72: =IFERROR(AH72+AL72,"-") -> - | AN72: =IFERROR((AH72+AI72+AJ72)/(SUMIFS($W$2:$W$1194,$E$2:$E$1194,E72)*1000*#REF!),0) -> 0
A73: 102 | B73: CE12G0004 | C73: HP SAN CLEMENTE | D73: COLBÚN S.A. | E73: =_xlfn.XLOOKUP(D73,'[2]Coordinados SEN'!$A:$A,'[2]Coordinados SEN'!$B:$B,"-",0) -> 96.505.760-9 | F73: COLBÚN S.A. | G73: =COUNTIFS($D$2:$D$1194,D73) -> 29 | H73: S/E CENTRAL CHIBURGO 66KV | I73: S/E COLBUN 220KV | J73: =_xlfn.XLOOKUP(I73,'[2]Barras CMg'!$E$2:$E$1527,'[2]Barras CMg'!$A$2:$A$1527,"------",0,1) -> COLBUN________220 | K73: 1 | L73: 2025 | M73: Hidroeléctrica | N73: Minihidro de pasada | O73: Pequeños medio de generación o PMG | P73: Maule | Q73: Talca | R73: San Clemente | S73: Operativa | T73: 16-09-2010 | U73: 5.9 | V73: 5.8853 | W73: =_xlfn.XLOOKUP(C73,#REF!,#REF!,"S/I",0) -> #REF! | X73: =_xlfn.XLOOKUP($D73,[2]Retiros_dinamica!$F:$F,[2]Retiros_dinamica!B:B,"S/I",0) -> 3718226.1 | Y73: =_xlfn.XLOOKUP($D73,[2]Retiros_dinamica!$F:$F,[2]Retiros_dinamica!C:C,"S/I",0) -> 3629256.6 | Z73: =_xlfn.XLOOKUP($D73,[2]Retiros_dinamica!$F:$F,[2]Retiros_dinamica!D:D,"S/I",0) -> 1641521.7 | AA73: =_xlfn.XLOOKUP($D73,[2]Retiros_dinamica!$F:$F,[2]Retiros_dinamica!E:E,"S/I",0) -> 8989004.4 | AB73: =_xlfn.XLOOKUP(C73,[2]CMg!$I$4:$I$106,[2]CMg!$M$4:$M$106,"----",0,1) -> ---- | AC73: =_xlfn.XLOOKUP(C73,[2]CMg!$A$4:$A$106,[2]CMg!$B$4:$B$106,"----",0,1) -> ---- | AD73: =_xlfn.XLOOKUP(C73,'[3]Promedio solar Cmg'!$A$4:$A$106,'[3]Promedio solar Cmg'!$B$4:$B$106,"----",0,1) -> ---- | AH73: =_xlfn.XLOOKUP($E73,'[2]Balance económico'!$C:$C,'[2]Balance económico'!$D:$D,"-",0) -> -1.345249e+09 | AI73: =_xlfn.XLOOKUP($E73,'[2]Balance económico'!$C:$C,'[2]Balance económico'!$E:$E,"-",0) -> 1.898617e+09 | AJ73: =_xlfn.XLOOKUP($E73,'[2]Balance económico'!$C:$C,'[2]Balance económico'!$F:$F,"-",0) -> 3.0881173e+10 | AK73: =IF(AA73>0,"PPA","-") -> PPA | AL73: {=IFERROR((X73*[2]!Tabla2[Bloque A] + 'BD Centrales 2025'!Y457*[2]!Tabla2[Bloque B] + 'BD Centrales 2025'!Z457*[2]!Tabla2[Bloque C])*#REF!,"-")} -> - | AM73: =IFERROR(AH73+AL73,"-") -> - | AN73: =IFERROR((AH73+AI73+AJ73)/(SUMIFS($W$2:$W$1194,$E$2:$E$1194,E73)*1000*#REF!),0) -> 0
A74: 103 | B74: CE08G0004 | C74: HP SAN IGNACIO | D74: COLBÚN S.A. | E74: =_xlfn.XLOOKUP(D74,'[2]Coordinados SEN'!$A:$A,'[2]Coordinados SEN'!$B:$B,"-",0) -> 96.505.760-9 | F74: COLBÚN S.A. | G74: =COUNTIFS($D$2:$D$1194,D74) -> 29 | H74: TAP SAN CLEMENTE 66KV | I74: S/E CENTRAL SAN IGNACIO 66KV | J74: =_xlfn.XLOOKUP(I74,'[2]Barras CMg'!$E$2:$E$1527,'[2]Barras CMg'!$A$2:$A$1527,"------",0,1) -> SAN_IGNACIO___066 | K74: 1 | L74: 2025 | M74: Hidroeléctrica | N74: Hidroeléctrica de pasada | O74: Instalaciones de generación | P74: Maule | Q74: Linares | R74: Yerbas Buenas | S74: Operativa | T74: 31-07-1996 | U74: 35.42 | V74: 35.08 | W74: =_xlfn.XLOOKUP(C74,#REF!,#REF!,"S/I",0) -> #REF! | X74: =_xlfn.XLOOKUP($D74,[2]Retiros_dinamica!$F:$F,[2]Retiros_dinamica!B:B,"S/I",0) -> 3718226.1 | Y74: =_xlfn.XLOOKUP($D74,[2]Retiros_dinamica!$F:$F,[2]Retiros_dinamica!C:C,"S/I",0) -> 3629256.6 | Z74: =_xlfn.XLOOKUP($D74,[2]Retiros_dinamica!$F:$F,[2]Retiros_dinamica!D:D,"S/I",0) -> 1641521.7 | AA74: =_xlfn.XLOOKUP($D74,[2]Retiros_dinamica!$F:$F,[2]Retiros_dinamica!E:E,"S/I",0) -> 8989004.4 | AB74: =_xlfn.XLOOKUP(C74,[2]CMg!$I$4:$I$106,[2]CMg!$M$4:$M$106,"----",0,1) -> ---- | AC74: =_xlfn.XLOOKUP(C74,[2]CMg!$A$4:$A$106,[2]CMg!$B$4:$B$106,"----",0,1) -> ---- | AD74: =_xlfn.XLOOKUP(C74,'[3]Promedio solar Cmg'!$A$4:$A$106,'[3]Promedio solar Cmg'!$B$4:$B$106,"----",0,1) -> ---- | AH74: =_xlfn.XLOOKUP($E74,'[2]Balance económico'!$C:$C,'[2]Balance económico'!$D:$D,"-",0) -> -1.345249e+09 | AI74: =_xlfn.XLOOKUP($E74,'[2]Balance económico'!$C:$C,'[2]Balance económico'!$E:$E,"-",0) -> 1.898617e+09 | AJ74: =_xlfn.XLOOKUP($E74,'[2]Balance económico'!$C:$C,'[2]Balance económico'!$F:$F,"-",0) -> 3.0881173e+10 | AK74: =IF(AA74>0,"PPA","-") -> PPA | AL74: {=IFERROR((X74*[2]!Tabla2[Bloque A] + 'BD Centrales 2025'!Y467*[2]!Tabla2[Bloque B] + 'BD Centrales 2025'!Z467*[2]!Tabla2[Bloque C])*#REF!,"-")} -> - | AM74: =IFERROR(AH74+AL74,"-") -> - | AN74: =IFERROR((AH74+AI74+AJ74)/(SUMIFS($W$2:$W$1194,$E$2:$E$1194,E74)*1000*#REF!),0) -> 0
A75: 104 | B75: CE14G0004 | C75: TER SANTA MARIA | D75: COLBÚN S.A. | E75: =_xlfn.XLOOKUP(D75,'[2]Coordinados SEN'!$A:$A,'[2]Coordinados SEN'!$B:$B,"-",0) -> 96.505.760-9 | F75: COLBÚN S.A. | G75: =COUNTIFS($D$2:$D$1194,D75) -> 29 | H75: S/E SANTA MARIA 220KV | I75: S/E SANTA MARIA 220KV | J75: =_xlfn.XLOOKUP(I75,'[2]Barras CMg'!$E$2:$E$1527,'[2]Barras CMg'!$A$2:$A$1527,"------",0,1) -> STA.MARIA_____220 | K75: 1 | L75: 2025 | M75: Termoeléctrica | N75: Termoeléctrica de turbina a vapor | O75: Instalaciones de generación | P75: Biobío | Q75: Concepción | R75: Coronel | S75: Operativa | T75: 15-08-2012 | U75: 378.95 | V75: 348.35 | W75: =_xlfn.XLOOKUP(C75,#REF!,#REF!,"S/I",0) -> #REF! | X75: =_xlfn.XLOOKUP($D75,[2]Retiros_dinamica!$F:$F,[2]Retiros_dinamica!B:B,"S/I",0) -> 3718226.1 | Y75: =_xlfn.XLOOKUP($D75,[2]Retiros_dinamica!$F:$F,[2]Retiros_dinamica!C:C,"S/I",0) -> 3629256.6 | Z75: =_xlfn.XLOOKUP($D75,[2]Retiros_dinamica!$F:$F,[2]Retiros_dinamica!D:D,"S/I",0) -> 1641521.7 | AA75: =_xlfn.XLOOKUP($D75,[2]Retiros_dinamica!$F:$F,[2]Retiros_dinamica!E:E,"S/I",0) -> 8989004.4 | AB75: =_xlfn.XLOOKUP(C75,[2]CMg!$I$4:$I$106,[2]CMg!$M$4:$M$106,"----",0,1) -> ---- | AH75: =_xlfn.XLOOKUP($E75,'[2]Balance económico'!$C:$C,'[2]Balance económico'!$D:$D,"-",0) -> -1.345249e+09 | AI75: =_xlfn.XLOOKUP($E75,'[2]Balance económico'!$C:$C,'[2]Balance económico'!$E:$E,"-",0) -> 1.898617e+09 | AJ75: =_xlfn.XLOOKUP($E75,'[2]Balance económico'!$C:$C,'[2]Balance económico'!$F:$F,"-",0) -> 3.0881173e+10 | AK75: =IF(AA75>0,"PPA","-") -> PPA | AL75: {=IFERROR((X75*[2]!Tabla2[Bloque A] + 'BD Centrales 2025'!Y1176*[2]!Tabla2[Bloque B] + 'BD Centrales 2025'!Z1176*[2]!Tabla2[Bloque C])*#REF!,"-")} -> - | AM75: =IFERROR(AH75+AL75,"-") -> - | AN75: =IFERROR((AH75+AI75+AJ75)/(SUMIFS($W$2:$W$1194,$E$2:$E$1194,E75)*1000*#REF!),0) -> 0
A76: 106 | B76: CE01G0005 | C76: HP CAPULLO | D76: EMPRESA ELÉCTRICA CAPULLO S.A. | E76: =_xlfn.XLOOKUP(D76,'[2]Coordinados SEN'!$A:$A,'[2]Coordinados SEN'!$B:$B,"-",0) -> 96.637.520-5 | F76: EMPRESA ELÉCTRICA CAPULLO S.A. | G76: =COUNTIFS($D$2:$D$1194,D76) -> 2 | H76: S/E PULELFU 66KV | I76: S/E PULELFU 66KV | J76: =_xlfn.XLOOKUP(I76,'[2]Barras CMg'!$E$2:$E$1527,'[2]Barras CMg'!$A$2:$A$1527,"------",0,1) -> TAP_PULELFU___066 | K76: 1 | L76: 2025 | M76: Hidroeléctrica | N76: Minihidro de pasada | O76: Instalaciones de generación | P76: Los Lagos | Q76: Osorno | R76: Puyehue | S76: Operativa | T76: 31-07-1995 | U76: 12 | V76: 11.84316 | W76: =_xlfn.XLOOKUP(C76,#REF!,#REF!,"S/I",0) -> #REF! | X76: =_xlfn.XLOOKUP($D76,[2]Retiros_dinamica!$F:$F,[2]Retiros_dinamica!B:B,"S/I",0) -> 169.05851 | Y76: =_xlfn.XLOOKUP($D76,[2]Retiros_dinamica!$F:$F,[2]Retiros_dinamica!C:C,"S/I",0) -> 264.30872 | Z76: =_xlfn.XLOOKUP($D76,[2]Retiros_dinamica!$F:$F,[2]Retiros_dinamica!D:D,"S/I",0) -> 130.3552 | AA76: =_xlfn.XLOOKUP($D76,[2]Retiros_dinamica!$F:$F,[2]Retiros_dinamica!E:E,"S/I",0) -> 563.72243 | AB76: =_xlfn.XLOOKUP(C76,[2]CMg!$I$4:$I$106,[2]CMg!$M$4:$M$106,"----",0,1) -> ---- | AC76: =_xlfn.XLOOKUP(C76,[2]CMg!$A$4:$A$106,[2]CMg!$B$4:$B$106,"----",0,1) -> ---- | AD76: =_xlfn.XLOOKUP(C76,'[3]Promedio solar Cmg'!$A$4:$A$106,'[3]Promedio solar Cmg'!$B$4:$B$106,"----",0,1) -> ---- | AH76: =_xlfn.XLOOKUP($E76,'[2]Balance económico'!$C:$C,'[2]Balance económico'!$D:$D,"-",0) -> 2.7899858e+08 | AI76: =_xlfn.XLOOKUP($E76,'[2]Balance económico'!$C:$C,'[2]Balance económico'!$E:$E,"-",0) -> 3.237494e+08 | AJ76: =_xlfn.XLOOKUP($E76,'[2]Balance económico'!$C:$C,'[2]Balance económico'!$F:$F,"-",0) -> 1171040.3 | AK76: =IF(AA76>0,"PPA","-") -> PPA | AL76: {=IFERROR((X76*[2]!Tabla2[Bloque A] + 'BD Centrales 2025'!Y25*[2]!Tabla2[Bloque B] + 'BD Centrales 2025'!Z25*[2]!Tabla2[Bloque C])*#REF!,"-")} -> - | AM76: =IFERROR(AH76+AL76,"-") -> - | AN76: =IFERROR((AH76+AI76+AJ76)/(SUMIFS($W$2:$W$1194,$E$2:$E$1194,E76)*1000*#REF!),0) -> 0
A77: 107 | B77: CE01G0082 | C77: HP LICAN | D77: AELA GENERACIÓN S.A. | E77: =_xlfn.XLOOKUP(D77,'[2]Coordinados SEN'!$A:$A,'[2]Coordinados SEN'!$B:$B,"-",0) -> 76.489.426-K | F77: LICÁN SPA | G77: =COUNTIFS($D$2:$D$1194,D77) -> 8 | H77: S/E MANTILHUE 110KV | I77: S/E MANTILHUE 110KV | J77: =_xlfn.XLOOKUP(I77,'[2]Barras CMg'!$E$2:$E$1527,'[2]Barras CMg'!$A$2:$A$1527,"------",0,1) -> MANTILHUE_____110 | K77: 2 | L77: 2025 | M77: Hidroeléctrica | N77: Minihidro de pasada | O77: Instalaciones de generación | P77: Los Ríos | Q77: Ranco | R77: Río Bueno | S77: Operativa | T77: 04-06-2011 | U77: 18 | V77: 17.955 | W77: =_xlfn.XLOOKUP(C77,#REF!,#REF!,"S/I",0) -> #REF! | X77: =_xlfn.XLOOKUP($D77,[2]Retiros_dinamica!$F:$F,[2]Retiros_dinamica!B:B,"S/I",0) -> 166347 | Y77: =_xlfn.XLOOKUP($D77,[2]Retiros_dinamica!$F:$F,[2]Retiros_dinamica!C:C,"S/I",0) -> 198978.01 | Z77: =_xlfn.XLOOKUP($D77,[2]Retiros_dinamica!$F:$F,[2]Retiros_dinamica!D:D,"S/I",0) -> 107362.25 | AA77: =_xlfn.XLOOKUP($D77,[2]Retiros_dinamica!$F:$F,[2]Retiros_dinamica!E:E,"S/I",0) -> 472687.27 | AB77: =_xlfn.XLOOKUP(C77,[2]CMg!$I$4:$I$106,[2]CMg!$M$4:$M$106,"----",0,1) -> ---- | AC77: =_xlfn.XLOOKUP(C77,[2]CMg!$A$4:$A$106,[2]CMg!$B$4:$B$106,"----",0,1) -> ---- | AD77: =_xlfn.XLOOKUP(C77,'[3]Promedio solar Cmg'!$A$4:$A$106,'[3]Promedio solar Cmg'!$B$4:$B$106,"----",0,1) -> ---- | AH77: =_xlfn.XLOOKUP($E77,'[2]Balance económico'!$C:$C,'[2]Balance económico'!$D:$D,"-",0) -> 7.9207069e+09 | AI77: =_xlfn.XLOOKUP($E77,'[2]Balance económico'!$C:$C,'[2]Balance económico'!$E:$E,"-",0) -> 8.0865776e+09 | AJ77: =_xlfn.XLOOKUP($E77,'[2]Balance económico'!$C:$C,'[2]Balance económico'!$F:$F,"-",0) -> 2.266958e+09 | AK77: =IF(AA77>0,"PPA","-") -> PPA | AL77: {=IFERROR((X77*[2]!Tabla2[Bloque A] + 'BD Centrales 2025'!Y66*[2]!Tabla2[Bloque B] + 'BD Centrales 2025'!Z66*[2]!Tabla2[Bloque C])*#REF!,"-")} -> - | AM77: =IFERROR(AH77+AL77,"-") -> - | AN77: =IFERROR((AH77+AI77+AJ77)/(SUMIFS($W$2:$W$1194,$E$2:$E$1194,E77)*1000*#REF!),0) -> 0
A78: 108 | B78: CE10G0292 | C78: HP PULLINQUE | D78: ENEL GREEN POWER CHILE S.A. | E78: =_xlfn.XLOOKUP(D78,'[2]Coordinados SEN'!$A:$A,'[2]Coordinados SEN'!$B:$B,"-",0) -> 76.412.562-2 | F78: ENEL GREEN POWER CHILE S.A. | G78: =COUNTIFS($D$2:$D$1194,D78) -> 39 | H78: S/E PULLINQUE 66KV | I78: S/E PULLINQUE 66KV | J78: =_xlfn.XLOOKUP(I78,'[2]Barras CMg'!$E$2:$E$1527,'[2]Barras CMg'!$A$2:$A$1527,"------",0,1) -> PULLINQUE_____066 | K78: 3 | L78: 2025 | M78: Hidroeléctrica | N78: Hidroeléctrica de pasada | O78: Instalaciones de generación | P78: Los Ríos | Q78: Valdivia | R78: Panguipulli | S78: Operativa | T78: 31-07-1962 | U78: 51.4 | V78: 51.1584 | W78: =_xlfn.XLOOKUP(C78,#REF!,#REF!,"S/I",0) -> #REF! | X78: =_xlfn.XLOOKUP($D78,[2]Retiros_dinamica!$F:$F,[2]Retiros_dinamica!B:B,"S/I",0) -> S/I | Y78: =_xlfn.XLOOKUP($D78,[2]Retiros_dinamica!$F:$F,[2]Retiros_dinamica!C:C,"S/I",0) -> S/I | Z78: =_xlfn.XLOOKUP($D78,[2]Retiros_dinamica!$F:$F,[2]Retiros_dinamica!D:D,"S/I",0) -> S/I | AA78: =_xlfn.XLOOKUP($D78,[2]Retiros_dinamica!$F:$F,[2]Retiros_dinamica!E:E,"S/I",0) -> S/I | AB78: =_xlfn.XLOOKUP(C78,[2]CMg!$I$4:$I$106,[2]CMg!$M$4:$M$106,"----",0,1) -> ---- | AC78: =_xlfn.XLOOKUP(C78,[2]CMg!$A$4:$A$106,[2]CMg!$B$4:$B$106,"----",0,1) -> ---- | AD78: =_xlfn.XLOOKUP(C78,'[3]Promedio solar Cmg'!$A$4:$A$106,'[3]Promedio solar Cmg'!$B$4:$B$106,"----",0,1) -> ---- | AH78: =_xlfn.XLOOKUP($E78,'[2]Balance económico'!$C:$C,'[2]Balance económico'!$D:$D,"-",0) -> 6.375328e+09 | AI78: =_xlfn.XLOOKUP($E78,'[2]Balance económico'!$C:$C,'[2]Balance económico'!$E:$E,"-",0) -> 4.8172067e+10 | AJ78: =_xlfn.XLOOKUP($E78,'[2]Balance económico'!$C:$C,'[2]Balance económico'!$F:$F,"-",0) -> 8.7975579e+08 | AK78: =IF(AA78>0,"PPA","-") -> PPA | AL78: {=IFERROR((X78*[2]!Tabla2[Bloque A] + 'BD Centrales 2025'!Y121*[2]!Tabla2[Bloque B] + 'BD Centrales 2025'!Z121*[2]!Tabla2[Bloque C])*#REF!,"-")} -> - | AM78: =IFERROR(AH78+AL78,"-") -> - | AN78: =IFERROR((AH78+AI78+AJ78)/(SUMIFS($W$2:$W$1194,$E$2:$E$1194,E78)*1000*#REF!),0) -> 0
A79: 109 | B79: CE11G0292 | C79: HP PILMAIQUEN | D79: ENEL GREEN POWER CHILE S.A. | E79: =_xlfn.XLOOKUP(D79,'[2]Coordinados SEN'!$A:$A,'[2]Coordinados SEN'!$B:$B,"-",0) -> 76.412.562-2 | F79: ENEL GREEN POWER CHILE S.A. | G79: =COUNTIFS($D$2:$D$1194,D79) -> 39 | H79: S/E CENTRAL PILMAIQUEN 66KV | I79: S/E CENTRAL PILMAIQUEN 66KV | J79: =_xlfn.XLOOKUP(I79,'[2]Barras CMg'!$E$2:$E$1527,'[2]Barras CMg'!$A$2:$A$1527,"------",0,1) -> PILMAIQUEN____066 | K79: 5 | L79: 2025 | M79: Hidroeléctrica | N79: Hidroeléctrica de pasada | O79: Instalaciones de generación | P79: Los Ríos | Q79: Ranco | R79: Río Bueno | S79: Operativa | T79: 31-07-1944 | U79: 40.8 | V79: 40.6776 | W79: =_xlfn.XLOOKUP(C79,#REF!,#REF!,"S/I",0) -> #REF! | X79: =_xlfn.XLOOKUP($D79,[2]Retiros_dinamica!$F:$F,[2]Retiros_dinamica!B:B,"S/I",0) -> S/I | Y79: =_xlfn.XLOOKUP($D79,[2]Retiros_dinamica!$F:$F,[2]Retiros_dinamica!C:C,"S/I",0) -> S/I | Z79: =_xlfn.XLOOKUP($D79,[2]Retiros_dinamica!$F:$F,[2]Retiros_dinamica!D:D,"S/I",0) -> S/I | AA79: =_xlfn.XLOOKUP($D79,[2]Retiros_dinamica!$F:$F,[2]Retiros_dinamica!E:E,"S/I",0) -> S/I | AB79: =_xlfn.XLOOKUP(C79,[2]CMg!$I$4:$I$106,[2]CMg!$M$4:$M$106,"----",0,1) -> ---- | AC79: =_xlfn.XLOOKUP(C79,[2]CMg!$A$4:$A$106,[2]CMg!$B$4:$B$106,"----",0,1) -> ---- | AD79: =_xlfn.XLOOKUP(C79,'[3]Promedio solar Cmg'!$A$4:$A$106,'[3]Promedio solar Cmg'!$B$4:$B$106,"----",0,1) -> ---- | AH79: =_xlfn.XLOOKUP($E79,'[2]Balance económico'!$C:$C,'[2]Balance económico'!$D:$D,"-",0) -> 6.375328e+09 | AI79: =_xlfn.XLOOKUP($E79,'[2]Balance económico'!$C:$C,'[2]Balance económico'!$E:$E,"-",0) -> 4.8172067e+10 | AJ79: =_xlfn.XLOOKUP($E79,'[2]Balance económico'!$C:$C,'[2]Balance económico'!$F:$F,"-",0) -> 8.7975579e+08 | AK79: =IF(AA79>0,"PPA","-") -> PPA | AL79: {=IFERROR((X79*[2]!Tabla2[Bloque A] + 'BD Centrales 2025'!Y101*[2]!Tabla2[Bloque B] + 'BD Centrales 2025'!Z101*[2]!Tabla2[Bloque C])*#REF!,"-")} -> - | AM79: =IFERROR(AH79+AL79,"-") -> - | AN79: =IFERROR((AH79+AI79+AJ79)/(SUMIFS($W$2:$W$1194,$E$2:$E$1194,E79)*1000*#REF!),0) -> 0
A80: 110 | B80: CE01G0039 | C80: TER CENIZAS | D80: IMELSA ENERGÍA SPA | E80: =_xlfn.XLOOKUP(D80,'[2]Coordinados SEN'!$A:$A,'[2]Coordinados SEN'!$B:$B,"-",0) -> 76.472.262-0 | F80: ELÉCTRICA CENIZAS S.A. | G80: =COUNTIFS($D$2:$D$1194,D80) -> 8 | H80: S/E CARDONES 110KV B1 | I80: S/E CARDONES 110KV | J80: =_xlfn.XLOOKUP(I80,'[2]Barras CMg'!$E$2:$E$1527,'[2]Barras CMg'!$A$2:$A$1527,"------",0,1) -> CARDONES______110 | K80: 1 | L80: 2025 | M80: Termoeléctrica | N80: Motor de combustión interna | O80: Instalaciones de generación | P80: Atacama | Q80: Copiapó | R80: Copiapó | S80: Operativa | T80: 31-07-2009 | U80: 15.2545 | V80: 14.0667 | W80: =_xlfn.XLOOKUP(C80,#REF!,#REF!,"S/I",0) -> #REF! | X80: =_xlfn.XLOOKUP($D80,[2]Retiros_dinamica!$F:$F,[2]Retiros_dinamica!B:B,"S/I",0) -> 241293.82 | Y80: =_xlfn.XLOOKUP($D80,[2]Retiros_dinamica!$F:$F,[2]Retiros_dinamica!C:C,"S/I",0) -> 329081.15 | Z80: =_xlfn.XLOOKUP($D80,[2]Retiros_dinamica!$F:$F,[2]Retiros_dinamica!D:D,"S/I",0) -> 128496.99 | AA80: =_xlfn.XLOOKUP($D80,[2]Retiros_dinamica!$F:$F,[2]Retiros_dinamica!E:E,"S/I",0) -> 698871.97 | AB80: =_xlfn.XLOOKUP(C80,[2]CMg!$I$4:$I$106,[2]CMg!$M$4:$M$106,"----",0,1) -> ---- | AH80: =_xlfn.XLOOKUP($E80,'[2]Balance económico'!$C:$C,'[2]Balance económico'!$D:$D,"-",0) -> -5.6087447e+09 | AI80: =_xlfn.XLOOKUP($E80,'[2]Balance económico'!$C:$C,'[2]Balance económico'!$E:$E,"-",0) -> -6.717898e+09 | AJ80: =_xlfn.XLOOKUP($E80,'[2]Balance económico'!$C:$C,'[2]Balance económico'!$F:$F,"-",0) -> 2.0395768e+09 | AK80: =IF(AA80>0,"PPA","-") -> PPA | AL80: {=IFERROR((X80*[2]!Tabla2[Bloque A] + 'BD Centrales 2025'!Y1006*[2]!Tabla2[Bloque B] + 'BD Centrales 2025'!Z1006*[2]!Tabla2[Bloque C])*#REF!,"-")} -> - | AM80: =IFERROR(AH80+AL80,"-") -> - | AN80: =IFERROR((AH80+AI80+AJ80)/(SUMIFS($W$2:$W$1194,$E$2:$E$1194,E80)*1000*#REF!),0) -> 0
A81: 111 | B81: CE01G0019 | C81: HP PUNTILLA | D81: ELÉCTRICA PUNTILLA S.A. | E81: =_xlfn.XLOOKUP(D81,'[2]Coordinados SEN'!$A:$A,'[2]Coordinados SEN'!$B:$B,"-",0) -> 96.817.230-1 | F81: ELÉCTRICA PUNTILLA S.A. | G81: =COUNTIFS($D$2:$D$1194,D81) -> 4 | H81: S/E PUENTE ALTO 110KV | I81: S/E PUENTE ALTO 110KV | J81: =_xlfn.XLOOKUP(I81,'[2]Barras CMg'!$E$2:$E$1527,'[2]Barras CMg'!$A$2:$A$1527,"------",0,1) -> P.ALTO________110 | K81: 3 | L81: 2025 | M81: Hidroeléctrica | N81: Hidroeléctrica de pasada | O81: Instalaciones de generación | P81: Metropolitana de Santiago | Q81: Cordillera | R81: Pirque | S81: Operativa | T81: 31-07-1926 | U81: 21.76 | V81: 21.7491 | W81: =_xlfn.XLOOKUP(C81,#REF!,#REF!,"S/I",0) -> #REF! | X81: =_xlfn.XLOOKUP($D81,[2]Retiros_dinamica!$F:$F,[2]Retiros_dinamica!B:B,"S/I",0) -> S/I | Y81: =_xlfn.XLOOKUP($D81,[2]Retiros_dinamica!$F:$F,[2]Retiros_dinamica!C:C,"S/I",0) -> S/I | Z81: =_xlfn.XLOOKUP($D81,[2]Retiros_dinamica!$F:$F,[2]Retiros_dinamica!D:D,"S/I",0) -> S/I | AA81: =_xlfn.XLOOKUP($D81,[2]Retiros_dinamica!$F:$F,[2]Retiros_dinamica!E:E,"S/I",0) -> S/I | AB81: =_xlfn.XLOOKUP(C81,[2]CMg!$I$4:$I$106,[2]CMg!$M$4:$M$106,"----",0,1) -> ---- | AC81: =_xlfn.XLOOKUP(C81,[2]CMg!$A$4:$A$106,[2]CMg!$B$4:$B$106,"----",0,1) -> ---- | AD81: =_xlfn.XLOOKUP(C81,'[3]Promedio solar Cmg'!$A$4:$A$106,'[3]Promedio solar Cmg'!$B$4:$B$106,"----",0,1) -> ---- | AH81: =_xlfn.XLOOKUP($E81,'[2]Balance económico'!$C:$C,'[2]Balance económico'!$D:$D,"-",0) -> 7.8687788e+09 | AI81: =_xlfn.XLOOKUP($E81,'[2]Balance económico'!$C:$C,'[2]Balance económico'!$E:$E,"-",0) -> 9.1926298e+08 | AJ81: =_xlfn.XLOOKUP($E81,'[2]Balance económico'!$C:$C,'[2]Balance económico'!$F:$F,"-",0) -> ---- | AK81: =IF(AA81>0,"PPA","-") -> PPA | AL81: {=IFERROR((X81*[2]!Tabla2[Bloque A] + 'BD Centrales 2025'!Y286*[2]!Tabla2[Bloque B] + 'BD Centrales 2025'!Z286*[2]!Tabla2[Bloque C])*#REF!,"-")} -> - | AM81: =IFERROR(AH81+AL81,"-") -> - | AN81: =IFERROR((AH81+AI81+AJ81)/(SUMIFS($W$2:$W$1194,$E$2:$E$1194,E81)*1000*#REF!),0) -> 0
A82: 112 | B82: CE01G0049 | C82: TER NUEVA VENTANAS | D82: EMPRESA ELÉCTRICA VENTANAS SPA | E82: =_xlfn.XLOOKUP(D82,'[2]Coordinados SEN'!$A:$A,'[2]Coordinados SEN'!$B:$B,"-",0) -> 96.814.370-0 | F82: EMPRESA ELÉCTRICA VENTANAS SPA | G82: =COUNTIFS($D$2:$D$1194,D82) -> 2 | H82: BA S/E CENTRAL NUEVA VENTANAS 220kV BP1 | I82: S/E VENTANAS 220KV | J82: =_xlfn.XLOOKUP(I82,'[2]Barras CMg'!$E$2:$E$1527,'[2]Barras CMg'!$A$2:$A$1527,"------",0,1) -> VENTANAS______220 | K82: 1 | L82: 2025 | M82: Termoeléctrica | N82: Termoeléctrica de turbina a vapor | O82: Instalaciones de generación | P82: Valparaíso | Q82: Valparaíso | R82: Puchuncaví | S82: Operativa | T82: 11-02-2010 | U82: 267.096 | V82: 245.165 | W82: =_xlfn.XLOOKUP(C82,#REF!,#REF!,"S/I",0) -> #REF! | X82: =_xlfn.XLOOKUP($D82,[2]Retiros_dinamica!$F:$F,[2]Retiros_dinamica!B:B,"S/I",0) -> S/I | Y82: =_xlfn.XLOOKUP($D82,[2]Retiros_dinamica!$F:$F,[2]Retiros_dinamica!C:C,"S/I",0) -> S/I | Z82: =_xlfn.XLOOKUP($D82,[2]Retiros_dinamica!$F:$F,[2]Retiros_dinamica!D:D,"S/I",0) -> S/I | AA82: =_xlfn.XLOOKUP($D82,[2]Retiros_dinamica!$F:$F,[2]Retiros_dinamica!E:E,"S/I",0) -> S/I | AB82: =_xlfn.XLOOKUP(C82,[2]CMg!$I$4:$I$106,[2]CMg!$M$4:$M$106,"----",0,1) -> ---- | AH82: =_xlfn.XLOOKUP($E82,'[2]Balance económico'!$C:$C,'[2]Balance económico'!$D:$D,"-",0) -> 4.3974298e+10 | AI82: =_xlfn.XLOOKUP($E82,'[2]Balance económico'!$C:$C,'[2]Balance económico'!$E:$E,"-",0) -> 2.6120853e+10 | AJ82: =_xlfn.XLOOKUP($E82,'[2]Balance económico'!$C:$C,'[2]Balance económico'!$F:$F,"-",0) -> ---- | AK82: =IF(AA82>0,"PPA","-") -> PPA | AL82: {=IFERROR((X82*[2]!Tabla2[Bloque A] + 'BD Centrales 2025'!Y1155*[2]!Tabla2[Bloque B] + 'BD Centrales 2025'!Z1155*[2]!Tabla2[Bloque C])*#REF!,"-")} -> - | AM82: =IFERROR(AH82+AL82,"-") -> - | AN82: =IFERROR((AH82+AI82+AJ82)/(SUMIFS($W$2:$W$1194,$E$2:$E$1194,E82)*1000*#REF!),0) -> 0
A83: 113 | B83: CE01G0061 | C83: TER EMELDA | D83: EMPRESA ELÉCTRICA DIEGO DE ALMAGRO SPA | E83: =_xlfn.XLOOKUP(D83,'[2]Coordinados SEN'!$A:$A,'[2]Coordinados SEN'!$B:$B,"-",0) -> 76.004.337-0 | F83: EMPRESA ELÉCTRICA DIEGO DE ALMAGRO SPA | G83: =COUNTIFS($D$2:$D$1194,D83) -> 1 | H83: ID 1777 BA S/E CENTRAL EMELDA 110KV BP1 | I83: S/E DIEGO DE ALMAGRO 110KV | J83: =_xlfn.XLOOKUP(I83,'[2]Barras CMg'!$E$2:$E$1527,'[2]Barras CMg'!$A$2:$A$1527,"------",0,1) -> D.ALMAGRO_____110 | K83: 2 | L83: 2025 | M83: Termoeléctrica | N83: Termoeléctrica de turbina a gas | O83: Instalaciones de generación | P83: Atacama | Q83: Chañaral | R83: Diego de Almagro | S83: Operativa | T83: 25-06-2010 | U83: 73.09 | V83: 71.51 | W83: =_xlfn.XLOOKUP(C83,#REF!,#REF!,"S/I",0) -> #REF! | X83: =_xlfn.XLOOKUP($D83,[2]Retiros_dinamica!$F:$F,[2]Retiros_dinamica!B:B,"S/I",0) -> S/I | Y83: =_xlfn.XLOOKUP($D83,[2]Retiros_dinamica!$F:$F,[2]Retiros_dinamica!C:C,"S/I",0) -> S/I | Z83: =_xlfn.XLOOKUP($D83,[2]Retiros_dinamica!$F:$F,[2]Retiros_dinamica!D:D,"S/I",0) -> S/I | AA83: =_xlfn.XLOOKUP($D83,[2]Retiros_dinamica!$F:$F,[2]Retiros_dinamica!E:E,"S/I",0) -> S/I | AB83: =_xlfn.XLOOKUP(C83,[2]CMg!$I$4:$I$106,[2]CMg!$M$4:$M$106,"----",0,1) -> ---- | AH83: =_xlfn.XLOOKUP($E83,'[2]Balance económico'!$C:$C,'[2]Balance económico'!$D:$D,"-",0) -> 35753469 | AI83: =_xlfn.XLOOKUP($E83,'[2]Balance económico'!$C:$C,'[2]Balance económico'!$E:$E,"-",0) -> 4.4215528e+09 | AJ83: =_xlfn.XLOOKUP($E83,'[2]Balance económico'!$C:$C,'[2]Balance económico'!$F:$F,"-",0) -> ---- | AK83: =IF(AA83>0,"PPA","-") -> PPA | AL83: {=IFERROR((X83*[2]!Tabla2[Bloque A] + 'BD Centrales 2025'!Y1103*[2]!Tabla2[Bloque B] + 'BD Centrales 2025'!Z1103*[2]!Tabla2[Bloque C])*#REF!,"-")} -> - | AM83: =IFERROR(AH83+AL83,"-") -> - | AN83: =IFERROR((AH83+AI83+AJ83)/(SUMIFS($W$2:$W$1194,$E$2:$E$1194,E83)*1000*#REF!),0) -> 0
A84: 114 | B84: CE10G1040 | C84: HP CARENA | D84: NUEVA CARENA SPA | E84: =_xlfn.XLOOKUP(D84,'[2]Coordinados SEN'!$A:$A,'[2]Coordinados SEN'!$B:$B,"-",0) -> 77.142.141-5 | F84: NUEVA CARENA SPA | G84: =COUNTIFS($D$2:$D$1194,D84) -> 1 | H84: S/E CARENA 44KV | I84: S/E CARENA 44KV | J84: =_xlfn.XLOOKUP(I84,'[2]Barras CMg'!$E$2:$E$1527,'[2]Barras CMg'!$A$2:$A$1527,"------",0,1) -> CARENA________044 | K84: 4 | L84: 2025 | M84: Hidroeléctrica | N84: Minihidro de pasada | O84: Instalaciones de generación | P84: Metropolitana de Santiago | Q84: Melipilla | R84: Curacaví | S84: Operativa | T84: 31-07-1943 | U84: 10 | V84: 8.4 | W84: =_xlfn.XLOOKUP(C84,#REF!,#REF!,"S/I",0) -> #REF! | X84: =_xlfn.XLOOKUP($D84,[2]Retiros_dinamica!$F:$F,[2]Retiros_dinamica!B:B,"S/I",0) -> S/I | Y84: =_xlfn.XLOOKUP($D84,[2]Retiros_dinamica!$F:$F,[2]Retiros_dinamica!C:C,"S/I",0) -> S/I | Z84: =_xlfn.XLOOKUP($D84,[2]Retiros_dinamica!$F:$F,[2]Retiros_dinamica!D:D,"S/I",0) -> S/I | AA84: =_xlfn.XLOOKUP($D84,[2]Retiros_dinamica!$F:$F,[2]Retiros_dinamica!E:E,"S/I",0) -> S/I | AB84: =_xlfn.XLOOKUP(C84,[2]CMg!$I$4:$I$106,[2]CMg!$M$4:$M$106,"----",0,1) -> ---- | AC84: =_xlfn.XLOOKUP(C84,[2]CMg!$A$4:$A$106,[2]CMg!$B$4:$B$106,"----",0,1) -> ---- | AD84: =_xlfn.XLOOKUP(C84,'[3]Promedio solar Cmg'!$A$4:$A$106,'[3]Promedio solar Cmg'!$B$4:$B$106,"----",0,1) -> ---- | AH84: =_xlfn.XLOOKUP($E84,'[2]Balance económico'!$C:$C,'[2]Balance económico'!$D:$D,"-",0) -> 3.1281892e+09 | AI84: =_xlfn.XLOOKUP($E84,'[2]Balance económico'!$C:$C,'[2]Balance económico'!$E:$E,"-",0) -> 3.072773e+08 | AJ84: =_xlfn.XLOOKUP($E84,'[2]Balance económico'!$C:$C,'[2]Balance económico'!$F:$F,"-",0) -> ---- | AK84: =IF(AA84>0,"PPA","-") -> PPA | AL84: {=IFERROR((X84*[2]!Tabla2[Bloque A] + 'BD Centrales 2025'!Y27*[2]!Tabla2[Bloque B] + 'BD Centrales 2025'!Z27*[2]!Tabla2[Bloque C])*#REF!,"-")} -> - | AM84: =IFERROR(AH84+AL84,"-") -> - | AN84: =IFERROR((AH84+AI84+AJ84)/(SUMIFS($W$2:$W$1194,$E$2:$E$1194,E84)*1000*#REF!),0) -> 0
A85: 115 | B85: CE01G0021 | C85: HP ABANICO | D85: ENEL GENERACIÓN CHILE S.A. | E85: =_xlfn.XLOOKUP(D85,'[2]Coordinados SEN'!$A:$A,'[2]Coordinados SEN'!$B:$B,"-",0) -> 91.081.000-6 | F85: ENEL GENERACIÓN CHILE S.A. | G85: =COUNTIFS($D$2:$D$1194,D85) -> 21 | H85: S/E ABANICO 154KV | I85: S/E CHARRUA 154KV | J85: =_xlfn.XLOOKUP(I85,'[2]Barras CMg'!$E$2:$E$1527,'[2]Barras CMg'!$A$2:$A$1527,"------",0,1) -> CHARRUA_______154 | K85: 4 | L85: 2025 | M85: Hidroeléctrica | N85: Hidroeléctrica de pasada | O85: Instalaciones de generación | P85: Biobío | Q85: Biobío | R85: Antuco | S85: Operativa | T85: 31-07-1948 | U85: 100 | V85: 90.3856 | W85: =_xlfn.XLOOKUP(C85,#REF!,#REF!,"S/I",0) -> #REF! | X85: =_xlfn.XLOOKUP($D85,[2]Retiros_dinamica!$F:$F,[2]Retiros_dinamica!B:B,"S/I",0) -> 7639445.9 | Y85: =_xlfn.XLOOKUP($D85,[2]Retiros_dinamica!$F:$F,[2]Retiros_dinamica!C:C,"S/I",0) -> 9104617.6 | Z85: =_xlfn.XLOOKUP($D85,[2]Retiros_dinamica!$F:$F,[2]Retiros_dinamica!D:D,"S/I",0) -> 4255877.2 | AA85: =_xlfn.XLOOKUP($D85,[2]Retiros_dinamica!$F:$F,[2]Retiros_dinamica!E:E,"S/I",0) -> 20999941 | AB85: =_xlfn.XLOOKUP(C85,[2]CMg!$I$4:$I$106,[2]CMg!$M$4:$M$106,"----",0,1) -> ---- | AC85: =_xlfn.XLOOKUP(C85,[2]CMg!$A$4:$A$106,[2]CMg!$B$4:$B$106,"----",0,1) -> ---- | AD85: =_xlfn.XLOOKUP(C85,'[3]Promedio solar Cmg'!$A$4:$A$106,'[3]Promedio solar Cmg'!$B$4:$B$106,"----",0,1) -> ---- | AH85: =_xlfn.XLOOKUP($E85,'[2]Balance económico'!$C:$C,'[2]Balance económico'!$D:$D,"-",0) -> -5.15558e+11 | AI85: =_xlfn.XLOOKUP($E85,'[2]Balance económico'!$C:$C,'[2]Balance económico'!$E:$E,"-",0) -> -1.8754195e+11 | AJ85: =_xlfn.XLOOKUP($E85,'[2]Balance económico'!$C:$C,'[2]Balance económico'!$F:$F,"-",0) -> 7.2834825e+10 | AK85: =IF(AA85>0,"PPA","-") -> PPA | AL85: {=IFERROR((X85*[2]!Tabla2[Bloque A] + 'BD Centrales 2025'!Y17*[2]!Tabla2[Bloque B] + 'BD Centrales 2025'!Z17*[2]!Tabla2[Bloque C])*#REF!,"-")} -> - | AM85: =IFERROR(AH85+AL85,"-") -> - | AN85: =IFERROR((AH85+AI85+AJ85)/(SUMIFS($W$2:$W$1194,$E$2:$E$1194,E85)*1000*#REF!),0) -> 0
A86: 116 | B86: CE02G0021 | C86: HE ANTUCO | D86: ENEL GENERACIÓN CHILE S.A. | E86: =_xlfn.XLOOKUP(D86,'[2]Coordinados SEN'!$A:$A,'[2]Coordinados SEN'!$B:$B,"-",0) -> 91.081.000-6 | F86: ENEL GENERACIÓN CHILE S.A. | G86: =COUNTIFS($D$2:$D$1194,D86) -> 21 | H86: S/E ANTUCO 220KV | I86: S/E ANTUCO (TRANSELEC) 220KV | J86: =_xlfn.XLOOKUP(I86,'[2]Barras CMg'!$E$2:$E$1527,'[2]Barras CMg'!$A$2:$A$1527,"------",0,1) -> ANTUCO________220 | K86: 2 | L86: 2025 | M86: Hidroeléctrica | N86: Hidroeléctrica de embalse | O86: Instalaciones de generación | P86: Biobío | Q86: Biobío | R86: Tucapel | S86: Operativa | T86: 31-07-1981 | U86: 329.125 | V86: 326.628 | W86: =_xlfn.XLOOKUP(C86,#REF!,#REF!,"S/I",0) -> #REF! | X86: =_xlfn.XLOOKUP($D86,[2]Retiros_dinamica!$F:$F,[2]Retiros_dinamica!B:B,"S/I",0) -> 7639445.9 | Y86: =_xlfn.XLOOKUP($D86,[2]Retiros_dinamica!$F:$F,[2]Retiros_dinamica!C:C,"S/I",0) -> 9104617.6 | Z86: =_xlfn.XLOOKUP($D86,[2]Retiros_dinamica!$F:$F,[2]Retiros_dinamica!D:D,"S/I",0) -> 4255877.2 | AA86: =_xlfn.XLOOKUP($D86,[2]Retiros_dinamica!$F:$F,[2]Retiros_dinamica!E:E,"S/I",0) -> 20999941 | AB86: =_xlfn.XLOOKUP(C86,[2]CMg!$I$4:$I$106,[2]CMg!$M$4:$M$106,"----",0,1) -> ---- | AC86: =_xlfn.XLOOKUP(C86,[2]CMg!$A$4:$A$106,[2]CMg!$B$4:$B$106,"----",0,1) -> ---- | AD86: =_xlfn.XLOOKUP(C86,'[3]Promedio solar Cmg'!$A$4:$A$106,'[3]Promedio solar Cmg'!$B$4:$B$106,"----",0,1) -> ---- | AH86: =_xlfn.XLOOKUP($E86,'[2]Balance económico'!$C:$C,'[2]Balance económico'!$D:$D,"-",0) -> -5.15558e+11 | AI86: =_xlfn.XLOOKUP($E86,'[2]Balance económico'!$C:$C,'[2]Balance económico'!$E:$E,"-",0) -> -1.8754195e+11 | AJ86: =_xlfn.XLOOKUP($E86,'[2]Balance económico'!$C:$C,'[2]Balance económico'!$F:$F,"-",0) -> 7.2834825e+10 | AK86: =IF(AA86>0,"PPA","-") -> PPA | AL86: {=IFERROR((X86*[2]!Tabla2[Bloque A] + 'BD Centrales 2025'!Y5*[2]!Tabla2[Bloque B] + 'BD Centrales 2025'!Z5*[2]!Tabla2[Bloque C])*#REF!,"-")} -> - | AM86: =IFERROR(AH86+AL86,"-") -> - | AN86: =IFERROR((AH86+AI86+AJ86)/(SUMIFS($W$2:$W$1194,$E$2:$E$1194,E86)*1000*#REF!),0) -> 0
A87: 118 | B87: CE20G0021 | C87: PE CANELA | D87: ENEL GENERACIÓN CHILE S.A. | E87: =_xlfn.XLOOKUP(D87,'[2]Coordinados SEN'!$A:$A,'[2]Coordinados SEN'!$B:$B,"-",0) -> 91.081.000-6 | F87: ENEL GENERACIÓN CHILE S.A. | G87: =COUNTIFS($D$2:$D$1194,D87) -> 21 | H87: S/E LAS PALMAS 220KV BA-B | I87: S/E LAS PALMAS 220KV | J87: =_xlfn.XLOOKUP(I87,'[2]Barras CMg'!$E$2:$E$1527,'[2]Barras CMg'!$A$2:$A$1527,"------",0,1) -> L.PALMAS______220 | K87: 11 | L87: 2025 | M87: Eólica | N87: Parque eólico | O87: Instalaciones de generación | P87: Coquimbo | Q87: Choapa | R87: Canela | S87: Operativa | T87: 27-12-2007 | U87: 18.15 | V87: 17.9685 | W87: =_xlfn.XLOOKUP(C87,#REF!,#REF!,"S/I",0) -> #REF! | X87: =_xlfn.XLOOKUP($D87,[2]Retiros_dinamica!$F:$F,[2]Retiros_dinamica!B:B,"S/I",0) -> 7639445.9 | Y87: =_xlfn.XLOOKUP($D87,[2]Retiros_dinamica!$F:$F,[2]Retiros_dinamica!C:C,"S/I",0) -> 9104617.6 | Z87: =_xlfn.XLOOKUP($D87,[2]Retiros_dinamica!$F:$F,[2]Retiros_dinamica!D:D,"S/I",0) -> 4255877.2 | AA87: =_xlfn.XLOOKUP($D87,[2]Retiros_dinamica!$F:$F,[2]Retiros_dinamica!E:E,"S/I",0) -> 20999941 | AB87: =_xlfn.XLOOKUP(C87,[2]CMg!$I$4:$I$106,[2]CMg!$M$4:$M$106,"----",0,1) -> ---- | AC87: =_xlfn.XLOOKUP(C87,[2]CMg!$A$4:$A$106,[2]CMg!$B$4:$B$106,"----",0,1) -> ---- | AD87: =_xlfn.XLOOKUP(C87,'[3]Promedio solar Cmg'!$A$4:$A$106,'[3]Promedio solar Cmg'!$B$4:$B$106,"----",0,1) -> ---- | AH87: =_xlfn.XLOOKUP($E87,'[2]Balance económico'!$C:$C,'[2]Balance económico'!$D:$D,"-",0) -> -5.15558e+11 | AI87: =_xlfn.XLOOKUP($E87,'[2]Balance económico'!$C:$C,'[2]Balance económico'!$E:$E,"-",0) -> -1.8754195e+11 | AJ87: =_xlfn.XLOOKUP($E87,'[2]Balance económico'!$C:$C,'[2]Balance económico'!$F:$F,"-",0) -> 7.2834825e+10 | AK87: =IF(AA87>0,"PPA","-") -> PPA | AL87: {=IFERROR((X87*[2]!Tabla2[Bloque A] + 'BD Centrales 2025'!Y608*[2]!Tabla2[Bloque B] + 'BD Centrales 2025'!Z608*[2]!Tabla2[Bloque C])*#REF!,"-")} -> - | AM87: =IFERROR(AH87+AL87,"-") -> - | AN87: =IFERROR((AH87+AI87+AJ87)/(SUMIFS($W$2:$W$1194,$E$2:$E$1194,E87)*1000*#REF!),0) -> 0
A88: 119 | B88: CE04G0021 | C88: HE CIPRESES | D88: ENEL GENERACIÓN CHILE S.A. | E88: =_xlfn.XLOOKUP(D88,'[2]Coordinados SEN'!$A:$A,'[2]Coordinados SEN'!$B:$B,"-",0) -> 91.081.000-6 | F88: ENEL GENERACIÓN CHILE S.A. | G88: =COUNTIFS($D$2:$D$1194,D88) -> 21 | H88: S/E CIPRESES 154KV B1 | I88: S/E CENTRAL CIPRESES 154KV | J88: =_xlfn.XLOOKUP(I88,'[2]Barras CMg'!$E$2:$E$1527,'[2]Barras CMg'!$A$2:$A$1527,"------",0,1) -> CIPRESES______154 | K88: 3 | L88: 2025 | M88: Hidroeléctrica | N88: Hidroeléctrica de embalse | O88: Instalaciones de generación | P88: Maule | Q88: Talca | R88: San Clemente | S88: Operativa | T88: 31-07-1955 | U88: 97.9807 | V88: 96.6415 | W88: =_xlfn.XLOOKUP(C88,#REF!,#REF!,"S/I",0) -> #REF! | X88: =_xlfn.XLOOKUP($D88,[2]Retiros_dinamica!$F:$F,[2]Retiros_dinamica!B:B,"S/I",0) -> 7639445.9 | Y88: =_xlfn.XLOOKUP($D88,[2]Retiros_dinamica!$F:$F,[2]Retiros_dinamica!C:C,"S/I",0) -> 9104617.6 | Z88: =_xlfn.XLOOKUP($D88,[2]Retiros_dinamica!$F:$F,[2]Retiros_dinamica!D:D,"S/I",0) -> 4255877.2 | AA88: =_xlfn.XLOOKUP($D88,[2]Retiros_dinamica!$F:$F,[2]Retiros_dinamica!E:E,"S/I",0) -> 20999941 | AB88: =_xlfn.XLOOKUP(C88,[2]CMg!$I$4:$I$106,[2]CMg!$M$4:$M$106,"----",0,1) -> ---- | AC88: =_xlfn.XLOOKUP(C88,[2]CMg!$A$4:$A$106,[2]CMg!$B$4:$B$106,"----",0,1) -> ---- | AD88: =_xlfn.XLOOKUP(C88,'[3]Promedio solar Cmg'!$A$4:$A$106,'[3]Promedio solar Cmg'!$B$4:$B$106,"----",0,1) -> ---- | AH88: =_xlfn.XLOOKUP($E88,'[2]Balance económico'!$C:$C,'[2]Balance económico'!$D:$D,"-",0) -> -5.15558e+11 | AI88: =_xlfn.XLOOKUP($E88,'[2]Balance económico'!$C:$C,'[2]Balance económico'!$E:$E,"-",0) -> -1.8754195e+11 | AJ88: =_xlfn.XLOOKUP($E88,'[2]Balance económico'!$C:$C,'[2]Balance económico'!$F:$F,"-",0) -> 7.2834825e+10 | AK88: =IF(AA88>0,"PPA","-") -> PPA | AL88: {=IFERROR((X88*[2]!Tabla2[Bloque A] + 'BD Centrales 2025'!Y7*[2]!Tabla2[Bloque B] + 'BD Centrales 2025'!Z7*[2]!Tabla2[Bloque C])*#REF!,"-")} -> - | AM88: =IFERROR(AH88+AL88,"-") -> - | AN88: =IFERROR((AH88+AI88+AJ88)/(SUMIFS($W$2:$W$1194,$E$2:$E$1194,E88)*1000*#REF!),0) -> 0
A89: 120 | B89: CE05G0477 | C89: TER DIEGO DE ALMAGRO | D89: ELÉCTRICA MOKA SPA | E89: =_xlfn.XLOOKUP(D89,'[2]Coordinados SEN'!$A:$A,'[2]Coordinados SEN'!$B:$B,"-",0) -> 77.513.675-8 | F89: ELÉCTRICA MOKA SPA | G89: =COUNTIFS($D$2:$D$1194,D89) -> 1 | H89: S/E DIEGO DE ALMAGRO 110 KV B2 | I89: S/E DIEGO DE ALMAGRO 110KV | J89: =_xlfn.XLOOKUP(I89,'[2]Barras CMg'!$E$2:$E$1527,'[2]Barras CMg'!$A$2:$A$1527,"------",0,1) -> D.ALMAGRO_____110 | K89: 1 | L89: 2025 | M89: Termoeléctrica | N89: Termoeléctrica de turbina a gas | O89: Instalaciones de generación | P89: Atacama | Q89: Chañaral | R89: Diego de Almagro | S89: Operativa | T89: 31-07-1981 | U89: 23.8 | V89: 23.6691 | W89: =_xlfn.XLOOKUP(C89,#REF!,#REF!,"S/I",0) -> #REF! | X89: =_xlfn.XLOOKUP($D89,[2]Retiros_dinamica!$F:$F,[2]Retiros_dinamica!B:B,"S/I",0) -> S/I | Y89: =_xlfn.XLOOKUP($D89,[2]Retiros_dinamica!$F:$F,[2]Retiros_dinamica!C:C,"S/I",0) -> S/I | Z89: =_xlfn.XLOOKUP($D89,[2]Retiros_dinamica!$F:$F,[2]Retiros_dinamica!D:D,"S/I",0) -> S/I | AA89: =_xlfn.XLOOKUP($D89,[2]Retiros_dinamica!$F:$F,[2]Retiros_dinamica!E:E,"S/I",0) -> S/I | AB89: =_xlfn.XLOOKUP(C89,[2]CMg!$I$4:$I$106,[2]CMg!$M$4:$M$106,"----",0,1) -> ---- | AH89: =_xlfn.XLOOKUP($E89,'[2]Balance económico'!$C:$C,'[2]Balance económico'!$D:$D,"-",0) -> 1.183727e+09 | AI89: =_xlfn.XLOOKUP($E89,'[2]Balance económico'!$C:$C,'[2]Balance económico'!$E:$E,"-",0) -> 1.4799879e+09 | AJ89: =_xlfn.XLOOKUP($E89,'[2]Balance económico'!$C:$C,'[2]Balance económico'!$F:$F,"-",0) -> ---- | AK89: =IF(AA89>0,"PPA","-") -> PPA | AL89: {=IFERROR((X89*[2]!Tabla2[Bloque A] + 'BD Centrales 2025'!Y1084*[2]!Tabla2[Bloque B] + 'BD Centrales 2025'!Z1084*[2]!Tabla2[Bloque C])*#REF!,"-")} -> - | AM89: =IFERROR(AH89+AL89,"-") -> - | AN89: =IFERROR((AH89+AI89+AJ89)/(SUMIFS($W$2:$W$1194,$E$2:$E$1194,E89)*1000*#REF!),0) -> 0
A90: 121 | B90: CE07G0021 | C90: HE EL TORO | D90: ENEL GENERACIÓN CHILE S.A. | E90: =_xlfn.XLOOKUP(D90,'[2]Coordinados SEN'!$A:$A,'[2]Coordinados SEN'!$B:$B,"-",0) -> 91.081.000-6 | F90: ENEL GENERACIÓN CHILE S.A. | G90: =COUNTIFS($D$2:$D$1194,D90) -> 21 | H90: S/E CENTRAL EL TORO 220KV B1 | I90: S/E CENTRAL EL TORO 220KV | J90: =_xlfn.XLOOKUP(I90,'[2]Barras CMg'!$E$2:$E$1527,'[2]Barras CMg'!$A$2:$A$1527,"------",0,1) -> EL_TORO_______220 | K90: 4 | L90: 2025 | M90: Hidroeléctrica | N90: Hidroeléctrica de embalse | O90: Instalaciones de generación | P90: Biobío | Q90: Biobío | R90: Antuco | S90: Operativa | T90: 31-07-1973 | U90: 443.8897 | V90: 437.2715 | W90: =_xlfn.XLOOKUP(C90,#REF!,#REF!,"S/I",0) -> #REF! | X90: =_xlfn.XLOOKUP($D90,[2]Retiros_dinamica!$F:$F,[2]Retiros_dinamica!B:B,"S/I",0) -> 7639445.9 | Y90: =_xlfn.XLOOKUP($D90,[2]Retiros_dinamica!$F:$F,[2]Retiros_dinamica!C:C,"S/I",0) -> 9104617.6 | Z90: =_xlfn.XLOOKUP($D90,[2]Retiros_dinamica!$F:$F,[2]Retiros_dinamica!D:D,"S/I",0) -> 4255877.2 | AA90: =_xlfn.XLOOKUP($D90,[2]Retiros_dinamica!$F:$F,[2]Retiros_dinamica!E:E,"S/I",0) -> 20999941 | AB90: =_xlfn.XLOOKUP(C90,[2]CMg!$I$4:$I$106,[2]CMg!$M$4:$M$106,"----",0,1) -> ---- | AC90: =_xlfn.XLOOKUP(C90,[2]CMg!$A$4:$A$106,[2]CMg!$B$4:$B$106,"----",0,1) -> ---- | AD90: =_xlfn.XLOOKUP(C90,'[3]Promedio solar Cmg'!$A$4:$A$106,'[3]Promedio solar Cmg'!$B$4:$B$106,"----",0,1) -> ---- | AH90: =_xlfn.XLOOKUP($E90,'[2]Balance económico'!$C:$C,'[2]Balance económico'!$D:$D,"-",0) -> -5.15558e+11 | AI90: =_xlfn.XLOOKUP($E90,'[2]Balance económico'!$C:$C,'[2]Balance económico'!$E:$E,"-",0) -> -1.8754195e+11 | AJ90: =_xlfn.XLOOKUP($E90,'[2]Balance económico'!$C:$C,'[2]Balance económico'!$F:$F,"-",0) -> 7.2834825e+10 | AK90: =IF(AA90>0,"PPA","-") -> PPA | AL90: {=IFERROR((X90*[2]!Tabla2[Bloque A] + 'BD Centrales 2025'!Y10*[2]!Tabla2[Bloque B] + 'BD Centrales 2025'!Z10*[2]!Tabla2[Bloque C])*#REF!,"-")} -> - | AM90: =IFERROR(AH90+AL90,"-") -> - | AN90: =IFERROR((AH90+AI90+AJ90)/(SUMIFS($W$2:$W$1194,$E$2:$E$1194,E90)*1000*#REF!),0) -> 0
A91: 122 | B91: CE08G0011 | C91: TER HUASCO | D91: GUACOLDA ENERGÍA SPA | E91: =_xlfn.XLOOKUP(D91,'[2]Coordinados SEN'!$A:$A,'[2]Coordinados SEN'!$B:$B,"-",0) -> 76.418.918-3 | F91: GUACOLDA ENERGÍA SPA | G91: =COUNTIFS($D$2:$D$1194,D91) -> 2 | H91: S/E HUASCO 110KV | I91: S/E HUASCO 110KV | J91: =_xlfn.XLOOKUP(I91,'[2]Barras CMg'!$E$2:$E$1527,'[2]Barras CMg'!$A$2:$A$1527,"------",0,1) -> HUASCO________110 | K91: 3 | L91: 2025 | M91: Termoeléctrica | N91: Termoeléctrica de turbina a gas | O91: Instalaciones de generación | P91: Atacama | Q91: Huasco | R91: Huasco | S91: Operativa | T91: 31-07-1977 | U91: 58 | V91: 57.681 | W91: =_xlfn.XLOOKUP(C91,#REF!,#REF!,"S/I",0) -> #REF! | X91: =_xlfn.XLOOKUP($D91,[2]Retiros_dinamica!$F:$F,[2]Retiros_dinamica!B:B,"S/I",0) -> 672174.52 | Y91: =_xlfn.XLOOKUP($D91,[2]Retiros_dinamica!$F:$F,[2]Retiros_dinamica!C:C,"S/I",0) -> 501623.19 | Z91: =_xlfn.XLOOKUP($D91,[2]Retiros_dinamica!$F:$F,[2]Retiros_dinamica!D:D,"S/I",0) -> 348337.48 | AA91: =_xlfn.XLOOKUP($D91,[2]Retiros_dinamica!$F:$F,[2]Retiros_dinamica!E:E,"S/I",0) -> 1522135.2 | AB91: =_xlfn.XLOOKUP(C91,[2]CMg!$I$4:$I$106,[2]CMg!$M$4:$M$106,"----",0,1) -> ---- | AH91: =_xlfn.XLOOKUP($E91,'[2]Balance económico'!$C:$C,'[2]Balance económico'!$D:$D,"-",0) -> 1.863808e+11 | AI91: =_xlfn.XLOOKUP($E91,'[2]Balance económico'!$C:$C,'[2]Balance económico'!$E:$E,"-",0) -> 1.4569815e+10 | AJ91: =_xlfn.XLOOKUP($E91,'[2]Balance económico'!$C:$C,'[2]Balance económico'!$F:$F,"-",0) -> 4.3603682e+09 | AK91: =IF(AA91>0,"PPA","-") -> PPA | AL91: {=IFERROR((X91*[2]!Tabla2[Bloque A] + 'BD Centrales 2025'!Y1122*[2]!Tabla2[Bloque B] + 'BD Centrales 2025'!Z1122*[2]!Tabla2[Bloque C])*#REF!,"-")} -> - | AM91: =IFERROR(AH91+AL91,"-") -> - | AN91: =IFERROR((AH91+AI91+AJ91)/(SUMIFS($W$2:$W$1194,$E$2:$E$1194,E91)*1000*#REF!),0) -> 0
A92: 123 | B92: CE09G0021 | C92: HP ISLA | D92: ENEL GENERACIÓN CHILE S.A. | E92: =_xlfn.XLOOKUP(D92,'[2]Coordinados SEN'!$A:$A,'[2]Coordinados SEN'!$B:$B,"-",0) -> 91.081.000-6 | F92: ENEL GENERACIÓN CHILE S.A. | G92: =COUNTIFS($D$2:$D$1194,D92) -> 21 | H92: S/E CENTRAL CIPRESES 154KV B2 | I92: S/E CENTRAL CIPRESES 154KV | J92: =_xlfn.XLOOKUP(I92,'[2]Barras CMg'!$E$2:$E$1527,'[2]Barras CMg'!$A$2:$A$1527,"------",0,1) -> CIPRESES______154 | K92: 2 | L92: 2025 | M92: Hidroeléctrica | N92: Hidroeléctrica de pasada | O92: Instalaciones de generación | P92: Maule | Q92: Talca | R92: San Clemente | S92: Operativa | T92: 31-07-1963 | U92: 70 | V92: 69.881 | W92: =_xlfn.XLOOKUP(C92,#REF!,#REF!,"S/I",0) -> #REF! | X92: =_xlfn.XLOOKUP($D92,[2]Retiros_dinamica!$F:$F,[2]Retiros_dinamica!B:B,"S/I",0) -> 7639445.9 | Y92: =_xlfn.XLOOKUP($D92,[2]Retiros_dinamica!$F:$F,[2]Retiros_dinamica!C:C,"S/I",0) -> 9104617.6 | Z92: =_xlfn.XLOOKUP($D92,[2]Retiros_dinamica!$F:$F,[2]Retiros_dinamica!D:D,"S/I",0) -> 4255877.2 | AA92: =_xlfn.XLOOKUP($D92,[2]Retiros_dinamica!$F:$F,[2]Retiros_dinamica!E:E,"S/I",0) -> 20999941 | AB92: =_xlfn.XLOOKUP(C92,[2]CMg!$I$4:$I$106,[2]CMg!$M$4:$M$106,"----",0,1) -> ---- | AC92: =_xlfn.XLOOKUP(C92,[2]CMg!$A$4:$A$106,[2]CMg!$B$4:$B$106,"----",0,1) -> ---- | AD92: =_xlfn.XLOOKUP(C92,'[3]Promedio solar Cmg'!$A$4:$A$106,'[3]Promedio solar Cmg'!$B$4:$B$106,"----",0,1) -> ---- | AH92: =_xlfn.XLOOKUP($E92,'[2]Balance económico'!$C:$C,'[2]Balance económico'!$D:$D,"-",0) -> -5.15558e+11 | AI92: =_xlfn.XLOOKUP($E92,'[2]Balance económico'!$C:$C,'[2]Balance económico'!$E:$E,"-",0) -> -1.8754195e+11 | AJ92: =_xlfn.XLOOKUP($E92,'[2]Balance económico'!$C:$C,'[2]Balance económico'!$F:$F,"-",0) -> 7.2834825e+10 | AK92: =IF(AA92>0,"PPA","-") -> PPA | AL92: {=IFERROR((X92*[2]!Tabla2[Bloque A] + 'BD Centrales 2025'!Y57*[2]!Tabla2[Bloque B] + 'BD Centrales 2025'!Z57*[2]!Tabla2[Bloque C])*#REF!,"-")} -> - | AM92: =IFERROR(AH92+AL92,"-") -> - | AN92: =IFERROR((AH92+AI92+AJ92)/(SUMIFS($W$2:$W$1194,$E$2:$E$1194,E92)*1000*#REF!),0) -> 0
A93: 124 | B93: CE10G0021 | C93: HP LOS MOLLES | D93: ENEL GENERACIÓN CHILE S.A. | E93: =_xlfn.XLOOKUP(D93,'[2]Coordinados SEN'!$A:$A,'[2]Coordinados SEN'!$B:$B,"-",0) -> 91.081.000-6 | F93: ENEL GENERACIÓN CHILE S.A. | G93: =COUNTIFS($D$2:$D$1194,D93) -> 21 | H93: S/E LOS MOLLES 66KV B1 | I93: S/E LOS MOLLES 66KV | J93: =_xlfn.XLOOKUP(I93,'[2]Barras CMg'!$E$2:$E$1527,'[2]Barras CMg'!$A$2:$A$1527,"------",0,1) -> MOLLES________066 | K93: 2 | L93: 2025 | M93: Hidroeléctrica | N93: Minihidro de pasada | O93: Instalaciones de generación | P93: Coquimbo | Q93: Limarí | R93: Monte Patria | S93: Operativa | T93: 31-07-1952 | U93: 18 | V93: 17.9514 | W93: =_xlfn.XLOOKUP(C93,#REF!,#REF!,"S/I",0) -> #REF! | X93: =_xlfn.XLOOKUP($D93,[2]Retiros_dinamica!$F:$F,[2]Retiros_dinamica!B:B,"S/I",0) -> 7639445.9 | Y93: =_xlfn.XLOOKUP($D93,[2]Retiros_dinamica!$F:$F,[2]Retiros_dinamica!C:C,"S/I",0) -> 9104617.6 | Z93: =_xlfn.XLOOKUP($D93,[2]Retiros_dinamica!$F:$F,[2]Retiros_dinamica!D:D,"S/I",0) -> 4255877.2 | AA93: =_xlfn.XLOOKUP($D93,[2]Retiros_dinamica!$F:$F,[2]Retiros_dinamica!E:E,"S/I",0) -> 20999941 | AB93: =_xlfn.XLOOKUP(C93,[2]CMg!$I$4:$I$106,[2]CMg!$M$4:$M$106,"----",0,1) -> ---- | AC93: =_xlfn.XLOOKUP(C93,[2]CMg!$A$4:$A$106,[2]CMg!$B$4:$B$106,"----",0,1) -> ---- | AD93: =_xlfn.XLOOKUP(C93,'[3]Promedio solar Cmg'!$A$4:$A$106,'[3]Promedio solar Cmg'!$B$4:$B$106,"----",0,1) -> ---- | AH93: =_xlfn.XLOOKUP($E93,'[2]Balance económico'!$C:$C,'[2]Balance económico'!$D:$D,"-",0) -> -5.15558e+11 | AI93: =_xlfn.XLOOKUP($E93,'[2]Balance económico'!$C:$C,'[2]Balance económico'!$E:$E,"-",0) -> -1.8754195e+11 | AJ93: =_xlfn.XLOOKUP($E93,'[2]Balance económico'!$C:$C,'[2]Balance económico'!$F:$F,"-",0) -> 7.2834825e+10 | AK93: =IF(AA93>0,"PPA","-") -> PPA | AL93: {=IFERROR((X93*[2]!Tabla2[Bloque A] + 'BD Centrales 2025'!Y72*[2]!Tabla2[Bloque B] + 'BD Centrales 2025'!Z72*[2]!Tabla2[Bloque C])*#REF!,"-")} -> - | AM93: =IFERROR(AH93+AL93,"-") -> - | AN93: =IFERROR((AH93+AI93+AJ93)/(SUMIFS($W$2:$W$1194,$E$2:$E$1194,E93)*1000*#REF!),0) -> 0
A94: 125 | B94: CE19G0021 | C94: HP PALMUCHO | D94: ENEL GENERACIÓN CHILE S.A. | E94: =_xlfn.XLOOKUP(D94,'[2]Coordinados SEN'!$A:$A,'[2]Coordinados SEN'!$B:$B,"-",0) -> 91.081.000-6 | F94: ENEL GENERACIÓN CHILE S.A. | G94: =COUNTIFS($D$2:$D$1194,D94) -> 21 | H94: S/E ZONA DE CAIDA 66KV | I94: S/E ZONA DE CAIDA 66KV | J94: =_xlfn.XLOOKUP(I94,'[2]Barras CMg'!$E$2:$E$1527,'[2]Barras CMg'!$A$2:$A$1527,"------",0,1) -> ZONA_CAIDA____066 | K94: 1 | L94: 2025 | M94: Hidroeléctrica | N94: Hidroeléctrica de pasada | O94: Instalaciones de generación | P94: Biobío | Q94: Biobío | R94: Alto Biobío | S94: Operativa | T94: 28-11-2007 | U94: 32 | V94: 31.952 | W94: =_xlfn.XLOOKUP(C94,#REF!,#REF!,"S/I",0) -> #REF! | X94: =_xlfn.XLOOKUP($D94,[2]Retiros_dinamica!$F:$F,[2]Retiros_dinamica!B:B,"S/I",0) -> 7639445.9 | Y94: =_xlfn.XLOOKUP($D94,[2]Retiros_dinamica!$F:$F,[2]Retiros_dinamica!C:C,"S/I",0) -> 9104617.6 | Z94: =_xlfn.XLOOKUP($D94,[2]Retiros_dinamica!$F:$F,[2]Retiros_dinamica!D:D,"S/I",0) -> 4255877.2 | AA94: =_xlfn.XLOOKUP($D94,[2]Retiros_dinamica!$F:$F,[2]Retiros_dinamica!E:E,"S/I",0) -> 20999941 | AB94: =_xlfn.XLOOKUP(C94,[2]CMg!$I$4:$I$106,[2]CMg!$M$4:$M$106,"----",0,1) -> ---- | AC94: =_xlfn.XLOOKUP(C94,[2]CMg!$A$4:$A$106,[2]CMg!$B$4:$B$106,"----",0,1) -> ---- | AD94: =_xlfn.XLOOKUP(C94,'[3]Promedio solar Cmg'!$A$4:$A$106,'[3]Promedio solar Cmg'!$B$4:$B$106,"----",0,1) -> ---- | AH94: =_xlfn.XLOOKUP($E94,'[2]Balance económico'!$C:$C,'[2]Balance económico'!$D:$D,"-",0) -> -5.15558e+11 | AI94: =_xlfn.XLOOKUP($E94,'[2]Balance económico'!$C:$C,'[2]Balance económico'!$E:$E,"-",0) -> -1.8754195e+11 | AJ94: =_xlfn.XLOOKUP($E94,'[2]Balance económico'!$C:$C,'[2]Balance económico'!$F:$F,"-",0) -> 7.2834825e+10 | AK94: =IF(AA94>0,"PPA","-") -> PPA | AL94: {=IFERROR((X94*[2]!Tabla2[Bloque A] + 'BD Centrales 2025'!Y87*[2]!Tabla2[Bloque B] + 'BD Centrales 2025'!Z87*[2]!Tabla2[Bloque C])*#REF!,"-")} -> - | AM94: =IFERROR(AH94+AL94,"-") -> - | AN94: =IFERROR((AH94+AI94+AJ94)/(SUMIFS($W$2:$W$1194,$E$2:$E$1194,E94)*1000*#REF!),0) -> 0
A95: 126 | B95: CE22G0021 | C95: TER QUINTERO | D95: ENEL GENERACIÓN CHILE S.A. | E95: =_xlfn.XLOOKUP(D95,'[2]Coordinados SEN'!$A:$A,'[2]Coordinados SEN'!$B:$B,"-",0) -> 91.081.000-6 | F95: ENEL GENERACIÓN CHILE S.A. | G95: =COUNTIFS($D$2:$D$1194,D95) -> 21 | H95: S/E QUINTERO 220KV | I95: S/E CENTRAL QUINTERO 220KV | J95: =_xlfn.XLOOKUP(I95,'[2]Barras CMg'!$E$2:$E$1527,'[2]Barras CMg'!$A$2:$A$1527,"------",0,1) -> QUINTERO______220 | K95: 2 | L95: 2025 | M95: Termoeléctrica | N95: Termoeléctrica de turbina a gas | O95: Instalaciones de generación | P95: Valparaíso | Q95: Valparaíso | R95: Quintero | S95: Operativa | T95: 22-07-2009 | U95: 240.6021 | V95: 239.0173 | W95: =_xlfn.XLOOKUP(C95,#REF!,#REF!,"S/I",0) -> #REF! | X95: =_xlfn.XLOOKUP($D95,[2]Retiros_dinamica!$F:$F,[2]Retiros_dinamica!B:B,"S/I",0) -> 7639445.9 | Y95: =_xlfn.XLOOKUP($D95,[2]Retiros_dinamica!$F:$F,[2]Retiros_dinamica!C:C,"S/I",0) -> 9104617.6 | Z95: =_xlfn.XLOOKUP($D95,[2]Retiros_dinamica!$F:$F,[2]Retiros_dinamica!D:D,"S/I",0) -> 4255877.2 | AA95: =_xlfn.XLOOKUP($D95,[2]Retiros_dinamica!$F:$F,[2]Retiros_dinamica!E:E,"S/I",0) -> 20999941 | AB95: =_xlfn.XLOOKUP(C95,[2]CMg!$I$4:$I$106,[2]CMg!$M$4:$M$106,"----",0,1) -> ---- | AH95: =_xlfn.XLOOKUP($E95,'[2]Balance económico'!$C:$C,'[2]Balance económico'!$D:$D,"-",0) -> -5.15558e+11 | AI95: =_xlfn.XLOOKUP($E95,'[2]Balance económico'!$C:$C,'[2]Balance económico'!$E:$E,"-",0) -> -1.8754195e+11 | AJ95: =_xlfn.XLOOKUP($E95,'[2]Balance económico'!$C:$C,'[2]Balance económico'!$F:$F,"-",0) -> 7.2834825e+10 | AK95: =IF(AA95>0,"PPA","-") -> PPA | AL95: {=IFERROR((X95*[2]!Tabla2[Bloque A] + 'BD Centrales 2025'!Y1163*[2]!Tabla2[Bloque B] + 'BD Centrales 2025'!Z1163*[2]!Tabla2[Bloque C])*#REF!,"-")} -> - | AM95: =IFERROR(AH95+AL95,"-") -> - | AN95: =IFERROR((AH95+AI95+AJ95)/(SUMIFS($W$2:$W$1194,$E$2:$E$1194,E95)*1000*#REF!),0) -> 0
A96: 127 | B96: CE11G0021 | C96: HE RALCO | D96: ENEL GENERACIÓN CHILE S.A. | E96: =_xlfn.XLOOKUP(D96,'[2]Coordinados SEN'!$A:$A,'[2]Coordinados SEN'!$B:$B,"-",0) -> 91.081.000-6 | F96: ENEL GENERACIÓN CHILE S.A. | G96: =COUNTIFS($D$2:$D$1194,D96) -> 21 | H96: S/E CENTRAL RALCO 220KV | I96: S/E CENTRAL RALCO 220KV | J96: =_xlfn.XLOOKUP(I96,'[2]Barras CMg'!$E$2:$E$1527,'[2]Barras CMg'!$A$2:$A$1527,"------",0,1) -> RALCO_________220 | K96: 2 | L96: 2025 | M96: Hidroeléctrica | N96: Hidroeléctrica de embalse | O96: Instalaciones de generación | P96: Biobío | Q96: Biobío | R96: Alto Biobío | S96: Operativa | T96: 06-09-2004 | U96: 690.12 | V96: 685.06 | W96: =_xlfn.XLOOKUP(C96,#REF!,#REF!,"S/I",0) -> #REF! | X96: =_xlfn.XLOOKUP($D96,[2]Retiros_dinamica!$F:$F,[2]Retiros_dinamica!B:B,"S/I",0) -> 7639445.9 | Y96: =_xlfn.XLOOKUP($D96,[2]Retiros_dinamica!$F:$F,[2]Retiros_dinamica!C:C,"S/I",0) -> 9104617.6 | Z96: =_xlfn.XLOOKUP($D96,[2]Retiros_dinamica!$F:$F,[2]Retiros_dinamica!D:D,"S/I",0) -> 4255877.2 | AA96: =_xlfn.XLOOKUP($D96,[2]Retiros_dinamica!$F:$F,[2]Retiros_dinamica!E:E,"S/I",0) -> 20999941 | AB96: =_xlfn.XLOOKUP(C96,[2]CMg!$I$4:$I$106,[2]CMg!$M$4:$M$106,"----",0,1) -> ---- | AC96: =_xlfn.XLOOKUP(C96,[2]CMg!$A$4:$A$106,[2]CMg!$B$4:$B$106,"----",0,1) -> ---- | AD96: =_xlfn.XLOOKUP(C96,'[3]Promedio solar Cmg'!$A$4:$A$106,'[3]Promedio solar Cmg'!$B$4:$B$106,"----",0,1) -> ---- | AH96: =_xlfn.XLOOKUP($E96,'[2]Balance económico'!$C:$C,'[2]Balance económico'!$D:$D,"-",0) -> -5.15558e+11 | AI96: =_xlfn.XLOOKUP($E96,'[2]Balance económico'!$C:$C,'[2]Balance económico'!$E:$E,"-",0) -> -1.8754195e+11 | AJ96: =_xlfn.XLOOKUP($E96,'[2]Balance económico'!$C:$C,'[2]Balance económico'!$F:$F,"-",0) -> 7.2834825e+10 | AK96: =IF(AA96>0,"PPA","-") -> PPA | AL96: {=IFERROR((X96*[2]!Tabla2[Bloque A] + 'BD Centrales 2025'!Y15*[2]!Tabla2[Bloque B] + 'BD Centrales 2025'!Z15*[2]!Tabla2[Bloque C])*#REF!,"-")} -> - | AM96: =IFERROR(AH96+AL96,"-") -> - | AN96: =IFERROR((AH96+AI96+AJ96)/(SUMIFS($W$2:$W$1194,$E$2:$E$1194,E96)*1000*#REF!),0) -> 0
A97: 128 | B97: CE12G0021 | C97: HE RAPEL | D97: ENEL GENERACIÓN CHILE S.A. | E97: =_xlfn.XLOOKUP(D97,'[2]Coordinados SEN'!$A:$A,'[2]Coordinados SEN'!$B:$B,"-",0) -> 91.081.000-6 | F97: ENEL GENERACIÓN CHILE S.A. | G97: =COUNTIFS($D$2:$D$1194,D97) -> 21 | H97: S/E RAPEL 220KV B1 | I97: S/E RAPEL 220KV | J97: =_xlfn.XLOOKUP(I97,'[2]Barras CMg'!$E$2:$E$1527,'[2]Barras CMg'!$A$2:$A$1527,"------",0,1) -> RAPEL_________220 | K97: 5 | L97: 2025 | M97: Hidroeléctrica | N97: Hidroeléctrica de embalse | O97: Instalaciones de generación | P97: Libertador General Bernardo O'Higgins | Q97: Cardenal Caro | R97: Litueche | S97: Operativa | T97: 31-07-1968 | U97: 363.8066 | V97: 361.9847 | W97: =_xlfn.XLOOKUP(C97,#REF!,#REF!,"S/I",0) -> #REF! | X97: =_xlfn.XLOOKUP($D97,[2]Retiros_dinamica!$F:$F,[2]Retiros_dinamica!B:B,"S/I",0) -> 7639445.9 | Y97: =_xlfn.XLOOKUP($D97,[2]Retiros_dinamica!$F:$F,[2]Retiros_dinamica!C:C,"S/I",0) -> 9104617.6 | Z97: =_xlfn.XLOOKUP($D97,[2]Retiros_dinamica!$F:$F,[2]Retiros_dinamica!D:D,"S/I",0) -> 4255877.2 | AA97: =_xlfn.XLOOKUP($D97,[2]Retiros_dinamica!$F:$F,[2]Retiros_dinamica!E:E,"S/I",0) -> 20999941 | AB97: =_xlfn.XLOOKUP(C97,[2]CMg!$I$4:$I$106,[2]CMg!$M$4:$M$106,"----",0,1) -> ---- | AC97: =_xlfn.XLOOKUP(C97,[2]CMg!$A$4:$A$106,[2]CMg!$B$4:$B$106,"----",0,1) -> ---- | AD97: =_xlfn.XLOOKUP(C97,'[3]Promedio solar Cmg'!$A$4:$A$106,'[3]Promedio solar Cmg'!$B$4:$B$106,"----",0,1) -> ---- | AH97: =_xlfn.XLOOKUP($E97,'[2]Balance económico'!$C:$C,'[2]Balance económico'!$D:$D,"-",0) -> -5.15558e+11 | AI97: =_xlfn.XLOOKUP($E97,'[2]Balance económico'!$C:$C,'[2]Balance económico'!$E:$E,"-",0) -> -1.8754195e+11 | AJ97: =_xlfn.XLOOKUP($E97,'[2]Balance económico'!$C:$C,'[2]Balance económico'!$F:$F,"-",0) -> 7.2834825e+10 | AK97: =IF(AA97>0,"PPA","-") -> PPA | AL97: {=IFERROR((X97*[2]!Tabla2[Bloque A] + 'BD Centrales 2025'!Y16*[2]!Tabla2[Bloque B] + 'BD Centrales 2025'!Z16*[2]!Tabla2[Bloque C])*#REF!,"-")} -> - | AM97: =IFERROR(AH97+AL97,"-") -> - | AN97: =IFERROR((AH97+AI97+AJ97)/(SUMIFS($W$2:$W$1194,$E$2:$E$1194,E97)*1000*#REF!),0) -> 0
A98: 131 | B98: CE13G0021 | C98: HP SAUZAL | D98: ENEL GENERACIÓN CHILE S.A. | E98: =_xlfn.XLOOKUP(D98,'[2]Coordinados SEN'!$A:$A,'[2]Coordinados SEN'!$B:$B,"-",0) -> 91.081.000-6 | F98: ENEL GENERACIÓN CHILE S.A. | G98: =COUNTIFS($D$2:$D$1194,D98) -> 21 | H98: S/E SAUZAL 110KV | I98: S/E SAUZAL 110KV | J98: =_xlfn.XLOOKUP(I98,'[2]Barras CMg'!$E$2:$E$1527,'[2]Barras CMg'!$A$2:$A$1527,"------",0,1) -> SAUZAL1_______110 | K98: 3 | L98: 2025 | M98: Hidroeléctrica | N98: Hidroeléctrica de pasada | O98: Instalaciones de generación | P98: Libertador General Bernardo O'Higgins | Q98: Cachapoal | R98: Machalí | S98: Operativa | T98: 31-07-1948 | U98: 83.1078 | V98: 82.6261 | W98: =_xlfn.XLOOKUP(C98,#REF!,#REF!,"S/I",0) -> #REF! | X98: =_xlfn.XLOOKUP($D98,[2]Retiros_dinamica!$F:$F,[2]Retiros_dinamica!B:B,"S/I",0) -> 7639445.9 | Y98: =_xlfn.XLOOKUP($D98,[2]Retiros_dinamica!$F:$F,[2]Retiros_dinamica!C:C,"S/I",0) -> 9104617.6 | Z98: =_xlfn.XLOOKUP($D98,[2]Retiros_dinamica!$F:$F,[2]Retiros_dinamica!D:D,"S/I",0) -> 4255877.2 | AA98: =_xlfn.XLOOKUP($D98,[2]Retiros_dinamica!$F:$F,[2]Retiros_dinamica!E:E,"S/I",0) -> 20999941 | AB98: =_xlfn.XLOOKUP(C98,[2]CMg!$I$4:$I$106,[2]CMg!$M$4:$M$106,"----",0,1) -> ---- | AC98: =_xlfn.XLOOKUP(C98,[2]CMg!$A$4:$A$106,[2]CMg!$B$4:$B$106,"----",0,1) -> ---- | AD98: =_xlfn.XLOOKUP(C98,'[3]Promedio solar Cmg'!$A$4:$A$106,'[3]Promedio solar Cmg'!$B$4:$B$106,"----",0,1) -> ---- | AH98: =_xlfn.XLOOKUP($E98,'[2]Balance económico'!$C:$C,'[2]Balance económico'!$D:$D,"-",0) -> -5.15558e+11 | AI98: =_xlfn.XLOOKUP($E98,'[2]Balance económico'!$C:$C,'[2]Balance económico'!$E:$E,"-",0) -> -1.8754195e+11 | AJ98: =_xlfn.XLOOKUP($E98,'[2]Balance económico'!$C:$C,'[2]Balance económico'!$F:$F,"-",0) -> 7.2834825e+10 | AK98: =IF(AA98>0,"PPA","-") -> PPA | AL98: {=IFERROR((X98*[2]!Tabla2[Bloque A] + 'BD Centrales 2025'!Y497*[2]!Tabla2[Bloque B] + 'BD Centrales 2025'!Z497*[2]!Tabla2[Bloque C])*#REF!,"-")} -> - | AM98: =IFERROR(AH98+AL98,"-") -> - | AN98: =IFERROR((AH98+AI98+AJ98)/(SUMIFS($W$2:$W$1194,$E$2:$E$1194,E98)*1000*#REF!),0) -> 0
A99: 132 | B99: CE15G0021 | C99: HP SAUZALITO | D99: ENEL GENERACIÓN CHILE S.A. | E99: =_xlfn.XLOOKUP(D99,'[2]Coordinados SEN'!$A:$A,'[2]Coordinados SEN'!$B:$B,"-",0) -> 91.081.000-6 | F99: ENEL GENERACIÓN CHILE S.A. | G99: =COUNTIFS($D$2:$D$1194,D99) -> 21 | H99: S/E SAUZAL 110KV | I99: S/E SAUZAL 110KV | J99: =_xlfn.XLOOKUP(I99,'[2]Barras CMg'!$E$2:$E$1527,'[2]Barras CMg'!$A$2:$A$1527,"------",0,1) -> SAUZAL1_______110 | K99: 1 | L99: 2025 | M99: Hidroeléctrica | N99: Minihidro de pasada | O99: Instalaciones de generación | P99: Libertador General Bernardo O'Higgins | Q99: Cachapoal | R99: Machalí | S99: Operativa | T99: 31-07-1959 | U99: 11.3115 | V99: 11.2221 | W99: =_xlfn.XLOOKUP(C99,#REF!,#REF!,"S/I",0) -> #REF! | X99: =_xlfn.XLOOKUP($D99,[2]Retiros_dinamica!$F:$F,[2]Retiros_dinamica!B:B,"S/I",0) -> 7639445.9 | Y99: =_xlfn.XLOOKUP($D99,[2]Retiros_dinamica!$F:$F,[2]Retiros_dinamica!C:C,"S/I",0) -> 9104617.6 | Z99: =_xlfn.XLOOKUP($D99,[2]Retiros_dinamica!$F:$F,[2]Retiros_dinamica!D:D,"S/I",0) -> 4255877.2 | AA99: =_xlfn.XLOOKUP($D99,[2]Retiros_dinamica!$F:$F,[2]Retiros_dinamica!E:E,"S/I",0) -> 20999941 | AB99: =_xlfn.XLOOKUP(C99,[2]CMg!$I$4:$I$106,[2]CMg!$M$4:$M$106,"----",0,1) -> ---- | AC99: =_xlfn.XLOOKUP(C99,[2]CMg!$A$4:$A$106,[2]CMg!$B$4:$B$106,"----",0,1) -> ---- | AD99: =_xlfn.XLOOKUP(C99,'[3]Promedio solar Cmg'!$A$4:$A$106,'[3]Promedio solar Cmg'!$B$4:$B$106,"----",0,1) -> ---- | AH99: =_xlfn.XLOOKUP($E99,'[2]Balance económico'!$C:$C,'[2]Balance económico'!$D:$D,"-",0) -> -5.15558e+11 | AI99: =_xlfn.XLOOKUP($E99,'[2]Balance económico'!$C:$C,'[2]Balance económico'!$E:$E,"-",0) -> -1.8754195e+11 | AJ99: =_xlfn.XLOOKUP($E99,'[2]Balance económico'!$C:$C,'[2]Balance económico'!$F:$F,"-",0) -> 7.2834825e+10 | AK99: =IF(AA99>0,"PPA","-") -> PPA | AL99: {=IFERROR((X99*[2]!Tabla2[Bloque A] + 'BD Centrales 2025'!Y498*[2]!Tabla2[Bloque B] + 'BD Centrales 2025'!Z498*[2]!Tabla2[Bloque C])*#REF!,"-")} -> - | AM99: =IFERROR(AH99+AL99,"-") -> - | AN99: =IFERROR((AH99+AI99+AJ99)/(SUMIFS($W$2:$W$1194,$E$2:$E$1194,E99)*1000*#REF!),0) -> 0
A100: 133 | B100: CE14G0021 | C100: TER TALTAL | D100: ENEL GENERACIÓN CHILE S.A. | E100: =_xlfn.XLOOKUP(D100,'[2]Coordinados SEN'!$A:$A,'[2]Coordinados SEN'!$B:$B,"-",0) -> 91.081.000-6 | F100: ENEL GENERACIÓN CHILE S.A. | G100: =COUNTIFS($D$2:$D$1194,D100) -> 21 | H100: S/E PAPOSO 220 KV B1 | I100: S/E PAPOSO 220KV | J100: =_xlfn.XLOOKUP(I100,'[2]Barras CMg'!$E$2:$E$1527,'[2]Barras CMg'!$A$2:$A$1527,"------",0,1) -> PAPOSO________220 | K100: 2 | L100: 2025 | M100: Termoeléctrica | N100: Termoeléctrica de turbina a gas | O100: Instalaciones de generación | P100: Antofagasta | Q100: Antofagasta | R100: Taltal | S100: Operativa | T100: 31-07-2000 | U100: 238,8497 (GNL) / 242,3773 (DIESEL) | V100: 238,0084 (GNL) / 241,3456 (DIESEL) | W100: =_xlfn.XLOOKUP(C100,#REF!,#REF!,"S/I",0) -> #REF! | X100: =_xlfn.XLOOKUP($D100,[2]Retiros_dinamica!$F:$F,[2]Retiros_dinamica!B:B,"S/I",0) -> 7639445.9 | Y100: =_xlfn.XLOOKUP($D100,[2]Retiros_dinamica!$F:$F,[2]Retiros_dinamica!C:C,"S/I",0) -> 9104617.6 | Z100: =_xlfn.XLOOKUP($D100,[2]Retiros_dinamica!$F:$F,[2]Retiros_dinamica!D:D,"S/I",0) -> 4255877.2 | AA100: =_xlfn.XLOOKUP($D100,[2]Retiros_dinamica!$F:$F,[2]Retiros_dinamica!E:E,"S/I",0) -> 20999941 | AB100: =_xlfn.XLOOKUP(C100,[2]CMg!$I$4:$I$106,[2]CMg!$M$4:$M$106,"----",0,1) -> ---- | AH100: =_xlfn.XLOOKUP($E100,'[2]Balance económico'!$C:$C,'[2]Balance económico'!$D:$D,"-",0) -> -5.15558e+11 | AI100: =_xlfn.XLOOKUP($E100,'[2]Balance económico'!$C:$C,'[2]Balance económico'!$E:$E,"-",0) -> -1.8754195e+11 | AJ100: =_xlfn.XLOOKUP($E100,'[2]Balance económico'!$C:$C,'[2]Balance económico'!$F:$F,"-",0) -> 7.2834825e+10 | AK100: =IF(AA100>0,"PPA","-") -> PPA | AL100: {=IFERROR((X100*[2]!Tabla2[Bloque A] + 'BD Centrales 2025'!Y1178*[2]!Tabla2[Bloque B] + 'BD Centrales 2025'!Z1178*[2]!Tabla2[Bloque C])*#REF!,"-")} -> - | AM100: =IFERROR(AH100+AL100,"-") -> - | AN100: =IFERROR((AH100+AI100+AJ100)/(SUMIFS($W$2:$W$1194,$E$2:$E$1194,E100)*1000*#REF!),0) -> 0
...

Sheet BD Centrales 2024
A1: ID Central infotécnica | B1: Nemotécnico Central Infotécnica | C1: Rut | D1: Nombre Central Infotécnica | E1: Coordinado | F1: Propietario | G1: POI | H1: Cantidad de unidades | I1: Año | J1: Tipo de central | K1: Tipo tecnología | L1: Medio de generación | M1: Región | N1: Provincia | O1: Comuna | P1: Estado | Q1: Fecha EO | R1: Potencia máxima bruta Central [MW] | S1: Consumos propios Central Infotécnica [%] | T1: Potencia máxima neta Central [MW] | U1: Potencia mínimo técnico Central [MW] | V1: Inyección energía [GWh] | W1: Retiros energía [GWh] | X1: Vertimientos [GWh] | Y1: Vertimientos [%] | Z1: CMg precio captura | AA1: CMg promedio horario | AB1: CMg promedio solar | AC1: CMg promedio noche | AD1: Porcentaje iny. costo cero | AE1: Ingresos energía | AF1: Pagos laterales | AG1: Potencia máxima verificada [MW] | AH1: EO disponibles | AI1: EO deteriorados | AJ1: EO deteriorado % | AK1: FP 2020 | AL1: FP 2021 | AM1: FP 2022 | AN1: FP 2023 | AO1: FP 2024 | AP1: FP 2025 | AQ1: Potencia Inicial | AR1: PEQ [MW] | AS1: IFOR representativo Central | AT1: FMM representativo Central | AU1: FMMM x (1-IFOR) | AV1: CCPP | AW1: PSUF pre | AX1: PSUF def | AY1: Ingresos PSUF
A2: 19 | B2: CE01G0053 | D2: PE LEBU | E2: PARQUE EÓLICO LEBU-TORO SPA | F2: PARQUE EÓLICO LEBU-TORO SPA | G2: S/E LEBU 66 KV | H2: 9 | I2: 2024 | J2: Eólica | K2: Parque eólico | L2: Pequeños medio de generación o PMG | M2: Biobío | N2: Arauco | O2: Lebu | P2: Operativa – Autodespacho DS88 | Q2: 25-03-2014 | R2: 10.045 | S2: 7.018 | T2: 9.34 | U2: Sin información | V2: =_xlfn.XLOOKUP(D2,'[4]Gen. Real'!$A$2:$A$1168,'[4]Gen. Real'!$C$2:$C$1168,"-",0) -> 3.6374 | X2: =_xlfn.XLOOKUP(D2,[4]Vertimiento!$J$2:$J$119,[4]Vertimiento!$K$2:$K$119,"-",0) -> - | Y2: =IFERROR(X2/(V2+X2),"-") -> - | Z2: =_xlfn.XLOOKUP(D2,[4]Cmg!$I$4:$I$99,[4]Cmg!$M$4:$M$99,"----",0,1) -> ---- | AA2: =_xlfn.XLOOKUP(D2,[4]Cmg!$A$4:$A$101,[4]Cmg!$B$4:$B$101,"----",0,1) -> ---- | AB2: =_xlfn.XLOOKUP(D2,[4]Cmg!$E$4:$E$101,[4]Cmg!$F$4:$F$101,"----",0,1) -> ---- | AC2: =_xlfn.XLOOKUP(D2,[4]Cmg!$O$4:$O$101,[4]Cmg!$P$4:$P$101,"----",0,1) -> ---- | AD2: =_xlfn.XLOOKUP(D2,[4]Cmg!$S$4:$S$101,[4]Cmg!$U$4:$U$101,"----",0,1) -> ---- | AG2: =IFERROR(SUMIFS('[4]BD Unidades'!$AH:$AH,'[4]BD Unidades'!$A:$A,'BD Centrales 2024'!$A2),"-") -> 10.045 | AH2: =SUMIFS('[4]BD Unidades'!$AJ$3:$AJ$1424,'[4]BD Unidades'!$A$3:$A$1424,$A2) -> 8641.7333 | AI2: =SUMIFS('[4]BD Unidades'!$AL$3:$AL$1424,'[4]BD Unidades'!$A$3:$A$1424,$A2) -> 12.5 | AJ2: =IFERROR(AI2/(AH2+AI2),"-") -> 0.0014443798 | AK2: =IFERROR(SUMIFS('[4]BD Unidades'!$AO$3:$AO$1424,'[4]BD Unidades'!$A$3:$A$1424,$A2),"-") -> 0.25948928 | AL2: =IFERROR(SUMIFS('[4]BD Unidades'!$AQ$3:$AQ$1424,'[4]BD Unidades'!$A$3:$A$1424,$A2),"-") -> 0.18240497 | AM2: =IFERROR(SUMIFS('[4]BD Unidades'!$AS$3:$AS$1424,'[4]BD Unidades'!$A$3:$A$1424,$A2),"-") -> 0.13282963 | AN2: =IFERROR(SUMIFS('[4]BD Unidades'!$AU$3:$AU$1424,'[4]BD Unidades'!$A$3:$A$1424,$A2),"-") -> 0.063216 | AO2: =IFERROR(SUMIFS('[4]BD Unidades'!$AW$3:$AW$1424,'[4]BD Unidades'!$A$3:$A$1424,$A2),"-") -> 0.04162 | AP2: =IFERROR(SUMIFS('[4]BD Unidades'!$AY$3:$AY$1424,'[4]BD Unidades'!$A$3:$A$1424,$A2),"-") -> 0.039152 | AQ2: =IFERROR(SUMIFS('[4]BD Unidades'!$AZ$3:$AZ$1424,'[4]BD Unidades'!$A$3:$A$1424,$A2),"-") -> 0.39329189 | AR2: =IFERROR(SUMIFS('[4]BD Unidades'!$BA$3:$BA$1424,'[4]BD Unidades'!$A$3:$A$1424,$A2),"-") -> 10.031072 | AS2: =SUMIFS('[4]BD Unidades'!$BC$3:$BC$1424,'[4]BD Unidades'!$A$3:$A$1424,$A2) -> 0.004960304 | AT2: =SUMIFS('[4]BD Unidades'!$BE$3:$BE$1424,'[4]BD Unidades'!$A$3:$A$1424,$A2) -> 1 | AU2: =IFERROR(AT2*(1-AS2),"-") -> 0.9950397 | AV2: =IFERROR(S2/100,"-") -> 0.07018 | AW2: =IFERROR(SUMIFS('[4]BD Unidades'!$BI$3:$BI$1424,'[4]BD Unidades'!$A$3:$A$1424,$A2),"-") -> 0.36637348 | AX2: =IFERROR(SUMIFS('[4]BD Unidades'!$BJ$3:$BJ$1424,'[4]BD Unidades'!$A$3:$A$1424,$A2),"-") -> 0.23544733
A3: 83 | B3: CE25G0021 | D3: PE CANELA II | E3: ENEL GENERACIÓN CHILE S.A. | F3: ENEL GENERACIÓN CHILE S.A. | G3: S/E LAS PALMAS 220KV BA-A | H3: 40 | I3: 2024 | J3: Eólica | K3: Parque eólico | L3: Instalaciones de generación | M3: Coquimbo | N3: Choapa | O3: Canela | P3: Operativa | Q3: 11-12-2009 | R3: 60 | S3: 1 | T3: 59.4 | U3: 0 | V3: =_xlfn.XLOOKUP(D3,'[4]Gen. Real'!$A$2:$A$1168,'[4]Gen. Real'!$C$2:$C$1168,"-",0) -> 104.17678 | X3: =_xlfn.XLOOKUP(D3,[4]Vertimiento!$J$2:$J$119,[4]Vertimiento!$K$2:$K$119,"-",0) -> 18.366595 | Y3: =IFERROR(X3/(V3+X3),"-") -> 0.14987832 | Z3: =_xlfn.XLOOKUP(D3,[4]Cmg!$I$4:$I$99,[4]Cmg!$M$4:$M$99,"----",0,1) -> ---- | AA3: =_xlfn.XLOOKUP(D3,[4]Cmg!$A$4:$A$101,[4]Cmg!$B$4:$B$101,"----",0,1) -> ---- | AB3: =_xlfn.XLOOKUP(D3,[4]Cmg!$E$4:$E$101,[4]Cmg!$F$4:$F$101,"----",0,1) -> ---- | AC3: =_xlfn.XLOOKUP(D3,[4]Cmg!$O$4:$O$101,[4]Cmg!$P$4:$P$101,"----",0,1) -> ---- | AD3: =_xlfn.XLOOKUP(D3,[4]Cmg!$S$4:$S$101,[4]Cmg!$U$4:$U$101,"----",0,1) -> ---- | AG3: =IFERROR(SUMIFS('[4]BD Unidades'!$AH:$AH,'[4]BD Unidades'!$A:$A,'BD Centrales 2024'!$A3),"-") -> 60 | AH3: =SUMIFS('[4]BD Unidades'!$AJ$3:$AJ$1424,'[4]BD Unidades'!$A$3:$A$1424,$A3) -> 6272.6333 | AI3: =SUMIFS('[4]BD Unidades'!$AL$3:$AL$1424,'[4]BD Unidades'!$A$3:$A$1424,$A3) -> 2476.1 | AJ3: =IFERROR(AI3/(AH3+AI3),"-") -> 0.28302383 | AK3: =IFERROR(SUMIFS('[4]BD Unidades'!$AO$3:$AO$1424,'[4]BD Unidades'!$A$3:$A$1424,$A3),"-") -> 0.22871273 | AL3: =IFERROR(SUMIFS('[4]BD Unidades'!$AQ$3:$AQ$1424,'[4]BD Unidades'!$A$3:$A$1424,$A3),"-") -> 0.20608864 | AM3: =IFERROR(SUMIFS('[4]BD Unidades'!$AS$3:$AS$1424,'[4]BD Unidades'!$A$3:$A$1424,$A3),"-") -> 0.2385467 | AN3: =IFERROR(SUMIFS('[4]BD Unidades'!$AU$3:$AU$1424,'[4]BD Unidades'!$A$3:$A$1424,$A3),"-") -> 0.224005 | AO3: =IFERROR(SUMIFS('[4]BD Unidades'!$AW$3:$AW$1424,'[4]BD Unidades'!$A$3:$A$1424,$A3),"-") -> 0.233674 | AP3: =IFERROR(SUMIFS('[4]BD Unidades'!$AY$3:$AY$1424,'[4]BD Unidades'!$A$3:$A$1424,$A3),"-") -> 0.205643 | AQ3: =IFERROR(SUMIFS('[4]BD Unidades'!$AZ$3:$AZ$1424,'[4]BD Unidades'!$A$3:$A$1424,$A3),"-") -> 8.1135 | AR3: =IFERROR(SUMIFS('[4]BD Unidades'!$BA$3:$BA$1424,'[4]BD Unidades'!$A$3:$A$1424,$A3),"-") -> 59.923941 | AS3: =SUMIFS('[4]BD Unidades'!$BC$3:$BC$1424,'[4]BD Unidades'!$A$3:$A$1424,$A3) -> 0.00035159819 | AT3: =SUMIFS('[4]BD Unidades'!$BE$3:$BE$1424,'[4]BD Unidades'!$A$3:$A$1424,$A3) -> 0.99781041 | AU3: =IFERROR(AT3*(1-AS3),"-") -> 0.99745958 | AV3: =IFERROR(S3/100,"-") -> 0.01 | AW3: =IFERROR(SUMIFS('[4]BD Unidades'!$BI$3:$BI$1424,'[4]BD Unidades'!$A$3:$A$1424,$A3),"-") -> 8.0119595 | AX3: =IFERROR(SUMIFS('[4]BD Unidades'!$BJ$3:$BJ$1424,'[4]BD Unidades'!$A$3:$A$1424,$A3),"-") -> 5.1488293
A4: 118 | B4: CE20G0021 | D4: PE CANELA | E4: ENEL GENERACIÓN CHILE S.A. | F4: ENEL GENERACIÓN CHILE S.A. | G4: S/E LAS PALMAS 220KV BA-B | H4: 11 | I4: 2024 | J4: Eólica | K4: Parque eólico | L4: Instalaciones de generación | M4: Coquimbo | N4: Choapa | O4: Canela | P4: Operativa | Q4: 27-12-2007 | R4: 18.15 | S4: 1 | T4: 17.9685 | U4: 0 | V4: =_xlfn.XLOOKUP(D4,'[4]Gen. Real'!$A$2:$A$1168,'[4]Gen. Real'!$C$2:$C$1168,"-",0) -> 27.75816 | X4: =_xlfn.XLOOKUP(D4,[4]Vertimiento!$J$2:$J$119,[4]Vertimiento!$K$2:$K$119,"-",0) -> 2.363384 | Y4: =IFERROR(X4/(V4+X4),"-") -> 0.078461582 | Z4: =_xlfn.XLOOKUP(D4,[4]Cmg!$I$4:$I$99,[4]Cmg!$M$4:$M$99,"----",0,1) -> ---- | AA4: =_xlfn.XLOOKUP(D4,[4]Cmg!$A$4:$A$101,[4]Cmg!$B$4:$B$101,"----",0,1) -> ---- | AB4: =_xlfn.XLOOKUP(D4,[4]Cmg!$E$4:$E$101,[4]Cmg!$F$4:$F$101,"----",0,1) -> ---- | AC4: =_xlfn.XLOOKUP(D4,[4]Cmg!$O$4:$O$101,[4]Cmg!$P$4:$P$101,"----",0,1) -> ---- | AD4: =_xlfn.XLOOKUP(D4,[4]Cmg!$S$4:$S$101,[4]Cmg!$U$4:$U$101,"----",0,1) -> ---- | AG4: =IFERROR(SUMIFS('[4]BD Unidades'!$AH:$AH,'[4]BD Unidades'!$A:$A,'BD Centrales 2024'!$A4),"-") -> 18.15 | AH4: =SUMIFS('[4]BD Unidades'!$AJ$3:$AJ$1424,'[4]BD Unidades'!$A$3:$A$1424,$A4) -> 8652.85 | AI4: =SUMIFS('[4]BD Unidades'!$AL$3:$AL$1424,'[4]BD Unidades'!$A$3:$A$1424,$A4) -> 96.316667 | AJ4: =IFERROR(AI4/(AH4+AI4),"-") -> 0.011008667 | AK4: =IFERROR(SUMIFS('[4]BD Unidades'!$AO$3:$AO$1424,'[4]BD Unidades'!$A$3:$A$1424,$A4),"-") -> 0.16088189 | AL4: =IFERROR(SUMIFS('[4]BD Unidades'!$AQ$3:$AQ$1424,'[4]BD Unidades'!$A$3:$A$1424,$A4),"-") -> 0.14717698 | AM4: =IFERROR(SUMIFS('[4]BD Unidades'!$AS$3:$AS$1424,'[4]BD Unidades'!$A$3:$A$1424,$A4),"-") -> 0.18270701 | AN4: =IFERROR(SUMIFS('[4]BD Unidades'!$AU$3:$AU$1424,'[4]BD Unidades'!$A$3:$A$1424,$A4),"-") -> 0.168075 | AO4: =IFERROR(SUMIFS('[4]BD Unidades'!$AW$3:$AW$1424,'[4]BD Unidades'!$A$3:$A$1424,$A4),"-") -> 0.189715 | AP4: =IFERROR(SUMIFS('[4]BD Unidades'!$AY$3:$AY$1424,'[4]BD Unidades'!$A$3:$A$1424,$A4),"-") -> 0.153567 | AQ4: =IFERROR(SUMIFS('[4]BD Unidades'!$AZ$3:$AZ$1424,'[4]BD Unidades'!$A$3:$A$1424,$A4),"-") -> 2.4447143 | AR4: =IFERROR(SUMIFS('[4]BD Unidades'!$BA$3:$BA$1424,'[4]BD Unidades'!$A$3:$A$1424,$A4),"-") -> 18.135479 | AS4: =SUMIFS('[4]BD Unidades'!$BC$3:$BC$1424,'[4]BD Unidades'!$A$3:$A$1424,$A4) -> 0.0012216499 | AT4: =SUMIFS('[4]BD Unidades'!$BE$3:$BE$1424,'[4]BD Unidades'!$A$3:$A$1424,$A4) -> 0.99741576 | AU4: =IFERROR(AT4*(1-AS4),"-") -> 0.99619726 | AV4: =IFERROR(S4/100,"-") -> 0.01 | AW4: =IFERROR(SUMIFS('[4]BD Unidades'!$BI$3:$BI$1424,'[4]BD Unidades'!$A$3:$A$1424,$A4),"-") -> 2.4110635 | AX4: =IFERROR(SUMIFS('[4]BD Unidades'!$BJ$3:$BJ$1424,'[4]BD Unidades'!$A$3:$A$1424,$A4),"-") -> 1.5494529
